Workbook

Sheet MASTER_SHEET
A1: OVERALL SUMMARY | B1: Total Revenue | C1: Total Cost | D1: Overall ROAS | E1: Total Profit | F1: Total Conv | G1: Overall CPA | H1: PAUSE Count | I1: SCALE Count
B2: =SUM(P10:P6109) -> 552176.52 | C2: =SUM(O10:O6109) -> 170173.18 | D2: =IFERROR(B2/C2,0) -> 3.2447917 | E2: =B2-C2 -> 382003.34 | F2: =SUM(N10:N6109) -> 9955 | G2: =IFERROR(C2/F2,0) -> 17.094242 | H2: =COUNTIF(X10:X6109,"PAUSE") -> 2546 | I2: =COUNTIF(X10:X6109,"SCALE") -> 3554
A4: Platform | B4: Total Revenue | C4: Total Cost | D4: ROAS | E4: Conversions
A5: Google Ads | B5: =SUMIF($I$10:$I$6109,"Google Ads",$P$10:$P$6109) -> 190827.89 | C5: =SUMIF($I$10:$I$6109,"Google Ads",$O$10:$O$6109) -> 57593.42 | D5: =IFERROR(B5/C5,0) -> 3.3133627 | E5: =SUMIF($I$10:$I$6109,"Google Ads",$N$10:$N$6109) -> 3411
A6: Facebook Ads | B6: =SUMIF($I$10:$I$6109,"Facebook Ads",$P$10:$P$6109) -> 187088.02 | C6: =SUMIF($I$10:$I$6109,"Facebook Ads",$O$10:$O$6109) -> 57083.8 | D6: =IFERROR(B6/C6,0) -> 3.2774276 | E6: =SUMIF($I$10:$I$6109,"Facebook Ads",$N$10:$N$6109) -> 3381
A7: TikTok Ads | B7: =SUMIF($I$10:$I$6109,"TikTok Ads",$P$10:$P$6109) -> 174260.61 | C7: =SUMIF($I$10:$I$6109,"TikTok Ads",$O$10:$O$6109) -> 55495.96 | D7: =IFERROR(B7/C7,0) -> 3.1400594 | E7: =SUMIF($I$10:$I$6109,"TikTok Ads",$N$10:$N$6109) -> 3163
A9: EMAIL | B9: firstname | C9: lastname | D9: city | E9: state | F9: salary | G9: employer | H9: campaign_name | I9: platform | J9: Date | K9: loan_amount.1 | L9: impressions | M9: clicks | N9: conversions | O9: cost | P9: revenue | Q9: ROAS | R9: Profit | S9: ROI% | T9: CTR | U9: CPC | V9: CPA | W9: Conv% | X9: Status | Y9: Loan_Bucket
A10: brodriguez.hojo@yahoo.com | B10: beverly | C10: rodriguez | D10: Wichita Falls | E10: TX | F10: 6369 | G10: na | H10: Campaign_10 | I10: Google Ads | J10: 2024-01-12 | K10: 700 | L10: 707 | M10: 13 | N10: 0 | O10: 8.01 | P10: 0 | Q10: =IFERROR(P10-O10, 0) -> -8.01 | R10: =P10-O10 -> -8.01 | S10: =R10/O10 -> -1 | T10: 1.84 | U10: 0.62 | V10: 0 | W10: =N10/M10 -> 0 | X10: =IF(P10>=4, "SCALE", IF(P10>=2, "MONITOR", IF(P10>=1, "OPTIMISE", "PAUSE"))) -> PAUSE | Y10: =IF(K10<=300,"Low (100-300)", IF(K10<=500,"Mid (301-500)", IF(K10<=750,"High (501-750)", "Premium (751-1000)"))) -> High (501-750)
A11: mickeymousee2@yahoo.com | B11: debra | C11: johnson | D11: Wilson | E11: NC | F11: 1500 | G11: fred hight | H11: Campaign_16 | I11: Google Ads | J11: 2024-01-04 | K11: 800 | L11: 738 | M11: 13 | N11: 0 | O11: 6.34 | P11: 0 | Q11: =IFERROR(P11-O11, 0) -> -6.34 | R11: =P11-O11 -> -6.34 | S11: =R11/O11 -> -1 | T11: 1.76 | U11: 0.49 | V11: 0 | W11: =N11/M11 -> 0 | X11: =IF(P11>=4, "SCALE", IF(P11>=2, "MONITOR", IF(P11>=1, "OPTIMISE", "PAUSE"))) -> PAUSE | Y11: =IF(K11<=300,"Low (100-300)", IF(K11<=500,"Mid (301-500)", IF(K11<=750,"High (501-750)", "Premium (751-1000)"))) -> Premium (751-1000)
A12: elon41@gmail.com | B12: elon | C12: dickey | D12: Daytona Beach | E12: FL | F12: 5000 | G12: mc donalds | H12: Campaign_18 | I12: Google Ads | J12: 2024-01-16 | K12: 800 | L12: 2315 | M12: 39 | N12: 3 | O12: 22.7 | P12: 209.05 | Q12: =IFERROR(P12-O12, 0) -> 186.35 | R12: =P12-O12 -> 186.35 | S12: =R12/O12 -> 8.2092511 | T12: 1.68 | U12: 0.58 | V12: 7.57 | W12: =N12/M12 -> 0.076923077 | X12: =IF(P12>=4, "SCALE", IF(P12>=2, "MONITOR", IF(P12>=1, "OPTIMISE", "PAUSE"))) -> SCALE | Y12: =IF(K12<=300,"Low (100-300)", IF(K12<=500,"Mid (301-500)", IF(K12<=750,"High (501-750)", "Premium (751-1000)"))) -> Premium (751-1000)
A13: ccdmflz@bellsouth.net | B13: charles | C13: wattik | D13: Jonesville | E13: LA | F13: 1500 | G13: security insurance | H13: Campaign_11 | I13: Google Ads | J13: 2024-01-22 | K13: 500 | L13: 1401 | M13: 30 | N13: 0 | O13: 14.98 | P13: 0 | Q13: =IFERROR(P13-O13, 0) -> -14.98 | R13: =P13-O13 -> -14.98 | S13: =R13/O13 -> -1 | T13: 2.14 | U13: 0.5 | V13: 0 | W13: =N13/M13 -> 0 | X13: =IF(P13>=4, "SCALE", IF(P13>=2, "MONITOR", IF(P13>=1, "OPTIMISE", "PAUSE"))) -> PAUSE | Y13: =IF(K13<=300,"Low (100-300)", IF(K13<=500,"Mid (301-500)", IF(K13<=750,"High (501-750)", "Premium (751-1000)"))) -> Mid (301-500)
A14: ashlallemand28@yahoo.com | B14: ashley | C14: lallemand | D14: Canal Winches | E14: OH | F14: 7042 | G14: franklin county | H14: Campaign_5 | I14: Google Ads | J14: 2024-01-09 | K14: 600 | L14: 776 | M14: 30 | N14: 0 | O14: 25.31 | P14: 0 | Q14: =IFERROR(P14-O14, 0) -> -25.31 | R14: =P14-O14 -> -25.31 | S14: =R14/O14 -> -1 | T14: 3.87 | U14: 0.84 | V14: 0 | W14: =N14/M14 -> 0 | X14: =IF(P14>=4, "SCALE", IF(P14>=2, "MONITOR", IF(P14>=1, "OPTIMISE", "PAUSE"))) -> PAUSE | Y14: =IF(K14<=300,"Low (100-300)", IF(K14<=500,"Mid (301-500)", IF(K14<=750,"High (501-750)", "Premium (751-1000)"))) -> High (501-750)
A15: hugocleary@hotmail.com | B15: hugo | C15: cleary | D15: Charlotte | E15: NC | F15: 1284 | G15: mages | H15: Campaign_14 | I15: Google Ads | J15: 2024-01-29 | K15: 300 | L15: 1010 | M15: 19 | N15: 1 | O15: 13.69 | P15: 48.33 | Q15: =IFERROR(P15-O15, 0) -> 34.64 | R15: =P15-O15 -> 34.64 | S15: =R15/O15 -> 2.5303141 | T15: 1.88 | U15: 0.72 | V15: 13.69 | W15: =N15/M15 -> 0.052631579 | X15: =IF(P15>=4, "SCALE", IF(P15>=2, "MONITOR", IF(P15>=1, "OPTIMISE", "PAUSE"))) -> SCALE | Y15: =IF(K15<=300,"Low (100-300)", IF(K15<=500,"Mid (301-500)", IF(K15<=750,"High (501-750)", "Premium (751-1000)"))) -> Low (100-300)
A16: altonwjr@gmail.com | B16: alton | C16: white | D16: Lubbock | E16: TX | F16: 3700 | G16: joe\\'s crab shack | H16: Campaign_8 | I16: Google Ads | J16: 2024-01-05 | K16: 500 | L16: 2482 | M16: 96 | N16: 10 | O16: 57.44 | P16: 698.1 | Q16: =IFERROR(P16-O16, 0) -> 640.66 | R16: =P16-O16 -> 640.66 | S16: =R16/O16 -> 11.153552 | T16: 3.87 | U16: 0.6 | V16: 5.74 | W16: =N16/M16 -> 0.10416667 | X16: =IF(P16>=4, "SCALE", IF(P16>=2, "MONITOR", IF(P16>=1, "OPTIMISE", "PAUSE"))) -> SCALE | Y16: =IF(K16<=300,"Low (100-300)", IF(K16<=500,"Mid (301-500)", IF(K16<=750,"High (501-750)", "Premium (751-1000)"))) -> Mid (301-500)
A17: yolandad.washington@gmail.com | B17: yolando | C17: washington | D17: Florence | E17: SC | F17: 4065 | G17: assurant | H17: Campaign_5 | I17: Google Ads | J17: 2024-01-11 | K17: 200 | L17: 1331 | M17: 27 | N17: 1 | O17: 16.42 | P17: 41.3 | Q17: =IFERROR(P17-O17, 0) -> 24.88 | R17: =P17-O17 -> 24.88 | S17: =R17/O17 -> 1.5152253 | T17: 2.03 | U17: 0.61 | V17: 16.42 | W17: =N17/M17 -> 0.037037037 | X17: =IF(P17>=4, "SCALE", IF(P17>=2, "MONITOR", IF(P17>=1, "OPTIMISE", "PAUSE"))) -> SCALE | Y17: =IF(K17<=300,"Low (100-300)", IF(K17<=500,"Mid (301-500)", IF(K17<=750,"High (501-750)", "Premium (751-1000)"))) -> Low (100-300)
A18: amber6329@gmail.com | B18: amber | C18: jones | D18: Cumberland | E18: VA | F18: 3100 | G18: wells fargo | H18: Campaign_1 | I18: Google Ads | J18: 2024-01-26 | K18: 1000 | L18: 1908 | M18: 63 | N18: 6 | O18: 32.2 | P18: 324.79 | Q18: =IFERROR(P18-O18, 0) -> 292.59 | R18: =P18-O18 -> 292.59 | S18: =R18/O18 -> 9.086646 | T18: 3.3 | U18: 0.51 | V18: 5.37 | W18: =N18/M18 -> 0.095238095 | X18: =IF(P18>=4, "SCALE", IF(P18>=2, "MONITOR", IF(P18>=1, "OPTIMISE", "PAUSE"))) -> SCALE | Y18: =IF(K18<=300,"Low (100-300)", IF(K18<=500,"Mid (301-500)", IF(K18<=750,"High (501-750)", "Premium (751-1000)"))) -> Premium (751-1000)
A19: minnie_82_00@yahoo.com | B19: angela | C19: hairston | D19: Fieldale | E19: VA | F19: 5282 | G19: memorial hospital | H19: Campaign_13 | I19: Google Ads | J19: 2024-01-30 | K19: 500 | L19: 937 | M19: 24 | N19: 1 | O19: 20.4 | P19: 42.54 | Q19: =IFERROR(P19-O19, 0) -> 22.14 | R19: =P19-O19 -> 22.14 | S19: =R19/O19 -> 1.0852941 | T19: 2.56 | U19: 0.85 | V19: 20.4 | W19: =N19/M19 -> 0.041666667 | X19: =IF(P19>=4, "SCALE", IF(P19>=2, "MONITOR", IF(P19>=1, "OPTIMISE", "PAUSE"))) -> SCALE | Y19: =IF(K19<=300,"Low (100-300)", IF(K19<=500,"Mid (301-500)", IF(K19<=750,"High (501-750)", "Premium (751-1000)"))) -> Mid (301-500)
A20: lovingiimerii@gmail.com | B20: yasmeen | C20: roddy | D20: Las Vegas | E20: NV | F20: 2750 | G20: nba raw sports | H20: Campaign_3 | I20: Google Ads | J20: 2024-01-16 | K20: 200 | L20: 808 | M20: 17 | N20: 0 | O20: 10.9 | P20: 0 | Q20: =IFERROR(P20-O20, 0) -> -10.9 | R20: =P20-O20 -> -10.9 | S20: =R20/O20 -> -1 | T20: 2.1 | U20: 0.64 | V20: 0 | W20: =N20/M20 -> 0 | X20: =IF(P20>=4, "SCALE", IF(P20>=2, "MONITOR", IF(P20>=1, "OPTIMISE", "PAUSE"))) -> PAUSE | Y20: =IF(K20<=300,"Low (100-300)", IF(K20<=500,"Mid (301-500)", IF(K20<=750,"High (501-750)", "Premium (751-1000)"))) -> Low (100-300)
A21: justinhilton81@gmail.com | B21: justin | C21: hilton | D21: Christiansbur | E21: VA | F21: 1500 | G21: energy management services | H21: Campaign_18 | I21: Google Ads | J21: 2024-01-11 | K21: 300 | L21: 2006 | M21: 48 | N21: 0 | O21: 23.39 | P21: 0 | Q21: =IFERROR(P21-O21, 0) -> -23.39 | R21: =P21-O21 -> -23.39 | S21: =R21/O21 -> -1 | T21: 2.39 | U21: 0.49 | V21: 0 | W21: =N21/M21 -> 0 | X21: =IF(P21>=4, "SCALE", IF(P21>=2, "MONITOR", IF(P21>=1, "OPTIMISE", "PAUSE"))) -> PAUSE | Y21: =IF(K21<=300,"Low (100-300)", IF(K21<=500,"Mid (301-500)", IF(K21<=750,"High (501-750)", "Premium (751-1000)"))) -> Low (100-300)
... A42: valeriejjohnson@gmail.com | B42: valerie | C42: johnson | D42: South Holland | E42: IL | F42: 4500 | G42: levitz furniture | H42: Campaign_8 | I42: Google Ads | J42: 2024-01-29 | K42: 100 | L42: 1159 | M42: 24 | N42: 2 | O42: 13.03 | P42: 133.86 | Q42: =IFERROR(P42-O42, 0) -> 120.83 | R42: =P42-O42 -> 120.83 | S42: =R42/O42 -> 9.2732157 | T42: 2.07 | U42: 0.54 | V42: 6.52 | W42: =N42/M42 -> 0.083333333 | X42: =IF(P42>=4, "SCALE", IF(P42>=2, "MONITOR", IF(P42>=1, "OPTIMISE", "PAUSE"))) -> SCALE | Y42: =IF(K42<=300,"Low (100-300)", IF(K42<=500,"Mid (301-500)", IF(K42<=750,"High (501-750)", "Premium (751-1000)"))) -> Low (100-300)
A43: samkrb101@gmail.com | B43: sam | C43: kirby | D43: Goreville | E43: IL | F43: 5417 | G43: 0 | H43: Campaign_13 | I43: Google Ads | J43: 2024-01-24 | K43: 400 | L43: 788 | M43: 17 | N43: 0 | O43: 13.99 | P43: 0 | Q43: =IFERROR(P43-O43, 0) -> -13.99 | R43: =P43-O43 -> -13.99 | S43: =R43/O43 -> -1 | T43: 2.16 | U43: 0.82 | V43: 0 | W43: =N43/M43 -> 0 | X43: =IF(P43>=4, "SCALE", IF(P43>=2, "MONITOR", IF(P43>=1, "OPTIMISE", "PAUSE"))) -> PAUSE | Y43: =IF(K43<=300,"Low (100-300)", IF(K43<=500,"Mid (301-500)", IF(K43<=750,"High (501-750)", "Premium (751-1000)"))) -> Mid (301-500)
A44: januaryh272@yahoo.com | B44: january | C44: harris | D44: Saint Louis | E44: MO | F44: 1300 | G44: gma paralegal services;llc | H44: Campaign_6 | I44: Google Ads | J44: 2024-01-11 | K44: 400 | L44: 1941 | M44: 85 | N44: 3 | O44: 40.6 | P44: 136.75 | Q44: =IFERROR(P44-O44, 0) -> 96.15 | R44: =P44-O44 -> 96.15 | S44: =R44/O44 -> 2.3682266 | T44: 4.38 | U44: 0.48 | V44: 13.53 | W44: =N44/M44 -> 0.035294118 | X44: =IF(P44>=4, "SCALE", IF(P44>=2, "MONITOR", IF(P44>=1, "OPTIMISE", "PAUSE"))) -> SCALE | Y44: =IF(K44<=300,"Low (100-300)", IF(K44<=500,"Mid (301-500)", IF(K44<=750,"High (501-750)", "Premium (751-1000)"))) -> Mid (301-500)
A45: valeriewalden@yahoo.com | B45: valerie | C45: walden | D45: Beaumont | E45: TX | F45: 1500 | G45: forth & towne | H45: Campaign_16 | I45: Google Ads | J45: 2024-01-08 | K45: 700 | L45: 676 | M45: 22 | N45: 1 | O45: 14.77 | P45: 49.55 | Q45: =IFERROR(P45-O45, 0) -> 34.78 | R45: =P45-O45 -> 34.78 | S45: =R45/O45 -> 2.3547732 | T45: 3.25 | U45: 0.67 | V45: 14.77 | W45: =N45/M45 -> 0.045454545 | X45: =IF(P45>=4, "SCALE", IF(P45>=2, "MONITOR", IF(P45>=1, "OPTIMISE", "PAUSE"))) -> SCALE | Y45: =IF(K45<=300,"Low (100-300)", IF(K45<=500,"Mid (301-500)", IF(K45<=750,"High (501-750)", "Premium (751-1000)"))) -> High (501-750)
A46: uearl51@yahoo.com | B46: earl | C46: underwood | D46: Navasota | E46: TX | F46: 2167 | G46: bj trucking | H46: Campaign_4 | I46: Google Ads | J46: 2024-01-13 | K46: 500 | L46: 1268 | M46: 50 | N46: 1 | O46: 34.57 | P46: 50.35 | Q46: =IFERROR(P46-O46, 0) -> 15.78 | R46: =P46-O46 -> 15.78 | S46: =R46/O46 -> 0.45646514 | T46: 3.94 | U46: 0.69 | V46: 34.57 | W46: =N46/M46 -> 0.02 | X46: =IF(P46>=4, "SCALE", IF(P46>=2, "MONITOR", IF(P46>=1, "OPTIMISE", "PAUSE"))) -> SCALE | Y46: =IF(K46<=300,"Low (100-300)", IF(K46<=500,"Mid (301-500)", IF(K46<=750,"High (501-750)", "Premium (751-1000)"))) -> Mid (301-500)
A47: jonesletique@gmail.com | B47: cathy | C47: jones | D47: Houston | E47: TX | F47: 2708 | G47: houstonisd | H47: Campaign_2 | I47: Google Ads | J47: 2024-01-08 | K47: 700 | L47: 541 | M47: 18 | N47: 0 | O47: 11.76 | P47: 0 | Q47: =IFERROR(P47-O47, 0) -> -11.76 | R47: =P47-O47 -> -11.76 | S47: =R47/O47 -> -1 | T47: 3.33 | U47: 0.65 | V47: 0 | W47: =N47/M47 -> 0 | X47: =IF(P47>=4, "SCALE", IF(P47>=2, "MONITOR", IF(P47>=1, "OPTIMISE", "PAUSE"))) -> PAUSE | Y47: =IF(K47<=300,"Low (100-300)", IF(K47<=500,"Mid (301-500)", IF(K47<=750,"High (501-750)", "Premium (751-1000)"))) -> High (501-750)
A48: elmarquez@gmail.com | B48: eloise | C48: marquez | D48: Portland | E48: OR | F48: 3250 | G48: realty depot | H48: Campaign_17 | I48: Google Ads | J48: 2024-01-08 | K48: 100 | L48: 1818 | M48: 67 | N48: 0 | O48: 43.74 | P48: 0 | Q48: =IFERROR(P48-O48, 0) -> -43.74 | R48: =P48-O48 -> -43.74 | S48: =R48/O48 -> -1 | T48: 3.69 | U48: 0.65 | V48: 0 | W48: =N48/M48 -> 0 | X48: =IF(P48>=4, "SCALE", IF(P48>=2, "MONITOR", IF(P48>=1, "OPTIMISE", "PAUSE"))) -> PAUSE | Y48: =IF(K48<=300,"Low (100-300)", IF(K48<=500,"Mid (301-500)", IF(K48<=750,"High (501-750)", "Premium (751-1000)"))) -> Low (100-300)
A49: laboy783@yahoo.com | B49: eliseo | C49: duarte | D49: Dallas | E49: TX | F49: 4100 | G49: bumc | H49: Campaign_20 | I49: Google Ads | J49: 2024-01-28 | K49: 400 | L49: 2032 | M49: 90 | N49: 0 | O49: 74.64 | P49: 0 | Q49: =IFERROR(P49-O49, 0) -> -74.64 | R49: =P49-O49 -> -74.64 | S49: =R49/O49 -> -1 | T49: 4.43 | U49: 0.83 | V49: 0 | W49: =N49/M49 -> 0 | X49: =IF(P49>=4, "SCALE", IF(P49>=2, "MONITOR", IF(P49>=1, "OPTIMISE", "PAUSE"))) -> PAUSE | Y49: =IF(K49<=300,"Low (100-300)", IF(K49<=500,"Mid (301-500)", IF(K49<=750,"High (501-750)", "Premium (751-1000)"))) -> Mid (301-500)
A50: bbluv4u2@yahoo.com | B50: marlin | C50: brown | D50: Concord | E50: NC | F50: 3400 | G50: china spring isd | H50: Campaign_19 | I50: Google Ads | J50: 2024-01-23 | K50: 300 | L50: 2373 | M50: 55 | N50: 0 | O50: 25.61 | P50: 0 | Q50: =IFERROR(P50-O50, 0) -> -25.61 | R50: =P50-O50 -> -25.61 | S50: =R50/O50 -> -1 | T50: 2.32 | U50: 0.47 | V50: 0 | W50: =N50/M50 -> 0 | X50: =IF(P50>=4, "SCALE", IF(P50>=2, "MONITOR", IF(P50>=1, "OPTIMISE", "PAUSE"))) -> PAUSE | Y50: =IF(K50<=300,"Low (100-300)", IF(K50<=500,"Mid (301-500)", IF(K50<=750,"High (501-750)", "Premium (751-1000)"))) -> Low (100-300)
A51: heruone2000@yahoo.com | B51: terrance | C51: merck | D51: Detroit | E51: MI | F51: 2498 | G51: embrenche | H51: Campaign_8 | I51: Google Ads | J51: 2024-01-17 | K51: 1000 | L51: 1148 | M51: 17 | N51: 1 | O51: 8.05 | P51: 70.32 | Q51: =IFERROR(P51-O51, 0) -> 62.27 | R51: =P51-O51 -> 62.27 | S51: =R51/O51 -> 7.7354037 | T51: 1.48 | U51: 0.47 | V51: 8.05 | W51: =N51/M51 -> 0.058823529 | X51: =IF(P51>=4, "SCALE", IF(P51>=2, "MONITOR", IF(P51>=1, "OPTIMISE", "PAUSE"))) -> SCALE | Y51: =IF(K51<=300,"Low (100-300)", IF(K51<=500,"Mid (301-500)", IF(K51<=750,"High (501-750)", "Premium (751-1000)"))) -> Premium (751-1000)
A52: buffanged@yahoo.com | B52: angela | C52: buffington | D52: Nicholasville | E52: KY | F52: 2167 | G52: eden bishop | H52: Campaign_19 | I52: Google Ads | J52: 2024-01-15 | K52: 500 | L52: 2166 | M52: 39 | N52: 3 | O52: 20.6 | P52: 175.07 | Q52: =IFERROR(P52-O52, 0) -> 154.47 | R52: =P52-O52 -> 154.47 | S52: =R52/O52 -> 7.4985437 | T52: 1.8 | U52: 0.53 | V52: 6.87 | W52: =N52/M52 -> 0.076923077 | X52: =IF(P52>=4, "SCALE", IF(P52>=2, "MONITOR", IF(P52>=1, "OPTIMISE", "PAUSE"))) -> SCALE | Y52: =IF(K52<=300,"Low (100-300)", IF(K52<=500,"Mid (301-500)", IF(K52<=750,"High (501-750)", "Premium (751-1000)"))) -> Mid (301-500)
A53: rkarinagarzon@hotmail.com | B53: rosana | C53: lamoglia | D53: Naples | E53: FL | F53: 2000 | G53: pelicanbayfoundation | H53: Campaign_17 | I53: Google Ads | J53: 2024-01-10 | K53: 600 | L53: 1430 | M53: 61 | N53: 2 | O53: 45.15 | P53: 104.72 | Q53: =IFERROR(P53-O53, 0) -> 59.57 | R53: =P53-O53 -> 59.57 | S53: =R53/O53 -> 1.3193798 | T53: 4.27 | U53: 0.74 | V53: 22.58 | W53: =N53/M53 -> 0.032786885 | X53: =IF(P53>=4, "SCALE", IF(P53>=2, "MONITOR", IF(P53>=1, "OPTIMISE", "PAUSE"))) -> SCALE | Y53: =IF(K53<=300,"Low (100-300)", IF(K53<=500,"Mid (301-500)", IF(K53<=750,"High (501-750)", "Premium (751-1000)"))) -> High (501-750)
A54: ortizana85@gmail.com | B54: ana | C54: villanueva | D54: Arlington | E54: TX | F54: 3100 | G54: ats | H54: Campaign_11 | I54: Google Ads | J54: 2024-01-14 | K54: 1000 | L54: 2055 | M54: 85 | N54: 0 | O54: 64.77 | P54: 0 | Q54: =IFERROR(P54-O54, 0) -> -64.77 | R54: =P54-O54 -> -64.77 | S54: =R54/O54 -> -1 | T54: 4.14 | U54: 0.76 | V54: 0 | W54: =N54/M54 -> 0 | X54: =IF(P54>=4, "SCALE", IF(P54>=2, "MONITOR", IF(P54>=1, "OPTIMISE", "PAUSE"))) -> PAUSE | Y54: =IF(K54<=300,"Low (100-300)", IF(K54<=500,"Mid (301-500)", IF(K54<=750,"High (501-750)", "Premium (751-1000)"))) -> Premium (751-1000)
A55: revo6419@gmail.com | B55: david | C55: revolinski | D55: Fort Atkinson | E55: WI | F55: 1924 | G55: eaton | H55: Campaign_20 | I55: Google Ads | J55: 2024-01-20 | K55: 400 | L55: 1727 | M55: 26 | N55: 3 | O55: 16.67 | P55: 162.56 | Q55: =IFERROR(P55-O55, 0) -> 145.89 | R55: =P55-O55 -> 145.89 | S55: =R55/O55 -> 8.7516497 | T55: 1.51 | U55: 0.64 | V55: 5.56 | W55: =N55/M55 -> 0.11538462 | X55: =IF(P55>=4, "SCALE", IF(P55>=2, "MONITOR", IF(P55>=1, "OPTIMISE", "PAUSE"))) -> SCALE | Y55: =IF(K55<=300,"Low (100-300)", IF(K55<=500,"Mid (301-500)", IF(K55<=750,"High (501-750)", "Premium (751-1000)"))) -> Mid (301-500)
... A69: dtfrison05@yahoo.com | B69: dawntesha | C69: frison | D69: Tolleson | E69: AZ | F69: 2708 | G69: wells fargo | H69: Campaign_10 | I69: Google Ads | J69: 2024-01-28 | K69: 700 | L69: 850 | M69: 22 | N69: 0 | O69: 15.66 | P69: 0 | Q69: =IFERROR(P69-O69, 0) -> -15.66 | R69: =P69-O69 -> -15.66 | S69: =R69/O69 -> -1 | T69: 2.59 | U69: 0.71 | V69: 0 | W69: =N69/M69 -> 0 | X69: =IF(P69>=4, "SCALE", IF(P69>=2, "MONITOR", IF(P69>=1, "OPTIMISE", "PAUSE"))) -> PAUSE | Y69: =IF(K69<=300,"Low (100-300)", IF(K69<=500,"Mid (301-500)", IF(K69<=750,"High (501-750)", "Premium (751-1000)"))) -> High (501-750)
A70: rgililland@live.com | B70: rebekah | C70: gililland | D70: Oklahoma City | E70: OK | F70: 1733 | G70: 0 | H70: Campaign_7 | I70: Google Ads | J70: 2024-01-03 | K70: 400 | L70: 834 | M70: 15 | N70: 0 | O70: 7.46 | P70: 0 | Q70: =IFERROR(P70-O70, 0) -> -7.46 | R70: =P70-O70 -> -7.46 | S70: =R70/O70 -> -1 | T70: 1.8 | U70: 0.5 | V70: 0 | W70: =N70/M70 -> 0 | X70: =IF(P70>=4, "SCALE", IF(P70>=2, "MONITOR", IF(P70>=1, "OPTIMISE", "PAUSE"))) -> PAUSE | Y70: =IF(K70<=300,"Low (100-300)", IF(K70<=500,"Mid (301-500)", IF(K70<=750,"High (501-750)", "Premium (751-1000)"))) -> Mid (301-500)
A71: a30yroldfrog@aol.com | B71: angela | C71: stephens | D71: Lehigh Acres | E71: FL | F71: 2500 | G71: murphy usa | H71: Campaign_13 | I71: Google Ads | J71: 2024-01-28 | K71: 1000 | L71: 648 | M71: 26 | N71: 0 | O71: 16.05 | P71: 0 | Q71: =IFERROR(P71-O71, 0) -> -16.05 | R71: =P71-O71 -> -16.05 | S71: =R71/O71 -> -1 | T71: 4.01 | U71: 0.62 | V71: 0 | W71: =N71/M71 -> 0 | X71: =IF(P71>=4, "SCALE", IF(P71>=2, "MONITOR", IF(P71>=1, "OPTIMISE", "PAUSE"))) -> PAUSE | Y71: =IF(K71<=300,"Low (100-300)", IF(K71<=500,"Mid (301-500)", IF(K71<=750,"High (501-750)", "Premium (751-1000)"))) -> Premium (751-1000)
A72: aydinsmommy1221@live.com | B72: terina | C72: barlow | D72: Chicago | E72: IL | F72: 3900 | G72: tcf national bank illinois | H72: Campaign_13 | I72: Google Ads | J72: 2024-01-06 | K72: 100 | L72: 893 | M72: 15 | N72: 0 | O72: 7.26 | P72: 0 | Q72: =IFERROR(P72-O72, 0) -> -7.26 | R72: =P72-O72 -> -7.26 | S72: =R72/O72 -> -1 | T72: 1.68 | U72: 0.48 | V72: 0 | W72: =N72/M72 -> 0 | X72: =IF(P72>=4, "SCALE", IF(P72>=2, "MONITOR", IF(P72>=1, "OPTIMISE", "PAUSE"))) -> PAUSE | Y72: =IF(K72<=300,"Low (100-300)", IF(K72<=500,"Mid (301-500)", IF(K72<=750,"High (501-750)", "Premium (751-1000)"))) -> Low (100-300)
A73: tiffanylenae04@yahoo.com | B73: tiffany | C73: mock | D73: Ravenna | E73: NE | F73: 2250 | G73: cabelas | H73: Campaign_7 | I73: Google Ads | J73: 2024-01-12 | K73: 800 | L73: 1515 | M73: 33 | N73: 0 | O73: 18.21 | P73: 0 | Q73: =IFERROR(P73-O73, 0) -> -18.21 | R73: =P73-O73 -> -18.21 | S73: =R73/O73 -> -1 | T73: 2.18 | U73: 0.55 | V73: 0 | W73: =N73/M73 -> 0 | X73: =IF(P73>=4, "SCALE", IF(P73>=2, "MONITOR", IF(P73>=1, "OPTIMISE", "PAUSE"))) -> PAUSE | Y73: =IF(K73<=300,"Low (100-300)", IF(K73<=500,"Mid (301-500)", IF(K73<=750,"High (501-750)", "Premium (751-1000)"))) -> Premium (751-1000)
A74: christylnolen@abbey.bac.edu | B74: christy | C74: nolen | D74: Cramerton | E74: NC | F74: 4604 | G74: mcso | H74: Campaign_12 | I74: Google Ads | J74: 2024-01-23 | K74: 800 | L74: 1846 | M74: 41 | N74: 0 | O74: 32.59 | P74: 0 | Q74: =IFERROR(P74-O74, 0) -> -32.59 | R74: =P74-O74 -> -32.59 | S74: =R74/O74 -> -1 | T74: 2.22 | U74: 0.79 | V74: 0 | W74: =N74/M74 -> 0 | X74: =IF(P74>=4, "SCALE", IF(P74>=2, "MONITOR", IF(P74>=1, "OPTIMISE", "PAUSE"))) -> PAUSE | Y74: =IF(K74<=300,"Low (100-300)", IF(K74<=500,"Mid (301-500)", IF(K74<=750,"High (501-750)", "Premium (751-1000)"))) -> Premium (751-1000)
A75: lebpsc09@yahoo.com | B75: pam | C75: coston | D75: Charlotte | E75: NC | F75: 4800 | G75: branch banking and trust compa | H75: Campaign_4 | I75: Google Ads | J75: 2024-01-24 | K75: 100 | L75: 936 | M75: 18 | N75: 0 | O75: 9.31 | P75: 0 | Q75: =IFERROR(P75-O75, 0) -> -9.31 | R75: =P75-O75 -> -9.31 | S75: =R75/O75 -> -1 | T75: 1.92 | U75: 0.52 | V75: 0 | W75: =N75/M75 -> 0 | X75: =IF(P75>=4, "SCALE", IF(P75>=2, "MONITOR", IF(P75>=1, "OPTIMISE", "PAUSE"))) -> PAUSE | Y75: =IF(K75<=300,"Low (100-300)", IF(K75<=500,"Mid (301-500)", IF(K75<=750,"High (501-750)", "Premium (751-1000)"))) -> Low (100-300)
A76: crayfield65@gmail.com | B76: christina | C76: rayfield | D76: Houston | E76: TX | F76: 2200 | G76: central market | H76: Campaign_11 | I76: Google Ads | J76: 2024-01-22 | K76: 1000 | L76: 667 | M76: 17 | N76: 0 | O76: 7.61 | P76: 0 | Q76: =IFERROR(P76-O76, 0) -> -7.61 | R76: =P76-O76 -> -7.61 | S76: =R76/O76 -> -1 | T76: 2.55 | U76: 0.45 | V76: 0 | W76: =N76/M76 -> 0 | X76: =IF(P76>=4, "SCALE", IF(P76>=2, "MONITOR", IF(P76>=1, "OPTIMISE", "PAUSE"))) -> PAUSE | Y76: =IF(K76<=300,"Low (100-300)", IF(K76<=500,"Mid (301-500)", IF(K76<=750,"High (501-750)", "Premium (751-1000)"))) -> Premium (751-1000)
A77: samuel_brown84@yahoo.com | B77: brown | C77: sam | D77: Cleveland | E77: TX | F77: 2500 | G77: pitney bowes | H77: Campaign_6 | I77: Google Ads | J77: 2024-01-07 | K77: 200 | L77: 978 | M77: 40 | N77: 4 | O77: 22.01 | P77: 220 | Q77: =IFERROR(P77-O77, 0) -> 197.99 | R77: =P77-O77 -> 197.99 | S77: =R77/O77 -> 8.9954566 | T77: 4.09 | U77: 0.55 | V77: 5.5 | W77: =N77/M77 -> 0.1 | X77: =IF(P77>=4, "SCALE", IF(P77>=2, "MONITOR", IF(P77>=1, "OPTIMISE", "PAUSE"))) -> SCALE | Y77: =IF(K77<=300,"Low (100-300)", IF(K77<=500,"Mid (301-500)", IF(K77<=750,"High (501-750)", "Premium (751-1000)"))) -> Low (100-300)
A78: hdw1865@yahoo.com | B78: howard | C78: webster | D78: Crewe | E78: VA | F78: 2000 | G78: mark dunning ind. | H78: Campaign_12 | I78: Google Ads | J78: 2024-01-03 | K78: 1000 | L78: 1825 | M78: 77 | N78: 0 | O78: 46.53 | P78: 0 | Q78: =IFERROR(P78-O78, 0) -> -46.53 | R78: =P78-O78 -> -46.53 | S78: =R78/O78 -> -1 | T78: 4.22 | U78: 0.6 | V78: 0 | W78: =N78/M78 -> 0 | X78: =IF(P78>=4, "SCALE", IF(P78>=2, "MONITOR", IF(P78>=1, "OPTIMISE", "PAUSE"))) -> PAUSE | Y78: =IF(K78<=300,"Low (100-300)", IF(K78<=500,"Mid (301-500)", IF(K78<=750,"High (501-750)", "Premium (751-1000)"))) -> Premium (751-1000)
A79: kidwellk1031@aol.com | B79: kim | C79: kidwell | D79: Kokomo | E79: IN | F79: 3300 | G79: compass | H79: Campaign_1 | I79: Google Ads | J79: 2024-01-08 | K79: 300 | L79: 1807 | M79: 46 | N79: 1 | O79: 31.07 | P79: 70.38 | Q79: =IFERROR(P79-O79, 0) -> 39.31 | R79: =P79-O79 -> 39.31 | S79: =R79/O79 -> 1.2652076 | T79: 2.55 | U79: 0.68 | V79: 31.07 | W79: =N79/M79 -> 0.02173913 | X79: =IF(P79>=4, "SCALE", IF(P79>=2, "MONITOR", IF(P79>=1, "OPTIMISE", "PAUSE"))) -> SCALE | Y79: =IF(K79<=300,"Low (100-300)", IF(K79<=500,"Mid (301-500)", IF(K79<=750,"High (501-750)", "Premium (751-1000)"))) -> Low (100-300)
A80: jhockemeyer812@gmail.com | B80: jonathan | C80: hockemeyer | D80: Burleson | E80: TX | F80: 4500 | G80: bankston chevrolet | H80: Campaign_9 | I80: Google Ads | J80: 2024-01-30 | K80: 800 | L80: 2403 | M80: 57 | N80: 2 | O80: 47.38 | P80: 127.73 | Q80: =IFERROR(P80-O80, 0) -> 80.35 | R80: =P80-O80 -> 80.35 | S80: =R80/O80 -> 1.6958632 | T80: 2.37 | U80: 0.83 | V80: 23.69 | W80: =N80/M80 -> 0.035087719 | X80: =IF(P80>=4, "SCALE", IF(P80>=2, "MONITOR", IF(P80>=1, "OPTIMISE", "PAUSE"))) -> SCALE | Y80: =IF(K80<=300,"Low (100-300)", IF(K80<=500,"Mid (301-500)", IF(K80<=750,"High (501-750)", "Premium (751-1000)"))) -> Premium (751-1000)
A81: deemurray91@gmail.com | B81: deanna | C81: murray | D81: Fayetteville | E81: NC | F81: 1699 | G81: deanna murray | H81: Campaign_18 | I81: Google Ads | J81: 2024-01-06 | K81: 100 | L81: 2212 | M81: 81 | N81: 7 | O81: 34.45 | P81: 519.26 | Q81: =IFERROR(P81-O81, 0) -> 484.81 | R81: =P81-O81 -> 484.81 | S81: =R81/O81 -> 14.072859 | T81: 3.66 | U81: 0.43 | V81: 4.92 | W81: =N81/M81 -> 0.086419753 | X81: =IF(P81>=4, "SCALE", IF(P81>=2, "MONITOR", IF(P81>=1, "OPTIMISE", "PAUSE"))) -> SCALE | Y81: =IF(K81<=300,"Low (100-300)", IF(K81<=500,"Mid (301-500)", IF(K81<=750,"High (501-750)", "Premium (751-1000)"))) -> Low (100-300)
A82: arielbaker@gmail.com | B82: ariel | C82: baker | D82: Sarasota | E82: FL | F82: 2167 | G82: whole foods marker | H82: Campaign_16 | I82: Google Ads | J82: 2024-01-28 | K82: 800 | L82: 1242 | M82: 50 | N82: 2 | O82: 37.19 | P82: 107.85 | Q82: =IFERROR(P82-O82, 0) -> 70.66 | R82: =P82-O82 -> 70.66 | S82: =R82/O82 -> 1.8999731 | T82: 4.03 | U82: 0.74 | V82: 18.6 | W82: =N82/M82 -> 0.04 | X82: =IF(P82>=4, "SCALE", IF(P82>=2, "MONITOR", IF(P82>=1, "OPTIMISE", "PAUSE"))) -> SCALE | Y82: =IF(K82<=300,"Low (100-300)", IF(K82<=500,"Mid (301-500)", IF(K82<=750,"High (501-750)", "Premium (751-1000)"))) -> Premium (751-1000)
... A305: howardhannah329@yahoo.com | B305: howard | C305: hannah | D305: Houston | E305: TX | F305: 2500 | G305: goodman heating and cooling | H305: Campaign_16 | I305: Google Ads | J305: 2024-01-18 | K305: 1000 | L305: 1353 | M305: 33 | N305: 0 | O305: 16.22 | P305: 0 | Q305: =IFERROR(P305-O305, 0) -> -16.22 | R305: =P305-O305 -> -16.22 | S305: =R305/O305 -> -1 | T305: 2.44 | U305: 0.49 | V305: 0 | W305: =N305/M305 -> 0 | X305: =IF(P305>=4, "SCALE", IF(P305>=2, "MONITOR", IF(P305>=1, "OPTIMISE", "PAUSE"))) -> PAUSE | Y305: =IF(K305<=300,"Low (100-300)", IF(K305<=500,"Mid (301-500)", IF(K305<=750,"High (501-750)", "Premium (751-1000)"))) -> Premium (751-1000)
A306: tealesia0418@live.com | B306: tealesia | C306: marshall | D306: Marshall | E306: TX | F306: 2250 | G306: 0 | H306: Campaign_10 | I306: Google Ads | J306: 2024-01-18 | K306: 700 | L306: 1752 | M306: 64 | N306: 1 | O306: 42.36 | P306: 62.91 | Q306: =IFERROR(P306-O306, 0) -> 20.55 | R306: =P306-O306 -> 20.55 | S306: =R306/O306 -> 0.48512748 | T306: 3.65 | U306: 0.66 | V306: 42.36 | W306: =N306/M306 -> 0.015625 | X306: =IF(P306>=4, "SCALE", IF(P306>=2, "MONITOR", IF(P306>=1, "OPTIMISE", "PAUSE"))) -> SCALE | Y306: =IF(K306<=300,"Low (100-300)", IF(K306<=500,"Mid (301-500)", IF(K306<=750,"High (501-750)", "Premium (751-1000)"))) -> High (501-750)
A307: shalon.staten@gmail.com | B307: shalon | C307: staten | D307: Bonifay | E307: FL | F307: 2750 | G307: dove academy | H307: Campaign_13 | I307: Google Ads | J307: 2024-01-19 | K307: 300 | L307: 1984 | M307: 51 | N307: 0 | O307: 39.13 | P307: 0 | Q307: =IFERROR(P307-O307, 0) -> -39.13 | R307: =P307-O307 -> -39.13 | S307: =R307/O307 -> -1 | T307: 2.57 | U307: 0.77 | V307: 0 | W307: =N307/M307 -> 0 | X307: =IF(P307>=4, "SCALE", IF(P307>=2, "MONITOR", IF(P307>=1, "OPTIMISE", "PAUSE"))) -> PAUSE | Y307: =IF(K307<=300,"Low (100-300)", IF(K307<=500,"Mid (301-500)", IF(K307<=750,"High (501-750)", "Premium (751-1000)"))) -> Low (100-300)
A308: rdean_61@hotmail.com | B308: ronald | C308: chambers | D308: Casa Grande | E308: AZ | F308: 2750 | G308: abbott nutrition | H308: Campaign_13 | I308: Google Ads | J308: 2024-01-16 | K308: 600 | L308: 1029 | M308: 40 | N308: 0 | O308: 18.41 | P308: 0 | Q308: =IFERROR(P308-O308, 0) -> -18.41 | R308: =P308-O308 -> -18.41 | S308: =R308/O308 -> -1 | T308: 3.89 | U308: 0.46 | V308: 0 | W308: =N308/M308 -> 0 | X308: =IF(P308>=4, "SCALE", IF(P308>=2, "MONITOR", IF(P308>=1, "OPTIMISE", "PAUSE"))) -> PAUSE | Y308: =IF(K308<=300,"Low (100-300)", IF(K308<=500,"Mid (301-500)", IF(K308<=750,"High (501-750)", "Premium (751-1000)"))) -> High (501-750)
A309: s0n0fabish85@gmail.com | B309: tyler | C309: bish | D309: Lost Creek | E309: WV | F309: 1300 | G309: unitedsummitcenter | H309: Campaign_1 | I309: Google Ads | J309: 2024-01-15 | K309: 1000 | L309: 876 | M309: 36 | N309: 0 | O309: 19.37 | P309: 0 | Q309: =IFERROR(P309-O309, 0) -> -19.37 | R309: =P309-O309 -> -19.37 | S309: =R309/O309 -> -1 | T309: 4.11 | U309: 0.54 | V309: 0 | W309: =N309/M309 -> 0 | X309: =IF(P309>=4, "SCALE", IF(P309>=2, "MONITOR", IF(P309>=1, "OPTIMISE", "PAUSE"))) -> PAUSE | Y309: =IF(K309<=300,"Low (100-300)", IF(K309<=500,"Mid (301-500)", IF(K309<=750,"High (501-750)", "Premium (751-1000)"))) -> Premium (751-1000)
A310: laron2525@gmail.com | B310: laron | C310: lewis | D310: Lexington | E310: KY | F310: 2250 | G310: lextran | H310: Campaign_7 | I310: Google Ads | J310: 2024-01-14 | K310: 700 | L310: 1261 | M310: 33 | N310: 3 | O310: 21.54 | P310: 125.6 | Q310: =IFERROR(P310-O310, 0) -> 104.06 | R310: =P310-O310 -> 104.06 | S310: =R310/O310 -> 4.8310121 | T310: 2.62 | U310: 0.65 | V310: 7.18 | W310: =N310/M310 -> 0.090909091 | X310: =IF(P310>=4, "SCALE", IF(P310>=2, "MONITOR", IF(P310>=1, "OPTIMISE", "PAUSE"))) -> SCALE | Y310: =IF(K310<=300,"Low (100-300)", IF(K310<=500,"Mid (301-500)", IF(K310<=750,"High (501-750)", "Premium (751-1000)"))) -> High (501-750)
A311: danielledavid00@gmail.com | B311: danielle | C311: david | D311: Los Angeles | E311: CA | F311: 2250 | G311: bcbg max azria | H311: Campaign_12 | I311: Google Ads | J311: 2024-01-13 | K311: 500 | L311: 1080 | M311: 17 | N311: 0 | O311: 10.68 | P311: 0 | Q311: =IFERROR(P311-O311, 0) -> -10.68 | R311: =P311-O311 -> -10.68 | S311: =R311/O311 -> -1 | T311: 1.57 | U311: 0.63 | V311: 0 | W311: =N311/M311 -> 0 | X311: =IF(P311>=4, "SCALE", IF(P311>=2, "MONITOR", IF(P311>=1, "OPTIMISE", "PAUSE"))) -> PAUSE | Y311: =IF(K311<=300,"Low (100-300)", IF(K311<=500,"Mid (301-500)", IF(K311<=750,"High (501-750)", "Premium (751-1000)"))) -> Mid (301-500)
A312: dropdap@gmail.com | B312: elijah | C312: scott | D312: Atlanta | E312: GA | F312: 2250 | G312: wellpoint | H312: Campaign_4 | I312: Google Ads | J312: 2024-01-06 | K312: 800 | L312: 1717 | M312: 30 | N312: 2 | O312: 25.49 | P312: 149.98 | Q312: =IFERROR(P312-O312, 0) -> 124.49 | R312: =P312-O312 -> 124.49 | S312: =R312/O312 -> 4.883876 | T312: 1.75 | U312: 0.85 | V312: 12.74 | W312: =N312/M312 -> 0.066666667 | X312: =IF(P312>=4, "SCALE", IF(P312>=2, "MONITOR", IF(P312>=1, "OPTIMISE", "PAUSE"))) -> SCALE | Y312: =IF(K312<=300,"Low (100-300)", IF(K312<=500,"Mid (301-500)", IF(K312<=750,"High (501-750)", "Premium (751-1000)"))) -> Premium (751-1000)
A313: lclinard@yahoo.com | B313: michael | C313: clinard | D313: Bucyrus | E313: OH | F313: 1300 | G313: stratosphere | H313: Campaign_12 | I313: Google Ads | J313: 2024-01-25 | K313: 100 | L313: 1437 | M313: 36 | N313: 1 | O313: 20.72 | P313: 46.82 | Q313: =IFERROR(P313-O313, 0) -> 26.1 | R313: =P313-O313 -> 26.1 | S313: =R313/O313 -> 1.2596525 | T313: 2.51 | U313: 0.58 | V313: 20.72 | W313: =N313/M313 -> 0.027777778 | X313: =IF(P313>=4, "SCALE", IF(P313>=2, "MONITOR", IF(P313>=1, "OPTIMISE", "PAUSE"))) -> SCALE | Y313: =IF(K313<=300,"Low (100-300)", IF(K313<=500,"Mid (301-500)", IF(K313<=750,"High (501-750)", "Premium (751-1000)"))) -> Low (100-300)
A314: ca.13@live.com | B314: yasen | C314: jiang | D314: San Diego | E314: CA | F314: 4500 | G314: polymerex medical inc | H314: Campaign_16 | I314: Google Ads | J314: 2024-01-27 | K314: 600 | L314: 837 | M314: 28 | N314: 0 | O314: 15.96 | P314: 0 | Q314: =IFERROR(P314-O314, 0) -> -15.96 | R314: =P314-O314 -> -15.96 | S314: =R314/O314 -> -1 | T314: 3.35 | U314: 0.57 | V314: 0 | W314: =N314/M314 -> 0 | X314: =IF(P314>=4, "SCALE", IF(P314>=2, "MONITOR", IF(P314>=1, "OPTIMISE", "PAUSE"))) -> PAUSE | Y314: =IF(K314<=300,"Low (100-300)", IF(K314<=500,"Mid (301-500)", IF(K314<=750,"High (501-750)", "Premium (751-1000)"))) -> High (501-750)
A315: talithajones31@yahoo.com | B315: talitha | C315: jones | D315: Minneapolis | E315: MN | F315: 3250 | G315: a chance learning center | H315: Campaign_1 | I315: Google Ads | J315: 2024-01-27 | K315: 200 | L315: 897 | M315: 38 | N315: 0 | O315: 29.09 | P315: 0 | Q315: =IFERROR(P315-O315, 0) -> -29.09 | R315: =P315-O315 -> -29.09 | S315: =R315/O315 -> -1 | T315: 4.24 | U315: 0.77 | V315: 0 | W315: =N315/M315 -> 0 | X315: =IF(P315>=4, "SCALE", IF(P315>=2, "MONITOR", IF(P315>=1, "OPTIMISE", "PAUSE"))) -> PAUSE | Y315: =IF(K315<=300,"Low (100-300)", IF(K315<=500,"Mid (301-500)", IF(K315<=750,"High (501-750)", "Premium (751-1000)"))) -> Low (100-300)
A316: meryldsmith@yahoo.com | B316: meryl | C316: smith | D316: Fort Worth | E316: TX | F316: 1100 | G316: bell helicopter | H316: Campaign_6 | I316: Google Ads | J316: 2024-01-19 | K316: 100 | L316: 1632 | M316: 30 | N316: 1 | O316: 15.21 | P316: 66.37 | Q316: =IFERROR(P316-O316, 0) -> 51.16 | R316: =P316-O316 -> 51.16 | S316: =R316/O316 -> 3.3635766 | T316: 1.84 | U316: 0.51 | V316: 15.21 | W316: =N316/M316 -> 0.033333333 | X316: =IF(P316>=4, "SCALE", IF(P316>=2, "MONITOR", IF(P316>=1, "OPTIMISE", "PAUSE"))) -> SCALE | Y316: =IF(K316<=300,"Low (100-300)", IF(K316<=500,"Mid (301-500)", IF(K316<=750,"High (501-750)", "Premium (751-1000)"))) -> Low (100-300)
A317: d.trish7@gmail.com | B317: patricia | C317: dolan | D317: New Haven | E317: CT | F317: 1300 | G317: sealtitecontracting | H317: Campaign_18 | I317: Google Ads | J317: 2024-01-09 | K317: 700 | L317: 535 | M317: 8 | N317: 1 | O317: 5.22 | P317: 56.85 | Q317: =IFERROR(P317-O317, 0) -> 51.63 | R317: =P317-O317 -> 51.63 | S317: =R317/O317 -> 9.8908046 | T317: 1.5 | U317: 0.65 | V317: 5.22 | W317: =N317/M317 -> 0.125 | X317: =IF(P317>=4, "SCALE", IF(P317>=2, "MONITOR", IF(P317>=1, "OPTIMISE", "PAUSE"))) -> SCALE | Y317: =IF(K317<=300,"Low (100-300)", IF(K317<=500,"Mid (301-500)", IF(K317<=750,"High (501-750)", "Premium (751-1000)"))) -> High (501-750)
A318: drbill417@yahoo.com | B318: william c | C318: thomas | D318: Ormond Beach | E318: FL | F318: 4500 | G318: self employed | H318: Campaign_10 | I318: Google Ads | J318: 2024-01-16 | K318: 600 | L318: 908 | M318: 25 | N318: 0 | O318: 17.01 | P318: 0 | Q318: =IFERROR(P318-O318, 0) -> -17.01 | R318: =P318-O318 -> -17.01 | S318: =R318/O318 -> -1 | T318: 2.75 | U318: 0.68 | V318: 0 | W318: =N318/M318 -> 0 | X318: =IF(P318>=4, "SCALE", IF(P318>=2, "MONITOR", IF(P318>=1, "OPTIMISE", "PAUSE"))) -> PAUSE | Y318: =IF(K318<=300,"Low (100-300)", IF(K318<=500,"Mid (301-500)", IF(K318<=750,"High (501-750)", "Premium (751-1000)"))) -> High (501-750)
... A753: designedbyjenny@yahoo.com | B753: jennifer | C753: hao | D753: Fort Worth | E753: TX | F753: 2250 | G753: vast america | H753: Campaign_7 | I753: Google Ads | J753: 2024-01-10 | K753: 800 | L753: 1689 | M753: 25 | N753: 1 | O753: 12.48 | P753: 63.84 | Q753: =IFERROR(P753-O753, 0) -> 51.36 | R753: =P753-O753 -> 51.36 | S753: =R753/O753 -> 4.1153846 | T753: 1.48 | U753: 0.5 | V753: 12.48 | W753: =N753/M753 -> 0.04 | X753: =IF(P753>=4, "SCALE", IF(P753>=2, "MONITOR", IF(P753>=1, "OPTIMISE", "PAUSE"))) -> SCALE | Y753: =IF(K753<=300,"Low (100-300)", IF(K753<=500,"Mid (301-500)", IF(K753<=750,"High (501-750)", "Premium (751-1000)"))) -> Premium (751-1000)
A754: kjg50@aol.com | B754: stephen | C754: grant | D754: Lawrenceburg | E754: KY | F754: 6500 | G754: 0 | H754: Campaign_4 | I754: Google Ads | J754: 2024-01-15 | K754: 800 | L754: 1765 | M754: 72 | N754: 7 | O754: 53.11 | P754: 484.3 | Q754: =IFERROR(P754-O754, 0) -> 431.19 | R754: =P754-O754 -> 431.19 | S754: =R754/O754 -> 8.11881 | T754: 4.08 | U754: 0.74 | V754: 7.59 | W754: =N754/M754 -> 0.097222222 | X754: =IF(P754>=4, "SCALE", IF(P754>=2, "MONITOR", IF(P754>=1, "OPTIMISE", "PAUSE"))) -> SCALE | Y754: =IF(K754<=300,"Low (100-300)", IF(K754<=500,"Mid (301-500)", IF(K754<=750,"High (501-750)", "Premium (751-1000)"))) -> Premium (751-1000)
A755: t12v17m@yahoo.com | B755: gertrude | C755: vanmiddleswo | D755: Orlando | E755: FL | F755: 2000 | G755: disability insurance | H755: Campaign_14 | I755: Google Ads | J755: 2024-01-05 | K755: 1000 | L755: 1890 | M755: 75 | N755: 7 | O755: 53.39 | P755: 271.67 | Q755: =IFERROR(P755-O755, 0) -> 218.28 | R755: =P755-O755 -> 218.28 | S755: =R755/O755 -> 4.0884061 | T755: 3.97 | U755: 0.71 | V755: 7.63 | W755: =N755/M755 -> 0.093333333 | X755: =IF(P755>=4, "SCALE", IF(P755>=2, "MONITOR", IF(P755>=1, "OPTIMISE", "PAUSE"))) -> SCALE | Y755: =IF(K755<=300,"Low (100-300)", IF(K755<=500,"Mid (301-500)", IF(K755<=750,"High (501-750)", "Premium (751-1000)"))) -> Premium (751-1000)
A756: missnch127@gmail.com | B756: nikki | C756: holmes | D756: Gwynn Oak | E756: MD | F756: 3500 | G756: fhcb | H756: Campaign_3 | I756: Google Ads | J756: 2024-01-02 | K756: 200 | L756: 1615 | M756: 54 | N756: 0 | O756: 32.76 | P756: 0 | Q756: =IFERROR(P756-O756, 0) -> -32.76 | R756: =P756-O756 -> -32.76 | S756: =R756/O756 -> -1 | T756: 3.34 | U756: 0.61 | V756: 0 | W756: =N756/M756 -> 0 | X756: =IF(P756>=4, "SCALE", IF(P756>=2, "MONITOR", IF(P756>=1, "OPTIMISE", "PAUSE"))) -> PAUSE | Y756: =IF(K756<=300,"Low (100-300)", IF(K756<=500,"Mid (301-500)", IF(K756<=750,"High (501-750)", "Premium (751-1000)"))) -> Low (100-300)
A757: thartfield69@yahoo.com | B757: thomas | C757: hartfield | D757: Chicago | E757: IL | F757: 2500 | G757: centurion | H757: Campaign_7 | I757: Google Ads | J757: 2024-01-15 | K757: 100 | L757: 1164 | M757: 30 | N757: 2 | O757: 18.25 | P757: 94.43 | Q757: =IFERROR(P757-O757, 0) -> 76.18 | R757: =P757-O757 -> 76.18 | S757: =R757/O757 -> 4.1742466 | T757: 2.58 | U757: 0.61 | V757: 9.12 | W757: =N757/M757 -> 0.066666667 | X757: =IF(P757>=4, "SCALE", IF(P757>=2, "MONITOR", IF(P757>=1, "OPTIMISE", "PAUSE"))) -> SCALE | Y757: =IF(K757<=300,"Low (100-300)", IF(K757<=500,"Mid (301-500)", IF(K757<=750,"High (501-750)", "Premium (751-1000)"))) -> Low (100-300)
A758: hyltonheather@yahoo.com | B758: heather | C758: hylton | D758: Saint Petersb | E758: FL | F758: 2500 | G758: largo medical center | H758: Campaign_6 | I758: Google Ads | J758: 2024-01-31 | K758: 300 | L758: 1110 | M758: 22 | N758: 0 | O758: 9.21 | P758: 0 | Q758: =IFERROR(P758-O758, 0) -> -9.21 | R758: =P758-O758 -> -9.21 | S758: =R758/O758 -> -1 | T758: 1.98 | U758: 0.42 | V758: 0 | W758: =N758/M758 -> 0 | X758: =IF(P758>=4, "SCALE", IF(P758>=2, "MONITOR", IF(P758>=1, "OPTIMISE", "PAUSE"))) -> PAUSE | Y758: =IF(K758<=300,"Low (100-300)", IF(K758<=500,"Mid (301-500)", IF(K758<=750,"High (501-750)", "Premium (751-1000)"))) -> Low (100-300)
A759: daddio_wifeylife@yahoo.com | B759: angela | C759: cooper | D759: Fort Lauderda | E759: FL | F759: 2200 | G759: ckh business | H759: Campaign_14 | I759: Google Ads | J759: 2024-01-30 | K759: 300 | L759: 1310 | M759: 53 | N759: 1 | O759: 41.57 | P759: 35.6 | Q759: =IFERROR(P759-O759, 0) -> -5.97 | R759: =P759-O759 -> -5.97 | S759: =R759/O759 -> -0.14361318 | T759: 4.05 | U759: 0.78 | V759: 41.57 | W759: =N759/M759 -> 0.018867925 | X759: =IF(P759>=4, "SCALE", IF(P759>=2, "MONITOR", IF(P759>=1, "OPTIMISE", "PAUSE"))) -> SCALE | Y759: =IF(K759<=300,"Low (100-300)", IF(K759<=500,"Mid (301-500)", IF(K759<=750,"High (501-750)", "Premium (751-1000)"))) -> Low (100-300)
A760: kimber3662@yahoo.com | B760: kim | C760: tucker | D760: Lakewood | E760: CA | F760: 3000 | G760: ucla medical | H760: Campaign_7 | I760: Google Ads | J760: 2024-01-11 | K760: 1000 | L760: 1657 | M760: 69 | N760: 1 | O760: 57.73 | P760: 74.65 | Q760: =IFERROR(P760-O760, 0) -> 16.92 | R760: =P760-O760 -> 16.92 | S760: =R760/O760 -> 0.29308852 | T760: 4.16 | U760: 0.84 | V760: 57.73 | W760: =N760/M760 -> 0.014492754 | X760: =IF(P760>=4, "SCALE", IF(P760>=2, "MONITOR", IF(P760>=1, "OPTIMISE", "PAUSE"))) -> SCALE | Y760: =IF(K760<=300,"Low (100-300)", IF(K760<=500,"Mid (301-500)", IF(K760<=750,"High (501-750)", "Premium (751-1000)"))) -> Premium (751-1000)
A761: leisafortney@yahoo.com | B761: leisa | C761: fortney | D761: Lacey | E761: WA | F761: 4800 | G761: state of washington | H761: Campaign_17 | I761: Google Ads | J761: 2024-01-23 | K761: 1000 | L761: 1535 | M761: 51 | N761: 0 | O761: 31.74 | P761: 0 | Q761: =IFERROR(P761-O761, 0) -> -31.74 | R761: =P761-O761 -> -31.74 | S761: =R761/O761 -> -1 | T761: 3.32 | U761: 0.62 | V761: 0 | W761: =N761/M761 -> 0 | X761: =IF(P761>=4, "SCALE", IF(P761>=2, "MONITOR", IF(P761>=1, "OPTIMISE", "PAUSE"))) -> PAUSE | Y761: =IF(K761<=300,"Low (100-300)", IF(K761<=500,"Mid (301-500)", IF(K761<=750,"High (501-750)", "Premium (751-1000)"))) -> Premium (751-1000)
A762: stephanie.gustin5@yahoo.com | B762: stephanie | C762: gustin | D762: Greenfield | E762: IN | F762: 3000 | G762: dsa | H762: Campaign_10 | I762: Google Ads | J762: 2024-01-26 | K762: 100 | L762: 2224 | M762: 33 | N762: 0 | O762: 14.1 | P762: 0 | Q762: =IFERROR(P762-O762, 0) -> -14.1 | R762: =P762-O762 -> -14.1 | S762: =R762/O762 -> -1 | T762: 1.48 | U762: 0.43 | V762: 0 | W762: =N762/M762 -> 0 | X762: =IF(P762>=4, "SCALE", IF(P762>=2, "MONITOR", IF(P762>=1, "OPTIMISE", "PAUSE"))) -> PAUSE | Y762: =IF(K762<=300,"Low (100-300)", IF(K762<=500,"Mid (301-500)", IF(K762<=750,"High (501-750)", "Premium (751-1000)"))) -> Low (100-300)
A763: vlwilliam66@yahoo.com | B763: valerie | C763: williams | D763: Sacramento | E763: CA | F763: 2800 | G763: relationship skills center | H763: Campaign_13 | I763: Google Ads | J763: 2024-01-17 | K763: 500 | L763: 1390 | M763: 57 | N763: 0 | O763: 36.5 | P763: 0 | Q763: =IFERROR(P763-O763, 0) -> -36.5 | R763: =P763-O763 -> -36.5 | S763: =R763/O763 -> -1 | T763: 4.1 | U763: 0.64 | V763: 0 | W763: =N763/M763 -> 0 | X763: =IF(P763>=4, "SCALE", IF(P763>=2, "MONITOR", IF(P763>=1, "OPTIMISE", "PAUSE"))) -> PAUSE | Y763: =IF(K763<=300,"Low (100-300)", IF(K763<=500,"Mid (301-500)", IF(K763<=750,"High (501-750)", "Premium (751-1000)"))) -> Mid (301-500)
A764: monica_vance@yahoo.com | B764: monica | C764: vance | D764: Maple Heights | E764: OH | F764: 2349 | G764: bank of america | H764: Campaign_16 | I764: Google Ads | J764: 2024-01-21 | K764: 400 | L764: 639 | M764: 14 | N764: 0 | O764: 11.71 | P764: 0 | Q764: =IFERROR(P764-O764, 0) -> -11.71 | R764: =P764-O764 -> -11.71 | S764: =R764/O764 -> -1 | T764: 2.19 | U764: 0.84 | V764: 0 | W764: =N764/M764 -> 0 | X764: =IF(P764>=4, "SCALE", IF(P764>=2, "MONITOR", IF(P764>=1, "OPTIMISE", "PAUSE"))) -> PAUSE | Y764: =IF(K764<=300,"Low (100-300)", IF(K764<=500,"Mid (301-500)", IF(K764<=750,"High (501-750)", "Premium (751-1000)"))) -> Mid (301-500)
A765: prttythikgirl@gmail.com | B765: michael | C765: jones | D765: Sacramento | E765: CA | F765: 1500 | G765: sprint | H765: Campaign_14 | I765: Google Ads | J765: 2024-01-27 | K765: 700 | L765: 1570 | M765: 36 | N765: 1 | O765: 23.86 | P765: 68.13 | Q765: =IFERROR(P765-O765, 0) -> 44.27 | R765: =P765-O765 -> 44.27 | S765: =R765/O765 -> 1.8554065 | T765: 2.29 | U765: 0.66 | V765: 23.86 | W765: =N765/M765 -> 0.027777778 | X765: =IF(P765>=4, "SCALE", IF(P765>=2, "MONITOR", IF(P765>=1, "OPTIMISE", "PAUSE"))) -> SCALE | Y765: =IF(K765<=300,"Low (100-300)", IF(K765<=500,"Mid (301-500)", IF(K765<=750,"High (501-750)", "Premium (751-1000)"))) -> High (501-750)
A766: fitter14b@yahoo.com | B766: elbert | C766: grinstead | D766: Chicago | E766: IL | F766: 2200 | G766: dyesspeterson | H766: Campaign_16 | I766: Google Ads | J766: 2024-01-30 | K766: 600 | L766: 1053 | M766: 36 | N766: 0 | O766: 28.6 | P766: 0 | Q766: =IFERROR(P766-O766, 0) -> -28.6 | R766: =P766-O766 -> -28.6 | S766: =R766/O766 -> -1 | T766: 3.42 | U766: 0.79 | V766: 0 | W766: =N766/M766 -> 0 | X766: =IF(P766>=4, "SCALE", IF(P766>=2, "MONITOR", IF(P766>=1, "OPTIMISE", "PAUSE"))) -> PAUSE | Y766: =IF(K766<=300,"Low (100-300)", IF(K766<=500,"Mid (301-500)", IF(K766<=750,"High (501-750)", "Premium (751-1000)"))) -> High (501-750)
... A830: alyssaher@hotmail.com | B830: alyssa | C830: her | D830: Milwaukee | E830: WI | F830: 1535 | G830: columbia st. marys | H830: Campaign_18 | I830: Google Ads | J830: 2024-01-20 | K830: 700 | L830: 1643 | M830: 58 | N830: 1 | O830: 34.91 | P830: 61.45 | Q830: =IFERROR(P830-O830, 0) -> 26.54 | R830: =P830-O830 -> 26.54 | S830: =R830/O830 -> 0.76024062 | T830: 3.53 | U830: 0.6 | V830: 34.91 | W830: =N830/M830 -> 0.017241379 | X830: =IF(P830>=4, "SCALE", IF(P830>=2, "MONITOR", IF(P830>=1, "OPTIMISE", "PAUSE"))) -> SCALE | Y830: =IF(K830<=300,"Low (100-300)", IF(K830<=500,"Mid (301-500)", IF(K830<=750,"High (501-750)", "Premium (751-1000)"))) -> High (501-750)
A831: dh11982d@gmail.com | B831: dee | C831: harbour | D831: Meridian | E831: ID | F831: 4500 | G831: 0 | H831: Campaign_17 | I831: Google Ads | J831: 2024-01-22 | K831: 600 | L831: 1203 | M831: 30 | N831: 0 | O831: 21.7 | P831: 0 | Q831: =IFERROR(P831-O831, 0) -> -21.7 | R831: =P831-O831 -> -21.7 | S831: =R831/O831 -> -1 | T831: 2.49 | U831: 0.72 | V831: 0 | W831: =N831/M831 -> 0 | X831: =IF(P831>=4, "SCALE", IF(P831>=2, "MONITOR", IF(P831>=1, "OPTIMISE", "PAUSE"))) -> PAUSE | Y831: =IF(K831<=300,"Low (100-300)", IF(K831<=500,"Mid (301-500)", IF(K831<=750,"High (501-750)", "Premium (751-1000)"))) -> High (501-750)
A832: jlwverse@gmail.com | B832: jonathan | C832: williams | D832: San Antonio | E832: TX | F832: 1700 | G832: heb | H832: Campaign_7 | I832: Google Ads | J832: 2024-01-01 | K832: 700 | L832: 1953 | M832: 87 | N832: 2 | O832: 35.37 | P832: 84.61 | Q832: =IFERROR(P832-O832, 0) -> 49.24 | R832: =P832-O832 -> 49.24 | S832: =R832/O832 -> 1.3921402 | T832: 4.45 | U832: 0.41 | V832: 17.68 | W832: =N832/M832 -> 0.022988506 | X832: =IF(P832>=4, "SCALE", IF(P832>=2, "MONITOR", IF(P832>=1, "OPTIMISE", "PAUSE"))) -> SCALE | Y832: =IF(K832<=300,"Low (100-300)", IF(K832<=500,"Mid (301-500)", IF(K832<=750,"High (501-750)", "Premium (751-1000)"))) -> High (501-750)
A833: azesha_ryan@hotmail.com | B833: azesha | C833: ryan | D833: Portage | E833: IN | F833: 1500 | G833: massage envy | H833: Campaign_12 | I833: Google Ads | J833: 2024-01-30 | K833: 1000 | L833: 947 | M833: 20 | N833: 0 | O833: 16.34 | P833: 0 | Q833: =IFERROR(P833-O833, 0) -> -16.34 | R833: =P833-O833 -> -16.34 | S833: =R833/O833 -> -1 | T833: 2.11 | U833: 0.82 | V833: 0 | W833: =N833/M833 -> 0 | X833: =IF(P833>=4, "SCALE", IF(P833>=2, "MONITOR", IF(P833>=1, "OPTIMISE", "PAUSE"))) -> PAUSE | Y833: =IF(K833<=300,"Low (100-300)", IF(K833<=500,"Mid (301-500)", IF(K833<=750,"High (501-750)", "Premium (751-1000)"))) -> Premium (751-1000)
A834: myesha_stewart92@yahoo.com | B834: myesha | C834: stewart | D834: Beaumont | E834: TX | F834: 3000 | G834: ssi | H834: Campaign_9 | I834: Google Ads | J834: 2024-01-16 | K834: 700 | L834: 2210 | M834: 35 | N834: 1 | O834: 22.19 | P834: 49.84 | Q834: =IFERROR(P834-O834, 0) -> 27.65 | R834: =P834-O834 -> 27.65 | S834: =R834/O834 -> 1.2460568 | T834: 1.58 | U834: 0.63 | V834: 22.19 | W834: =N834/M834 -> 0.028571429 | X834: =IF(P834>=4, "SCALE", IF(P834>=2, "MONITOR", IF(P834>=1, "OPTIMISE", "PAUSE"))) -> SCALE | Y834: =IF(K834<=300,"Low (100-300)", IF(K834<=500,"Mid (301-500)", IF(K834<=750,"High (501-750)", "Premium (751-1000)"))) -> High (501-750)
A835: carolmccomber@yahoo.com | B835: carol | C835: mccomber | D835: Lansing | E835: MI | F835: 3500 | G835: ryder loc | H835: Campaign_12 | I835: Google Ads | J835: 2024-01-14 | K835: 300 | L835: 1491 | M835: 26 | N835: 0 | O835: 16.39 | P835: 0 | Q835: =IFERROR(P835-O835, 0) -> -16.39 | R835: =P835-O835 -> -16.39 | S835: =R835/O835 -> -1 | T835: 1.74 | U835: 0.63 | V835: 0 | W835: =N835/M835 -> 0 | X835: =IF(P835>=4, "SCALE", IF(P835>=2, "MONITOR", IF(P835>=1, "OPTIMISE", "PAUSE"))) -> PAUSE | Y835: =IF(K835<=300,"Low (100-300)", IF(K835<=500,"Mid (301-500)", IF(K835<=750,"High (501-750)", "Premium (751-1000)"))) -> Low (100-300)
A836: fpvaskejr@yahoo.com | B836: francis | C836: vaske | D836: Sardinia | E836: OH | F836: 1600 | G836: state of ohio | H836: Campaign_7 | I836: Google Ads | J836: 2024-01-27 | K836: 400 | L836: 2428 | M836: 72 | N836: 2 | O836: 37.66 | P836: 77.73 | Q836: =IFERROR(P836-O836, 0) -> 40.07 | R836: =P836-O836 -> 40.07 | S836: =R836/O836 -> 1.0639936 | T836: 2.97 | U836: 0.52 | V836: 18.83 | W836: =N836/M836 -> 0.027777778 | X836: =IF(P836>=4, "SCALE", IF(P836>=2, "MONITOR", IF(P836>=1, "OPTIMISE", "PAUSE"))) -> SCALE | Y836: =IF(K836<=300,"Low (100-300)", IF(K836<=500,"Mid (301-500)", IF(K836<=750,"High (501-750)", "Premium (751-1000)"))) -> Mid (301-500)
A837: dominicankidzz@hotmail.com | B837: fernando | C837: santos | D837: Lutz | E837: FL | F837: 1625 | G837: tampa general hospital | H837: Campaign_4 | I837: Google Ads | J837: 2024-01-28 | K837: 800 | L837: 1685 | M837: 71 | N837: 3 | O837: 39.75 | P837: 122.06 | Q837: =IFERROR(P837-O837, 0) -> 82.31 | R837: =P837-O837 -> 82.31 | S837: =R837/O837 -> 2.0706918 | T837: 4.21 | U837: 0.56 | V837: 13.25 | W837: =N837/M837 -> 0.042253521 | X837: =IF(P837>=4, "SCALE", IF(P837>=2, "MONITOR", IF(P837>=1, "OPTIMISE", "PAUSE"))) -> SCALE | Y837: =IF(K837<=300,"Low (100-300)", IF(K837<=500,"Mid (301-500)", IF(K837<=750,"High (501-750)", "Premium (751-1000)"))) -> Premium (751-1000)
A838: ckburk@hotmail.com | B838: cheryll | C838: burk | D838: Glendora | E838: CA | F838: 3200 | G838: retired | H838: Campaign_6 | I838: Google Ads | J838: 2024-01-11 | K838: 600 | L838: 2080 | M838: 78 | N838: 0 | O838: 40.11 | P838: 0 | Q838: =IFERROR(P838-O838, 0) -> -40.11 | R838: =P838-O838 -> -40.11 | S838: =R838/O838 -> -1 | T838: 3.75 | U838: 0.51 | V838: 0 | W838: =N838/M838 -> 0 | X838: =IF(P838>=4, "SCALE", IF(P838>=2, "MONITOR", IF(P838>=1, "OPTIMISE", "PAUSE"))) -> PAUSE | Y838: =IF(K838<=300,"Low (100-300)", IF(K838<=500,"Mid (301-500)", IF(K838<=750,"High (501-750)", "Premium (751-1000)"))) -> High (501-750)
A839: rachel1779@hotmail.com | B839: rachel | C839: jacobs | D839: West Bend | E839: WI | F839: 1535 | G839: mikkelson | H839: Campaign_9 | I839: Google Ads | J839: 2024-01-06 | K839: 400 | L839: 943 | M839: 29 | N839: 0 | O839: 18.23 | P839: 0 | Q839: =IFERROR(P839-O839, 0) -> -18.23 | R839: =P839-O839 -> -18.23 | S839: =R839/O839 -> -1 | T839: 3.08 | U839: 0.63 | V839: 0 | W839: =N839/M839 -> 0 | X839: =IF(P839>=4, "SCALE", IF(P839>=2, "MONITOR", IF(P839>=1, "OPTIMISE", "PAUSE"))) -> PAUSE | Y839: =IF(K839<=300,"Low (100-300)", IF(K839<=500,"Mid (301-500)", IF(K839<=750,"High (501-750)", "Premium (751-1000)"))) -> Mid (301-500)
A840: pascott33@yahoo.com | B840: melissa | C840: ross | D840: Simpsonville | E840: SC | F840: 3800 | G840: ssi | H840: Campaign_12 | I840: Google Ads | J840: 2024-01-02 | K840: 800 | L840: 1907 | M840: 34 | N840: 3 | O840: 19.62 | P840: 172.73 | Q840: =IFERROR(P840-O840, 0) -> 153.11 | R840: =P840-O840 -> 153.11 | S840: =R840/O840 -> 7.8037717 | T840: 1.78 | U840: 0.58 | V840: 6.54 | W840: =N840/M840 -> 0.088235294 | X840: =IF(P840>=4, "SCALE", IF(P840>=2, "MONITOR", IF(P840>=1, "OPTIMISE", "PAUSE"))) -> SCALE | Y840: =IF(K840<=300,"Low (100-300)", IF(K840<=500,"Mid (301-500)", IF(K840<=750,"High (501-750)", "Premium (751-1000)"))) -> Premium (751-1000)
A841: k_little17@hotmail.com | B841: kemisha | C841: little | D841: Hartford | E841: CT | F841: 1500 | G841: rr donelley | H841: Campaign_7 | I841: Google Ads | J841: 2024-01-26 | K841: 100 | L841: 1467 | M841: 62 | N841: 2 | O841: 26.25 | P841: 140.31 | Q841: =IFERROR(P841-O841, 0) -> 114.06 | R841: =P841-O841 -> 114.06 | S841: =R841/O841 -> 4.3451429 | T841: 4.23 | U841: 0.42 | V841: 13.12 | W841: =N841/M841 -> 0.032258065 | X841: =IF(P841>=4, "SCALE", IF(P841>=2, "MONITOR", IF(P841>=1, "OPTIMISE", "PAUSE"))) -> SCALE | Y841: =IF(K841<=300,"Low (100-300)", IF(K841<=500,"Mid (301-500)", IF(K841<=750,"High (501-750)", "Premium (751-1000)"))) -> Low (100-300)
A842: mztoya337@yahoo.com | B842: marquis | C842: ford | D842: Lafayette | E842: LA | F842: 1500 | G842: lafayette general hospital | H842: Campaign_17 | I842: Google Ads | J842: 2024-01-19 | K842: 800 | L842: 689 | M842: 21 | N842: 2 | O842: 16.83 | P842: 74.47 | Q842: =IFERROR(P842-O842, 0) -> 57.64 | R842: =P842-O842 -> 57.64 | S842: =R842/O842 -> 3.4248366 | T842: 3.05 | U842: 0.8 | V842: 8.41 | W842: =N842/M842 -> 0.095238095 | X842: =IF(P842>=4, "SCALE", IF(P842>=2, "MONITOR", IF(P842>=1, "OPTIMISE", "PAUSE"))) -> SCALE | Y842: =IF(K842<=300,"Low (100-300)", IF(K842<=500,"Mid (301-500)", IF(K842<=750,"High (501-750)", "Premium (751-1000)"))) -> Premium (751-1000)
A843: jhbales2727@yahoo.com | B843: john | C843: bales | D843: Cleves | E843: OH | F843: 3000 | G843: iowa steak | H843: Campaign_1 | I843: Google Ads | J843: 2024-01-07 | K843: 400 | L843: 673 | M843: 16 | N843: 1 | O843: 11.29 | P843: 72.48 | Q843: =IFERROR(P843-O843, 0) -> 61.19 | R843: =P843-O843 -> 61.19 | S843: =R843/O843 -> 5.4198406 | T843: 2.38 | U843: 0.71 | V843: 11.29 | W843: =N843/M843 -> 0.0625 | X843: =IF(P843>=4, "SCALE", IF(P843>=2, "MONITOR", IF(P843>=1, "OPTIMISE", "PAUSE"))) -> SCALE | Y843: =IF(K843<=300,"Low (100-300)", IF(K843<=500,"Mid (301-500)", IF(K843<=750,"High (501-750)", "Premium (751-1000)"))) -> Mid (301-500)
... A1933: kmcwane@yahoo.com | B1933: kim | C1933: mcwane | D1933: Killeen | E1933: TX | F1933: 1500 | G1933: wells fargo | H1933: Campaign_4 | I1933: Google Ads | J1933: 2024-01-22 | K1933: 200 | L1933: 554 | M1933: 11 | N1933: 0 | O1933: 4.51 | P1933: 0 | Q1933: =IFERROR(P1933-O1933, 0) -> -4.51 | R1933: =P1933-O1933 -> -4.51 | S1933: =R1933/O1933 -> -1 | T1933: 1.99 | U1933: 0.41 | V1933: 0 | W1933: =N1933/M1933 -> 0 | X1933: =IF(P1933>=4, "SCALE", IF(P1933>=2, "MONITOR", IF(P1933>=1, "OPTIMISE", "PAUSE"))) -> PAUSE | Y1933: =IF(K1933<=300,"Low (100-300)", IF(K1933<=500,"Mid (301-500)", IF(K1933<=750,"High (501-750)", "Premium (751-1000)"))) -> Low (100-300)
A1934: teyhall@gmail.com | B1934: teylor | C1934: hall | D1934: Rohnert Park | E1934: CA | F1934: 1818 | G1934: 0 | H1934: Campaign_13 | I1934: Google Ads | J1934: 2024-01-05 | K1934: 400 | L1934: 615 | M1934: 23 | N1934: 0 | O1934: 17.08 | P1934: 0 | Q1934: =IFERROR(P1934-O1934, 0) -> -17.08 | R1934: =P1934-O1934 -> -17.08 | S1934: =R1934/O1934 -> -1 | T1934: 3.74 | U1934: 0.74 | V1934: 0 | W1934: =N1934/M1934 -> 0 | X1934: =IF(P1934>=4, "SCALE", IF(P1934>=2, "MONITOR", IF(P1934>=1, "OPTIMISE", "PAUSE"))) -> PAUSE | Y1934: =IF(K1934<=300,"Low (100-300)", IF(K1934<=500,"Mid (301-500)", IF(K1934<=750,"High (501-750)", "Premium (751-1000)"))) -> Mid (301-500)
A1935: jle522000@yahoo.com | B1935: janet | C1935: emmick | D1935: Washington | E1935: IN | F1935: 1516 | G1935: government | H1935: Campaign_6 | I1935: Google Ads | J1935: 2024-01-17 | K1935: 400 | L1935: 1613 | M1935: 54 | N1935: 5 | O1935: 43.45 | P1935: 367.45 | Q1935: =IFERROR(P1935-O1935, 0) -> 324 | R1935: =P1935-O1935 -> 324 | S1935: =R1935/O1935 -> 7.456847 | T1935: 3.35 | U1935: 0.8 | V1935: 8.69 | W1935: =N1935/M1935 -> 0.092592593 | X1935: =IF(P1935>=4, "SCALE", IF(P1935>=2, "MONITOR", IF(P1935>=1, "OPTIMISE", "PAUSE"))) -> SCALE | Y1935: =IF(K1935<=300,"Low (100-300)", IF(K1935<=500,"Mid (301-500)", IF(K1935<=750,"High (501-750)", "Premium (751-1000)"))) -> Mid (301-500)
A1936: aminah22@hotmail.com | B1936: aminah | C1936: mears | D1936: Fontana | E1936: CA | F1936: 3116 | G1936: en valley | H1936: Campaign_9 | I1936: Google Ads | J1936: 2024-01-14 | K1936: 1000 | L1936: 2059 | M1936: 32 | N1936: 3 | O1936: 13.53 | P1936: 160.45 | Q1936: =IFERROR(P1936-O1936, 0) -> 146.92 | R1936: =P1936-O1936 -> 146.92 | S1936: =R1936/O1936 -> 10.858832 | T1936: 1.55 | U1936: 0.42 | V1936: 4.51 | W1936: =N1936/M1936 -> 0.09375 | X1936: =IF(P1936>=4, "SCALE", IF(P1936>=2, "MONITOR", IF(P1936>=1, "OPTIMISE", "PAUSE"))) -> SCALE | Y1936: =IF(K1936<=300,"Low (100-300)", IF(K1936<=500,"Mid (301-500)", IF(K1936<=750,"High (501-750)", "Premium (751-1000)"))) -> Premium (751-1000)
A1937: peter_johnson697@yahoo.com | B1937: ann | C1937: talor | D1937: Birmingham | E1937: AL | F1937: 1733 | G1937: ann taylor | H1937: Campaign_19 | I1937: Google Ads | J1937: 2024-01-02 | K1937: 200 | L1937: 1640 | M1937: 69 | N1937: 3 | O1937: 57.84 | P1937: 197.71 | Q1937: =IFERROR(P1937-O1937, 0) -> 139.87 | R1937: =P1937-O1937 -> 139.87 | S1937: =R1937/O1937 -> 2.4182227 | T1937: 4.21 | U1937: 0.84 | V1937: 19.28 | W1937: =N1937/M1937 -> 0.043478261 | X1937: =IF(P1937>=4, "SCALE", IF(P1937>=2, "MONITOR", IF(P1937>=1, "OPTIMISE", "PAUSE"))) -> SCALE | Y1937: =IF(K1937<=300,"Low (100-300)", IF(K1937<=500,"Mid (301-500)", IF(K1937<=750,"High (501-750)", "Premium (751-1000)"))) -> Low (100-300)
A1938: itserika21@gmail.com | B1938: erika | C1938: felipe | D1938: Hollywood | E1938: FL | F1938: 1000 | G1938: h. d. smith | H1938: Campaign_19 | I1938: Google Ads | J1938: 2024-01-25 | K1938: 200 | L1938: 1844 | M1938: 52 | N1938: 0 | O1938: 41.58 | P1938: 0 | Q1938: =IFERROR(P1938-O1938, 0) -> -41.58 | R1938: =P1938-O1938 -> -41.58 | S1938: =R1938/O1938 -> -1 | T1938: 2.82 | U1938: 0.8 | V1938: 0 | W1938: =N1938/M1938 -> 0 | X1938: =IF(P1938>=4, "SCALE", IF(P1938>=2, "MONITOR", IF(P1938>=1, "OPTIMISE", "PAUSE"))) -> PAUSE | Y1938: =IF(K1938<=300,"Low (100-300)", IF(K1938<=500,"Mid (301-500)", IF(K1938<=750,"High (501-750)", "Premium (751-1000)"))) -> Low (100-300)
A1939: vlmobley@aol.com | B1939: virgie | C1939: mobley | D1939: Killeen | E1939: TX | F1939: 2500 | G1939: us army | H1939: Campaign_9 | I1939: Google Ads | J1939: 2024-01-14 | K1939: 300 | L1939: 1163 | M1939: 35 | N1939: 0 | O1939: 24.02 | P1939: 0 | Q1939: =IFERROR(P1939-O1939, 0) -> -24.02 | R1939: =P1939-O1939 -> -24.02 | S1939: =R1939/O1939 -> -1 | T1939: 3.01 | U1939: 0.69 | V1939: 0 | W1939: =N1939/M1939 -> 0 | X1939: =IF(P1939>=4, "SCALE", IF(P1939>=2, "MONITOR", IF(P1939>=1, "OPTIMISE", "PAUSE"))) -> PAUSE | Y1939: =IF(K1939<=300,"Low (100-300)", IF(K1939<=500,"Mid (301-500)", IF(K1939<=750,"High (501-750)", "Premium (751-1000)"))) -> Low (100-300)
A1940: jjlroksolid@hotmail.com | B1940: joseph | C1940: litcher | D1940: Clearwater | E1940: FL | F1940: 3692 | G1940: self | H1940: Campaign_11 | I1940: Google Ads | J1940: 2024-01-25 | K1940: 800 | L1940: 1726 | M1940: 66 | N1940: 0 | O1940: 31.79 | P1940: 0 | Q1940: =IFERROR(P1940-O1940, 0) -> -31.79 | R1940: =P1940-O1940 -> -31.79 | S1940: =R1940/O1940 -> -1 | T1940: 3.82 | U1940: 0.48 | V1940: 0 | W1940: =N1940/M1940 -> 0 | X1940: =IF(P1940>=4, "SCALE", IF(P1940>=2, "MONITOR", IF(P1940>=1, "OPTIMISE", "PAUSE"))) -> PAUSE | Y1940: =IF(K1940<=300,"Low (100-300)", IF(K1940<=500,"Mid (301-500)", IF(K1940<=750,"High (501-750)", "Premium (751-1000)"))) -> Premium (751-1000)
A1941: helper_dough_girl@hotmail.com | B1941: john | C1941: harwood | D1941: Helper | E1941: UT | F1941: 1384 | G1941: wendys | H1941: Campaign_4 | I1941: Google Ads | J1941: 2024-01-04 | K1941: 800 | L1941: 1547 | M1941: 62 | N1941: 5 | O1941: 42.21 | P1941: 279.25 | Q1941: =IFERROR(P1941-O1941, 0) -> 237.04 | R1941: =P1941-O1941 -> 237.04 | S1941: =R1941/O1941 -> 5.6157309 | T1941: 4.01 | U1941: 0.68 | V1941: 8.44 | W1941: =N1941/M1941 -> 0.080645161 | X1941: =IF(P1941>=4, "SCALE", IF(P1941>=2, "MONITOR", IF(P1941>=1, "OPTIMISE", "PAUSE"))) -> SCALE | Y1941: =IF(K1941<=300,"Low (100-300)", IF(K1941<=500,"Mid (301-500)", IF(K1941<=750,"High (501-750)", "Premium (751-1000)"))) -> Premium (751-1000)
A1942: christinevogt@hotmail.com | B1942: christine | C1942: vogt | D1942: Crystal Lake | E1942: IL | F1942: 4000 | G1942: romp | H1942: Campaign_12 | I1942: Google Ads | J1942: 2024-01-19 | K1942: 100 | L1942: 2184 | M1942: 44 | N1942: 0 | O1942: 35.45 | P1942: 0 | Q1942: =IFERROR(P1942-O1942, 0) -> -35.45 | R1942: =P1942-O1942 -> -35.45 | S1942: =R1942/O1942 -> -1 | T1942: 2.01 | U1942: 0.81 | V1942: 0 | W1942: =N1942/M1942 -> 0 | X1942: =IF(P1942>=4, "SCALE", IF(P1942>=2, "MONITOR", IF(P1942>=1, "OPTIMISE", "PAUSE"))) -> PAUSE | Y1942: =IF(K1942<=300,"Low (100-300)", IF(K1942<=500,"Mid (301-500)", IF(K1942<=750,"High (501-750)", "Premium (751-1000)"))) -> Low (100-300)
A1943: prdnice@gmail.com | B1943: phyllis | C1943: dorsey | D1943: Rayville | E1943: LA | F1943: 2306 | G1943: richland parish schools | H1943: Campaign_18 | I1943: Google Ads | J1943: 2024-01-02 | K1943: 100 | L1943: 2115 | M1943: 90 | N1943: 8 | O1943: 37.78 | P1943: 533.95 | Q1943: =IFERROR(P1943-O1943, 0) -> 496.17 | R1943: =P1943-O1943 -> 496.17 | S1943: =R1943/O1943 -> 13.133139 | T1943: 4.26 | U1943: 0.42 | V1943: 4.72 | W1943: =N1943/M1943 -> 0.088888889 | X1943: =IF(P1943>=4, "SCALE", IF(P1943>=2, "MONITOR", IF(P1943>=1, "OPTIMISE", "PAUSE"))) -> SCALE | Y1943: =IF(K1943<=300,"Low (100-300)", IF(K1943<=500,"Mid (301-500)", IF(K1943<=750,"High (501-750)", "Premium (751-1000)"))) -> Low (100-300)
...

Sheet INSIGHTS
A1: PERFORMANCE MARKETING — CAMPAIGN ANALYSIS REPORT
A2: OVERALL SUMMARY
A3: Total Revenue | B3: Total Cost | C3: Total Profit | D3: Overall ROAS | E3: Total Conv. | F3: PAUSE Count | G3: SCALE Count
A4: =SUM(PT_Campaign!B2:B21) -> 552176.52 | B4: =SUM(PT_Campaign!C2:C21) -> 170173.18 | C4: =SUM(PT_Campaign!E2:E21) -> 382003.34 | D4: =IFERROR(A4/B4,0) -> 3.2447917 | E4: =SUM(PT_Campaign!D2:D21) -> 9955 | F4: =COUNTIF(PT_Campaign!J2:J21,"PAUSE") -> 2 | G4: =COUNTIF(PT_Campaign!J2:J21,"SCALE") -> 11
A6: TOP 5 PERFORMING CAMPAIGNS
A7: Rank | B7: Campaign | C7: Revenue | D7: Cost | E7: ROAS | F7: Profit | G7: Conversions | H7: ROI%
A8: 1 | B8: =INDEX(PT_Campaign!$A$2:$A$21,MATCH(LARGE(PT_Campaign!$G$2:$G$21,A8),PT_Campaign!$G$2:$G$21,0)) -> Campaign_1 | C8: =INDEX(PT_Campaign!$B$2:$B$21,MATCH(LARGE(PT_Campaign!$G$2:$G$21,A8),PT_Campaign!$G$2:$G$21,0)) -> 29904.15 | D8: =INDEX(PT_Campaign!$C$2:$C$21,MATCH(LARGE(PT_Campaign!$G$2:$G$21,A8),PT_Campaign!$G$2:$G$21,0)) -> 7960.53 | E8: =IFERROR(C8/D8,0) -> 3.7565526 | F8: =C8-D8 -> 21943.62 | G8: =IFERROR(VLOOKUP(B8,PT_Campaign!$A$2:$I$21,4,0),0) -> 530 | H8: =IFERROR((C8-D8)/D8*100,0) -> 275.65526
A9: 2 | B9: =INDEX(PT_Campaign!$A$2:$A$21,MATCH(LARGE(PT_Campaign!$G$2:$G$21,A9),PT_Campaign!$G$2:$G$21,0)) -> Campaign_8 | C9: =INDEX(PT_Campaign!$B$2:$B$21,MATCH(LARGE(PT_Campaign!$G$2:$G$21,A9),PT_Campaign!$G$2:$G$21,0)) -> 32379.51 | D9: =INDEX(PT_Campaign!$C$2:$C$21,MATCH(LARGE(PT_Campaign!$G$2:$G$21,A9),PT_Campaign!$G$2:$G$21,0)) -> 8866.27 | E9: =IFERROR(C9/D9,0) -> 3.6519878 | F9: =C9-D9 -> 23513.24 | G9: =IFERROR(VLOOKUP(B9,PT_Campaign!$A$2:$I$21,4,0),0) -> 577 | H9: =IFERROR((C9-D9)/D9*100,0) -> 265.19878
A10: 3 | B10: =INDEX(PT_Campaign!$A$2:$A$21,MATCH(LARGE(PT_Campaign!$G$2:$G$21,A10),PT_Campaign!$G$2:$G$21,0)) -> Campaign_6 | C10: =INDEX(PT_Campaign!$B$2:$B$21,MATCH(LARGE(PT_Campaign!$G$2:$G$21,A10),PT_Campaign!$G$2:$G$21,0)) -> 26591.14 | D10: =INDEX(PT_Campaign!$C$2:$C$21,MATCH(LARGE(PT_Campaign!$G$2:$G$21,A10),PT_Campaign!$G$2:$G$21,0)) -> 7475.48 | E10: =IFERROR(C10/D10,0) -> 3.5571147 | F10: =C10-D10 -> 19115.66 | G10: =IFERROR(VLOOKUP(B10,PT_Campaign!$A$2:$I$21,4,0),0) -> 485 | H10: =IFERROR((C10-D10)/D10*100,0) -> 255.71147
A11: 4 | B11: =INDEX(PT_Campaign!$A$2:$A$21,MATCH(LARGE(PT_Campaign!$G$2:$G$21,A11),PT_Campaign!$G$2:$G$21,0)) -> Campaign_17 | C11: =INDEX(PT_Campaign!$B$2:$B$21,MATCH(LARGE(PT_Campaign!$G$2:$G$21,A11),PT_Campaign!$G$2:$G$21,0)) -> 29099.18 | D11: =INDEX(PT_Campaign!$C$2:$C$21,MATCH(LARGE(PT_Campaign!$G$2:$G$21,A11),PT_Campaign!$G$2:$G$21,0)) -> 8198.2 | E11: =IFERROR(C11/D11,0) -> 3.5494596 | F11: =C11-D11 -> 20900.98 | G11: =IFERROR(VLOOKUP(B11,PT_Campaign!$A$2:$I$21,4,0),0) -> 524 | H11: =IFERROR((C11-D11)/D11*100,0) -> 254.94596
A12: 5 | B12: =INDEX(PT_Campaign!$A$2:$A$21,MATCH(LARGE(PT_Campaign!$G$2:$G$21,A12),PT_Campaign!$G$2:$G$21,0)) -> Campaign_3 | C12: =INDEX(PT_Campaign!$B$2:$B$21,MATCH(LARGE(PT_Campaign!$G$2:$G$21,A12),PT_Campaign!$G$2:$G$21,0)) -> 28563.44 | D12: =INDEX(PT_Campaign!$C$2:$C$21,MATCH(LARGE(PT_Campaign!$G$2:$G$21,A12),PT_Campaign!$G$2:$G$21,0)) -> 8114.7 | E12: =IFERROR(C12/D12,0) -> 3.5199625 | F12: =C12-D12 -> 20448.74 | G12: =IFERROR(VLOOKUP(B12,PT_Campaign!$A$2:$I$21,4,0),0) -> 513 | H12: =IFERROR((C12-D12)/D12*100,0) -> 251.99625
A14: WORST 5 CAMPAIGNS — PAUSE IMMEDIATELY
A15: Rank | B15: Campaign | C15: Revenue | D15: Cost | E15: ROAS | F15: Profit | G15: Conversions | H15: ROI%
A16: 1 | B16: =INDEX(PT_Campaign!$A$2:$A$21,MATCH(SMALL(PT_Campaign!$G$2:$G$21,A16),PT_Campaign!$G$2:$G$21,0)) -> Campaign_20 | C16: =INDEX(PT_Campaign!$B$2:$B$21,MATCH(SMALL(PT_Campaign!$G$2:$G$21,A16),PT_Campaign!$G$2:$G$21,0)) -> 22153.03 | D16: =INDEX(PT_Campaign!$C$2:$C$21,MATCH(SMALL(PT_Campaign!$G$2:$G$21,A16),PT_Campaign!$G$2:$G$21,0)) -> 8651.58 | E16: =IFERROR(C16/D16,0) -> 2.5605762 | F16: =C16-D16 -> 13501.45 | G16: =IFERROR(VLOOKUP(B16,PT_Campaign!$A$2:$I$21,4,0),0) -> 397 | H16: =IFERROR((C16-D16)/D16*100,0) -> 156.05762
A17: 2 | B17: =INDEX(PT_Campaign!$A$2:$A$21,MATCH(SMALL(PT_Campaign!$G$2:$G$21,A17),PT_Campaign!$G$2:$G$21,0)) -> Campaign_14 | C17: =INDEX(PT_Campaign!$B$2:$B$21,MATCH(SMALL(PT_Campaign!$G$2:$G$21,A17),PT_Campaign!$G$2:$G$21,0)) -> 20658.27 | D17: =INDEX(PT_Campaign!$C$2:$C$21,MATCH(SMALL(PT_Campaign!$G$2:$G$21,A17),PT_Campaign!$G$2:$G$21,0)) -> 7544.56 | E17: =IFERROR(C17/D17,0) -> 2.7381676 | F17: =C17-D17 -> 13113.71 | G17: =IFERROR(VLOOKUP(B17,PT_Campaign!$A$2:$I$21,4,0),0) -> 370 | H17: =IFERROR((C17-D17)/D17*100,0) -> 173.81676
A18: 3 | B18: =INDEX(PT_Campaign!$A$2:$A$21,MATCH(SMALL(PT_Campaign!$G$2:$G$21,A18),PT_Campaign!$G$2:$G$21,0)) -> Campaign_7 | C18: =INDEX(PT_Campaign!$B$2:$B$21,MATCH(SMALL(PT_Campaign!$G$2:$G$21,A18),PT_Campaign!$G$2:$G$21,0)) -> 27744.73 | D18: =INDEX(PT_Campaign!$C$2:$C$21,MATCH(SMALL(PT_Campaign!$G$2:$G$21,A18),PT_Campaign!$G$2:$G$21,0)) -> 9128.92 | E18: =IFERROR(C18/D18,0) -> 3.0392127 | F18: =C18-D18 -> 18615.81 | G18: =IFERROR(VLOOKUP(B18,PT_Campaign!$A$2:$I$21,4,0),0) -> 490 | H18: =IFERROR((C18-D18)/D18*100,0) -> 203.92127
A19: 4 | B19: =INDEX(PT_Campaign!$A$2:$A$21,MATCH(SMALL(PT_Campaign!$G$2:$G$21,A19),PT_Campaign!$G$2:$G$21,0)) -> Campaign_10 | C19: =INDEX(PT_Campaign!$B$2:$B$21,MATCH(SMALL(PT_Campaign!$G$2:$G$21,A19),PT_Campaign!$G$2:$G$21,0)) -> 25920.03 | D19: =INDEX(PT_Campaign!$C$2:$C$21,MATCH(SMALL(PT_Campaign!$G$2:$G$21,A19),PT_Campaign!$G$2:$G$21,0)) -> 8454.75 | E19: =IFERROR(C19/D19,0) -> 3.0657358 | F19: =C19-D19 -> 17465.28 | G19: =IFERROR(VLOOKUP(B19,PT_Campaign!$A$2:$I$21,4,0),0) -> 485 | H19: =IFERROR((C19-D19)/D19*100,0) -> 206.57358
A20: 5 | B20: =INDEX(PT_Campaign!$A$2:$A$21,MATCH(SMALL(PT_Campaign!$G$2:$G$21,A20),PT_Campaign!$G$2:$G$21,0)) -> Campaign_11 | C20: =INDEX(PT_Campaign!$B$2:$B$21,MATCH(SMALL(PT_Campaign!$G$2:$G$21,A20),PT_Campaign!$G$2:$G$21,0)) -> 28711.12 | D20: =INDEX(PT_Campaign!$C$2:$C$21,MATCH(SMALL(PT_Campaign!$G$2:$G$21,A20),PT_Campaign!$G$2:$G$21,0)) -> 9293.97 | E20: =IFERROR(C20/D20,0) -> 3.0892202 | F20: =C20-D20 -> 19417.15 | G20: =IFERROR(VLOOKUP(B20,PT_Campaign!$A$2:$I$21,4,0),0) -> 525 | H20: =IFERROR((C20-D20)/D20*100,0) -> 208.92202

Sheet PT_Campaign
A1: Row Labels | B1: Sum of revenue | C1: Sum of cost | D1: Sum of conversions | E1: Sum of Profit | F1: Average of ROAS | G1: ROAS Check | H1: Profit Check | I1: ROI% | J1: Status
A2: Campaign_1 | B2: 29904.15 | C2: 7960.53 | D2: 530 | E2: 21943.62 | F2: 73.1454 | G2: =IFERROR(B2/C2,0) -> 3.7565526 | H2: =B2-C2 -> 21943.62 | I2: =IFERROR((B2-C2)/C2*100,0) -> 275.65526 | J2: =IF(G2>=3.15,"SCALE",IF(G2>=3,"MONITOR",IF(G2>=2.8,"OPTIMISE","PAUSE"))) -> SCALE
A3: Campaign_10 | B3: 25920.03 | C3: 8454.75 | D3: 485 | E3: 17465.28 | F3: 58.024186 | G3: =IFERROR(B3/C3,0) -> 3.0657358 | H3: =B3-C3 -> 17465.28 | I3: =IFERROR((B3-C3)/C3*100,0) -> 206.57358 | J3: =IF(G3>=3.15,"SCALE",IF(G3>=3,"MONITOR",IF(G3>=2.8,"OPTIMISE","PAUSE"))) -> MONITOR
A4: Campaign_11 | B4: 28711.12 | C4: 9293.97 | D4: 525 | E4: 19417.15 | F4: 59.379664 | G4: =IFERROR(B4/C4,0) -> 3.0892202 | H4: =B4-C4 -> 19417.15 | I4: =IFERROR((B4-C4)/C4*100,0) -> 208.92202 | J4: =IF(G4>=3.15,"SCALE",IF(G4>=3,"MONITOR",IF(G4>=2.8,"OPTIMISE","PAUSE"))) -> MONITOR
A5: Campaign_12 | B5: 24986.1 | C5: 8060.01 | D5: 455 | E5: 16926.09 | F5: 56.608997 | G5: =IFERROR(B5/C5,0) -> 3.1000086 | H5: =B5-C5 -> 16926.09 | I5: =IFERROR((B5-C5)/C5*100,0) -> 210.00086 | J5: =IF(G5>=3.15,"SCALE",IF(G5>=3,"MONITOR",IF(G5>=2.8,"OPTIMISE","PAUSE"))) -> MONITOR
A6: Campaign_13 | B6: 26333.13 | C6: 8504.8 | D6: 472 | E6: 17828.33 | F6: 56.959521 | G6: =IFERROR(B6/C6,0) -> 3.0962668 | H6: =B6-C6 -> 17828.33 | I6: =IFERROR((B6-C6)/C6*100,0) -> 209.62668 | J6: =IF(G6>=3.15,"SCALE",IF(G6>=3,"MONITOR",IF(G6>=2.8,"OPTIMISE","PAUSE"))) -> MONITOR
A7: Campaign_14 | B7: 20658.27 | C7: 7544.56 | D7: 370 | E7: 13113.71 | F7: 47.341913 | G7: =IFERROR(B7/C7,0) -> 2.7381676 | H7: =B7-C7 -> 13113.71 | I7: =IFERROR((B7-C7)/C7*100,0) -> 173.81676 | J7: =IF(G7>=3.15,"SCALE",IF(G7>=3,"MONITOR",IF(G7>=2.8,"OPTIMISE","PAUSE"))) -> PAUSE
A8: Campaign_15 | B8: 28813.24 | C8: 8563.09 | D8: 521 | E8: 20250.15 | F8: 65.961401 | G8: =IFERROR(B8/C8,0) -> 3.3648181 | H8: =B8-C8 -> 20250.15 | I8: =IFERROR((B8-C8)/C8*100,0) -> 236.48181 | J8: =IF(G8>=3.15,"SCALE",IF(G8>=3,"MONITOR",IF(G8>=2.8,"OPTIMISE","PAUSE"))) -> SCALE
A9: Campaign_16 | B9: 24653.74 | C9: 7829.39 | D9: 452 | E9: 16824.35 | F9: 59.240669 | G9: =IFERROR(B9/C9,0) -> 3.1488711 | H9: =B9-C9 -> 16824.35 | I9: =IFERROR((B9-C9)/C9*100,0) -> 214.88711 | J9: =IF(G9>=3.15,"SCALE",IF(G9>=3,"MONITOR",IF(G9>=2.8,"OPTIMISE","PAUSE"))) -> MONITOR
A10: Campaign_17 | B10: 29099.18 | C10: 8198.2 | D10: 524 | E10: 20900.98 | F10: 72.072345 | G10: =IFERROR(B10/C10,0) -> 3.5494596 | H10: =B10-C10 -> 20900.98 | I10: =IFERROR((B10-C10)/C10*100,0) -> 254.94596 | J10: =IF(G10>=3.15,"SCALE",IF(G10>=3,"MONITOR",IF(G10>=2.8,"OPTIMISE","PAUSE"))) -> SCALE
A11: Campaign_18 | B11: 29190.48 | C11: 9242.78 | D11: 536 | E11: 19947.7 | F11: 64.140514 | G11: =IFERROR(B11/C11,0) -> 3.1581927 | H11: =B11-C11 -> 19947.7 | I11: =IFERROR((B11-C11)/C11*100,0) -> 215.81927 | J11: =IF(G11>=3.15,"SCALE",IF(G11>=3,"MONITOR",IF(G11>=2.8,"OPTIMISE","PAUSE"))) -> SCALE
A12: Campaign_19 | B12: 27594.02 | C12: 8300.3 | D12: 495 | E12: 19293.72 | F12: 65.181486 | G12: =IFERROR(B12/C12,0) -> 3.3244606 | H12: =B12-C12 -> 19293.72 | I12: =IFERROR((B12-C12)/C12*100,0) -> 232.44606 | J12: =IF(G12>=3.15,"SCALE",IF(G12>=3,"MONITOR",IF(G12>=2.8,"OPTIMISE","PAUSE"))) -> SCALE
A13: Campaign_2 | B13: 30694.36 | C13: 9643.38 | D13: 563 | E13: 21050.98 | F13: 63.406566 | G13: =IFERROR(B13/C13,0) -> 3.1829462 | H13: =B13-C13 -> 21050.98 | I13: =IFERROR((B13-C13)/C13*100,0) -> 218.29462 | J13: =IF(G13>=3.15,"SCALE",IF(G13>=3,"MONITOR",IF(G13>=2.8,"OPTIMISE","PAUSE"))) -> SCALE
... A22: Grand Total | B22: 552176.52 | C22: 170173.18 | D22: 9955 | E22: 382003.34 | F22: 62.623498 | G22: =IFERROR(B22/C22,0) -> 3.2447917 | H22: =B22-C22 -> 382003.34 | I22: =IFERROR((B22-C22)/C22*100,0) -> 224.47917 | J22: =IF(G22>=3.15,"SCALE",IF(G22>=3,"MONITOR",IF(G22>=2.8,"OPTIMISE","PAUSE"))) -> SCALE

Sheet PT_Platform
B2: Row Labels | C2: Sum of revenue | D2: Sum of cost | E2: Sum of conversions | F2: Sum of clicks | G2: Sum of impressions | H2: ROAS | I2: CPA | J2: CTR
B3: Facebook Ads | C3: 187088.02 | D3: 57083.8 | E3: 3381 | F3: 91359 | G3: 3076865 | H3: =IFERROR(C3/D3,0) -> 3.2774276 | I3: =IFERROR(D3/E3,0) -> 16.883703 | J3: =IFERROR(F3/G3,0) -> 0.029692235
B4: Google Ads | C4: 190827.89 | D4: 57593.42 | E4: 3411 | F4: 92036 | G4: 3108035 | H4: =IFERROR(C4/D4,0) -> 3.3133627 | I4: =IFERROR(D4/E4,0) -> 16.884614 | J4: =IFERROR(F4/G4,0) -> 0.029612279
B5: TikTok Ads | C5: 174260.61 | D5: 55495.96 | E5: 3163 | F5: 88503 | G5: 2960522 | H5: =IFERROR(C5/D5,0) -> 3.1400594 | I5: =IFERROR(D5/E5,0) -> 17.545356 | J5: =IFERROR(F5/G5,0) -> 0.02989439
B6: Grand Total | C6: 552176.52 | D6: 170173.18 | E6: 9955 | F6: 271898 | G6: 9145422 | H6: =IFERROR(C6/D6,0) -> 3.2447917 | I6: =IFERROR(D6/E6,0) -> 17.094242 | J6: =IFERROR(F6/G6,0) -> 0.029730503

Sheet PT_LoanAmt
B2: Row Labels | C2: Sum of revenue | D2: Sum of cost | E2: Sum of Profit | F2: Sum of conversions | G2: ROAS | H2: ROI% | I2: CPA | J2: Best Segment
B3: Premium (751-1000) | C3: 122456.25 | D3: 37608.33 | E3: 84847.92 | F3: 2213 | G3: =IFERROR(C3/D3,0) -> 3.2560938 | H3: =IFERROR((C3-D3)/D3*100,0) -> 225.60938 | I3: =IFERROR(D3/F3,0) -> 16.994275 | J3: =IF(G3>=3.25,"Target This","Review") -> Target This
B4: Mid (301-500) | C4: 121719.36 | D4: 37678.99 | E4: 84040.37 | F4: 2207 | G4: =IFERROR(C4/D4,0) -> 3.2304305 | H4: =IFERROR((C4-D4)/D4*100,0) -> 223.04305 | I4: =IFERROR(D4/F4,0) -> 17.072492 | J4: =IF(G4>=3.25,"Target This","Review") -> Review
B5: Low (100-300) | C5: 184027.95 | D5: 56958.48 | E5: 127069.47 | F5: 3304 | G5: =IFERROR(C5/D5,0) -> 3.230914 | H5: =IFERROR((C5-D5)/D5*100,0) -> 223.0914 | I5: =IFERROR(D5/F5,0) -> 17.239249 | J5: =IF(G5>=3.25,"Target This","Review") -> Review
B6: High (501-750) | C6: 123972.96 | D6: 37927.38 | E6: 86045.58 | F6: 2231 | G6: =IFERROR(C6/D6,0) -> 3.268693 | H6: =IFERROR((C6-D6)/D6*100,0) -> 226.8693 | I6: =IFERROR(D6/F6,0) -> 17.00017 | J6: =IF(G6>=3.25,"Target This","Review") -> Target This
B7: Grand Total | C7: 552176.52 | D7: 170173.18 | E7: 382003.34 | F7: 9955 | G7: =IFERROR(C7/D7,0) -> 3.2447917 | H7: =IFERROR((C7-D7)/D7*100,0) -> 224.47917 | I7: =IFERROR(D7/F7,0) -> 17.094242 | J7: =IF(G7>=3.25,"Target This","Review") -> Review

Sheet raw_google 
A1: EMAIL | B1: firstname | C1: lastname | D1: city | E1: state | F1: employer | G1: campaign_name | H1: platform | I1: Date | J1: loan_amount.1 | K1: impressions | L1: clicks | M1: conversions | N1: cost | O1: revenue | P1: CTR | Q1: CPC | R1: CPA | S1: salary
A2: brodriguez.hojo@yahoo.com | B2: beverly | C2: rodriguez | D2: Wichita Falls | E2: TX | F2: na | G2: Campaign_10 | H2: Google Ads | I2: 2024-01-12 | J2: 700 | K2: 707 | L2: 13 | M2: 0 | N2: 8.01 | O2: 0 | P2: 1.84 | Q2: 0.62 | R2: 0 | S2: 6369
A3: mickeymousee2@yahoo.com | B3: debra | C3: johnson | D3: Wilson | E3: NC | F3: fred hight | G3: Campaign_16 | H3: Google Ads | I3: 2024-01-04 | J3: 800 | K3: 738 | L3: 13 | M3: 0 | N3: 6.34 | O3: 0 | P3: 1.76 | Q3: 0.49 | R3: 0 | S3: 1500
A4: elon41@gmail.com | B4: elon | C4: dickey | D4: Daytona Beach | E4: FL | F4: mc donalds | G4: Campaign_18 | H4: Google Ads | I4: 2024-01-16 | J4: 800 | K4: 2315 | L4: 39 | M4: 3 | N4: 22.7 | O4: 209.05 | P4: 1.68 | Q4: 0.58 | R4: 7.57 | S4: 5000
A5: ccdmflz@bellsouth.net | B5: charles | C5: wattik | D5: Jonesville | E5: LA | F5: security insurance | G5: Campaign_11 | H5: Google Ads | I5: 2024-01-22 | J5: 500 | K5: 1401 | L5: 30 | M5: 0 | N5: 14.98 | O5: 0 | P5: 2.14 | Q5: 0.5 | R5: 0 | S5: 1500
A6: ashlallemand28@yahoo.com | B6: ashley | C6: lallemand | D6: Canal Winches | E6: OH | F6: franklin county | G6: Campaign_5 | H6: Google Ads | I6: 2024-01-09 | J6: 600 | K6: 776 | L6: 30 | M6: 0 | N6: 25.31 | O6: 0 | P6: 3.87 | Q6: 0.84 | R6: 0 | S6: 7042
A7: hugocleary@hotmail.com | B7: hugo | C7: cleary | D7: Charlotte | E7: NC | F7: mages | G7: Campaign_14 | H7: Google Ads | I7: 2024-01-29 | J7: 300 | K7: 1010 | L7: 19 | M7: 1 | N7: 13.69 | O7: 48.33 | P7: 1.88 | Q7: 0.72 | R7: 13.69 | S7: 1284
A8: altonwjr@gmail.com | B8: alton | C8: white | D8: Lubbock | E8: TX | F8: joe\\'s crab shack | G8: Campaign_8 | H8: Google Ads | I8: 2024-01-05 | J8: 500 | K8: 2482 | L8: 96 | M8: 10 | N8: 57.44 | O8: 698.1 | P8: 3.87 | Q8: 0.6 | R8: 5.74 | S8: 3700
A9: yolandad.washington@gmail.com | B9: yolando | C9: washington | D9: Florence | E9: SC | F9: assurant | G9: Campaign_5 | H9: Google Ads | I9: 2024-01-11 | J9: 200 | K9: 1331 | L9: 27 | M9: 1 | N9: 16.42 | O9: 41.3 | P9: 2.03 | Q9: 0.61 | R9: 16.42 | S9: 4065
A10: amber6329@gmail.com | B10: amber | C10: jones | D10: Cumberland | E10: VA | F10: wells fargo | G10: Campaign_1 | H10: Google Ads | I10: 2024-01-26 | J10: 1000 | K10: 1908 | L10: 63 | M10: 6 | N10: 32.2 | O10: 324.79 | P10: 3.3 | Q10: 0.51 | R10: 5.37 | S10: 3100
A11: minnie_82_00@yahoo.com | B11: angela | C11: hairston | D11: Fieldale | E11: VA | F11: memorial hospital | G11: Campaign_13 | H11: Google Ads | I11: 2024-01-30 | J11: 500 | K11: 937 | L11: 24 | M11: 1 | N11: 20.4 | O11: 42.54 | P11: 2.56 | Q11: 0.85 | R11: 20.4 | S11: 5282
A12: lovingiimerii@gmail.com | B12: yasmeen | C12: roddy | D12: Las Vegas | E12: NV | F12: nba raw sports | G12: Campaign_3 | H12: Google Ads | I12: 2024-01-16 | J12: 200 | K12: 808 | L12: 17 | M12: 0 | N12: 10.9 | O12: 0 | P12: 2.1 | Q12: 0.64 | R12: 0 | S12: 2750
A13: justinhilton81@gmail.com | B13: justin | C13: hilton | D13: Christiansbur | E13: VA | F13: energy management services | G13: Campaign_18 | H13: Google Ads | I13: 2024-01-11 | J13: 300 | K13: 2006 | L13: 48 | M13: 0 | N13: 23.39 | O13: 0 | P13: 2.39 | Q13: 0.49 | R13: 0 | S13: 1500
... A34: valeriejjohnson@gmail.com | B34: valerie | C34: johnson | D34: South Holland | E34: IL | F34: levitz furniture | G34: Campaign_8 | H34: Google Ads | I34: 2024-01-29 | J34: 100 | K34: 1159 | L34: 24 | M34: 2 | N34: 13.03 | O34: 133.86 | P34: 2.07 | Q34: 0.54 | R34: 6.52 | S34: 4500
A35: samkrb101@gmail.com | B35: sam | C35: kirby | D35: Goreville | E35: IL | F35: 0 | G35: Campaign_13 | H35: Google Ads | I35: 2024-01-24 | J35: 400 | K35: 788 | L35: 17 | M35: 0 | N35: 13.99 | O35: 0 | P35: 2.16 | Q35: 0.82 | R35: 0 | S35: 5417
A36: januaryh272@yahoo.com | B36: january | C36: harris | D36: Saint Louis | E36: MO | F36: gma paralegal services;llc | G36: Campaign_6 | H36: Google Ads | I36: 2024-01-11 | J36: 400 | K36: 1941 | L36: 85 | M36: 3 | N36: 40.6 | O36: 136.75 | P36: 4.38 | Q36: 0.48 | R36: 13.53 | S36: 1300
A37: valeriewalden@yahoo.com | B37: valerie | C37: walden | D37: Beaumont | E37: TX | F37: forth & towne | G37: Campaign_16 | H37: Google Ads | I37: 2024-01-08 | J37: 700 | K37: 676 | L37: 22 | M37: 1 | N37: 14.77 | O37: 49.55 | P37: 3.25 | Q37: 0.67 | R37: 14.77 | S37: 1500
A38: uearl51@yahoo.com | B38: earl | C38: underwood | D38: Navasota | E38: TX | F38: bj trucking | G38: Campaign_4 | H38: Google Ads | I38: 2024-01-13 | J38: 500 | K38: 1268 | L38: 50 | M38: 1 | N38: 34.57 | O38: 50.35 | P38: 3.94 | Q38: 0.69 | R38: 34.57 | S38: 2167
A39: jonesletique@gmail.com | B39: cathy | C39: jones | D39: Houston | E39: TX | F39: houstonisd | G39: Campaign_2 | H39: Google Ads | I39: 2024-01-08 | J39: 700 | K39: 541 | L39: 18 | M39: 0 | N39: 11.76 | O39: 0 | P39: 3.33 | Q39: 0.65 | R39: 0 | S39: 2708
A40: elmarquez@gmail.com | B40: eloise | C40: marquez | D40: Portland | E40: OR | F40: realty depot | G40: Campaign_17 | H40: Google Ads | I40: 2024-01-08 | J40: 100 | K40: 1818 | L40: 67 | M40: 0 | N40: 43.74 | O40: 0 | P40: 3.69 | Q40: 0.65 | R40: 0 | S40: 3250
A41: laboy783@yahoo.com | B41: eliseo | C41: duarte | D41: Dallas | E41: TX | F41: bumc | G41: Campaign_20 | H41: Google Ads | I41: 2024-01-28 | J41: 400 | K41: 2032 | L41: 90 | M41: 0 | N41: 74.64 | O41: 0 | P41: 4.43 | Q41: 0.83 | R41: 0 | S41: 4100
A42: bbluv4u2@yahoo.com | B42: marlin | C42: brown | D42: Concord | E42: NC | F42: china spring isd | G42: Campaign_19 | H42: Google Ads | I42: 2024-01-23 | J42: 300 | K42: 2373 | L42: 55 | M42: 0 | N42: 25.61 | O42: 0 | P42: 2.32 | Q42: 0.47 | R42: 0 | S42: 3400
A43: heruone2000@yahoo.com | B43: terrance | C43: merck | D43: Detroit | E43: MI | F43: embrenche | G43: Campaign_8 | H43: Google Ads | I43: 2024-01-17 | J43: 1000 | K43: 1148 | L43: 17 | M43: 1 | N43: 8.05 | O43: 70.32 | P43: 1.48 | Q43: 0.47 | R43: 8.05 | S43: 2498
A44: buffanged@yahoo.com | B44: angela | C44: buffington | D44: Nicholasville | E44: KY | F44: eden bishop | G44: Campaign_19 | H44: Google Ads | I44: 2024-01-15 | J44: 500 | K44: 2166 | L44: 39 | M44: 3 | N44: 20.6 | O44: 175.07 | P44: 1.8 | Q44: 0.53 | R44: 6.87 | S44: 2167
A45: rkarinagarzon@hotmail.com | B45: rosana | C45: lamoglia | D45: Naples | E45: FL | F45: pelicanbayfoundation | G45: Campaign_17 | H45: Google Ads | I45: 2024-01-10 | J45: 600 | K45: 1430 | L45: 61 | M45: 2 | N45: 45.15 | O45: 104.72 | P45: 4.27 | Q45: 0.74 | R45: 22.58 | S45: 2000
A46: ortizana85@gmail.com | B46: ana | C46: villanueva | D46: Arlington | E46: TX | F46: ats | G46: Campaign_11 | H46: Google Ads | I46: 2024-01-14 | J46: 1000 | K46: 2055 | L46: 85 | M46: 0 | N46: 64.77 | O46: 0 | P46: 4.14 | Q46: 0.76 | R46: 0 | S46: 3100
A47: revo6419@gmail.com | B47: david | C47: revolinski | D47: Fort Atkinson | E47: WI | F47: eaton | G47: Campaign_20 | H47: Google Ads | I47: 2024-01-20 | J47: 400 | K47: 1727 | L47: 26 | M47: 3 | N47: 16.67 | O47: 162.56 | P47: 1.51 | Q47: 0.64 | R47: 5.56 | S47: 1924
... A61: dtfrison05@yahoo.com | B61: dawntesha | C61: frison | D61: Tolleson | E61: AZ | F61: wells fargo | G61: Campaign_10 | H61: Google Ads | I61: 2024-01-28 | J61: 700 | K61: 850 | L61: 22 | M61: 0 | N61: 15.66 | O61: 0 | P61: 2.59 | Q61: 0.71 | R61: 0 | S61: 2708
A62: rgililland@live.com | B62: rebekah | C62: gililland | D62: Oklahoma City | E62: OK | F62: 0 | G62: Campaign_7 | H62: Google Ads | I62: 2024-01-03 | J62: 400 | K62: 834 | L62: 15 | M62: 0 | N62: 7.46 | O62: 0 | P62: 1.8 | Q62: 0.5 | R62: 0 | S62: 1733
A63: a30yroldfrog@aol.com | B63: angela | C63: stephens | D63: Lehigh Acres | E63: FL | F63: murphy usa | G63: Campaign_13 | H63: Google Ads | I63: 2024-01-28 | J63: 1000 | K63: 648 | L63: 26 | M63: 0 | N63: 16.05 | O63: 0 | P63: 4.01 | Q63: 0.62 | R63: 0 | S63: 2500
A64: aydinsmommy1221@live.com | B64: terina | C64: barlow | D64: Chicago | E64: IL | F64: tcf national bank illinois | G64: Campaign_13 | H64: Google Ads | I64: 2024-01-06 | J64: 100 | K64: 893 | L64: 15 | M64: 0 | N64: 7.26 | O64: 0 | P64: 1.68 | Q64: 0.48 | R64: 0 | S64: 3900
A65: tiffanylenae04@yahoo.com | B65: tiffany | C65: mock | D65: Ravenna | E65: NE | F65: cabelas | G65: Campaign_7 | H65: Google Ads | I65: 2024-01-12 | J65: 800 | K65: 1515 | L65: 33 | M65: 0 | N65: 18.21 | O65: 0 | P65: 2.18 | Q65: 0.55 | R65: 0 | S65: 2250
A66: christylnolen@abbey.bac.edu | B66: christy | C66: nolen | D66: Cramerton | E66: NC | F66: mcso | G66: Campaign_12 | H66: Google Ads | I66: 2024-01-23 | J66: 800 | K66: 1846 | L66: 41 | M66: 0 | N66: 32.59 | O66: 0 | P66: 2.22 | Q66: 0.79 | R66: 0 | S66: 4604
A67: lebpsc09@yahoo.com | B67: pam | C67: coston | D67: Charlotte | E67: NC | F67: branch banking and trust compa | G67: Campaign_4 | H67: Google Ads | I67: 2024-01-24 | J67: 100 | K67: 936 | L67: 18 | M67: 0 | N67: 9.31 | O67: 0 | P67: 1.92 | Q67: 0.52 | R67: 0 | S67: 4800
A68: crayfield65@gmail.com | B68: christina | C68: rayfield | D68: Houston | E68: TX | F68: central market | G68: Campaign_11 | H68: Google Ads | I68: 2024-01-22 | J68: 1000 | K68: 667 | L68: 17 | M68: 0 | N68: 7.61 | O68: 0 | P68: 2.55 | Q68: 0.45 | R68: 0 | S68: 2200
A69: samuel_brown84@yahoo.com | B69: brown | C69: sam | D69: Cleveland | E69: TX | F69: pitney bowes | G69: Campaign_6 | H69: Google Ads | I69: 2024-01-07 | J69: 200 | K69: 978 | L69: 40 | M69: 4 | N69: 22.01 | O69: 220 | P69: 4.09 | Q69: 0.55 | R69: 5.5 | S69: 2500
A70: hdw1865@yahoo.com | B70: howard | C70: webster | D70: Crewe | E70: VA | F70: mark dunning ind. | G70: Campaign_12 | H70: Google Ads | I70: 2024-01-03 | J70: 1000 | K70: 1825 | L70: 77 | M70: 0 | N70: 46.53 | O70: 0 | P70: 4.22 | Q70: 0.6 | R70: 0 | S70: 2000
A71: kidwellk1031@aol.com | B71: kim | C71: kidwell | D71: Kokomo | E71: IN | F71: compass | G71: Campaign_1 | H71: Google Ads | I71: 2024-01-08 | J71: 300 | K71: 1807 | L71: 46 | M71: 1 | N71: 31.07 | O71: 70.38 | P71: 2.55 | Q71: 0.68 | R71: 31.07 | S71: 3300
A72: jhockemeyer812@gmail.com | B72: jonathan | C72: hockemeyer | D72: Burleson | E72: TX | F72: bankston chevrolet | G72: Campaign_9 | H72: Google Ads | I72: 2024-01-30 | J72: 800 | K72: 2403 | L72: 57 | M72: 2 | N72: 47.38 | O72: 127.73 | P72: 2.37 | Q72: 0.83 | R72: 23.69 | S72: 4500
A73: deemurray91@gmail.com | B73: deanna | C73: murray | D73: Fayetteville | E73: NC | F73: deanna murray | G73: Campaign_18 | H73: Google Ads | I73: 2024-01-06 | J73: 100 | K73: 2212 | L73: 81 | M73: 7 | N73: 34.45 | O73: 519.26 | P73: 3.66 | Q73: 0.43 | R73: 4.92 | S73: 1699
A74: arielbaker@gmail.com | B74: ariel | C74: baker | D74: Sarasota | E74: FL | F74: whole foods marker | G74: Campaign_16 | H74: Google Ads | I74: 2024-01-28 | J74: 800 | K74: 1242 | L74: 50 | M74: 2 | N74: 37.19 | O74: 107.85 | P74: 4.03 | Q74: 0.74 | R74: 18.6 | S74: 2167
... A297: howardhannah329@yahoo.com | B297: howard | C297: hannah | D297: Houston | E297: TX | F297: goodman heating and cooling | G297: Campaign_16 | H297: Google Ads | I297: 2024-01-18 | J297: 1000 | K297: 1353 | L297: 33 | M297: 0 | N297: 16.22 | O297: 0 | P297: 2.44 | Q297: 0.49 | R297: 0 | S297: 2500
A298: tealesia0418@live.com | B298: tealesia | C298: marshall | D298: Marshall | E298: TX | F298: 0 | G298: Campaign_10 | H298: Google Ads | I298: 2024-01-18 | J298: 700 | K298: 1752 | L298: 64 | M298: 1 | N298: 42.36 | O298: 62.91 | P298: 3.65 | Q298: 0.66 | R298: 42.36 | S298: 2250
A299: shalon.staten@gmail.com | B299: shalon | C299: staten | D299: Bonifay | E299: FL | F299: dove academy | G299: Campaign_13 | H299: Google Ads | I299: 2024-01-19 | J299: 300 | K299: 1984 | L299: 51 | M299: 0 | N299: 39.13 | O299: 0 | P299: 2.57 | Q299: 0.77 | R299: 0 | S299: 2750
A300: rdean_61@hotmail.com | B300: ronald | C300: chambers | D300: Casa Grande | E300: AZ | F300: abbott nutrition | G300: Campaign_13 | H300: Google Ads | I300: 2024-01-16 | J300: 600 | K300: 1029 | L300: 40 | M300: 0 | N300: 18.41 | O300: 0 | P300: 3.89 | Q300: 0.46 | R300: 0 | S300: 2750
A301: s0n0fabish85@gmail.com | B301: tyler | C301: bish | D301: Lost Creek | E301: WV | F301: unitedsummitcenter | G301: Campaign_1 | H301: Google Ads | I301: 2024-01-15 | J301: 1000 | K301: 876 | L301: 36 | M301: 0 | N301: 19.37 | O301: 0 | P301: 4.11 | Q301: 0.54 | R301: 0 | S301: 1300
A302: laron2525@gmail.com | B302: laron | C302: lewis | D302: Lexington | E302: KY | F302: lextran | G302: Campaign_7 | H302: Google Ads | I302: 2024-01-14 | J302: 700 | K302: 1261 | L302: 33 | M302: 3 | N302: 21.54 | O302: 125.6 | P302: 2.62 | Q302: 0.65 | R302: 7.18 | S302: 2250
A303: danielledavid00@gmail.com | B303: danielle | C303: david | D303: Los Angeles | E303: CA | F303: bcbg max azria | G303: Campaign_12 | H303: Google Ads | I303: 2024-01-13 | J303: 500 | K303: 1080 | L303: 17 | M303: 0 | N303: 10.68 | O303: 0 | P303: 1.57 | Q303: 0.63 | R303: 0 | S303: 2250
A304: dropdap@gmail.com | B304: elijah | C304: scott | D304: Atlanta | E304: GA | F304: wellpoint | G304: Campaign_4 | H304: Google Ads | I304: 2024-01-06 | J304: 800 | K304: 1717 | L304: 30 | M304: 2 | N304: 25.49 | O304: 149.98 | P304: 1.75 | Q304: 0.85 | R304: 12.74 | S304: 2250
A305: lclinard@yahoo.com | B305: michael | C305: clinard | D305: Bucyrus | E305: OH | F305: stratosphere | G305: Campaign_12 | H305: Google Ads | I305: 2024-01-25 | J305: 100 | K305: 1437 | L305: 36 | M305: 1 | N305: 20.72 | O305: 46.82 | P305: 2.51 | Q305: 0.58 | R305: 20.72 | S305: 1300
A306: ca.13@live.com | B306: yasen | C306: jiang | D306: San Diego | E306: CA | F306: polymerex medical inc | G306: Campaign_16 | H306: Google Ads | I306: 2024-01-27 | J306: 600 | K306: 837 | L306: 28 | M306: 0 | N306: 15.96 | O306: 0 | P306: 3.35 | Q306: 0.57 | R306: 0 | S306: 4500
A307: talithajones31@yahoo.com | B307: talitha | C307: jones | D307: Minneapolis | E307: MN | F307: a chance learning center | G307: Campaign_1 | H307: Google Ads | I307: 2024-01-27 | J307: 200 | K307: 897 | L307: 38 | M307: 0 | N307: 29.09 | O307: 0 | P307: 4.24 | Q307: 0.77 | R307: 0 | S307: 3250
A308: meryldsmith@yahoo.com | B308: meryl | C308: smith | D308: Fort Worth | E308: TX | F308: bell helicopter | G308: Campaign_6 | H308: Google Ads | I308: 2024-01-19 | J308: 100 | K308: 1632 | L308: 30 | M308: 1 | N308: 15.21 | O308: 66.37 | P308: 1.84 | Q308: 0.51 | R308: 15.21 | S308: 1100
A309: d.trish7@gmail.com | B309: patricia | C309: dolan | D309: New Haven | E309: CT | F309: sealtitecontracting | G309: Campaign_18 | H309: Google Ads | I309: 2024-01-09 | J309: 700 | K309: 535 | L309: 8 | M309: 1 | N309: 5.22 | O309: 56.85 | P309: 1.5 | Q309: 0.65 | R309: 5.22 | S309: 1300
A310: drbill417@yahoo.com | B310: william c | C310: thomas | D310: Ormond Beach | E310: FL | F310: self employed | G310: Campaign_10 | H310: Google Ads | I310: 2024-01-16 | J310: 600 | K310: 908 | L310: 25 | M310: 0 | N310: 17.01 | O310: 0 | P310: 2.75 | Q310: 0.68 | R310: 0 | S310: 4500
... A745: designedbyjenny@yahoo.com | B745: jennifer | C745: hao | D745: Fort Worth | E745: TX | F745: vast america | G745: Campaign_7 | H745: Google Ads | I745: 2024-01-10 | J745: 800 | K745: 1689 | L745: 25 | M745: 1 | N745: 12.48 | O745: 63.84 | P745: 1.48 | Q745: 0.5 | R745: 12.48 | S745: 2250
A746: kjg50@aol.com | B746: stephen | C746: grant | D746: Lawrenceburg | E746: KY | F746: 0 | G746: Campaign_4 | H746: Google Ads | I746: 2024-01-15 | J746: 800 | K746: 1765 | L746: 72 | M746: 7 | N746: 53.11 | O746: 484.3 | P746: 4.08 | Q746: 0.74 | R746: 7.59 | S746: 6500
A747: t12v17m@yahoo.com | B747: gertrude | C747: vanmiddleswo | D747: Orlando | E747: FL | F747: disability insurance | G747: Campaign_14 | H747: Google Ads | I747: 2024-01-05 | J747: 1000 | K747: 1890 | L747: 75 | M747: 7 | N747: 53.39 | O747: 271.67 | P747: 3.97 | Q747: 0.71 | R747: 7.63 | S747: 2000
A748: missnch127@gmail.com | B748: nikki | C748: holmes | D748: Gwynn Oak | E748: MD | F748: fhcb | G748: Campaign_3 | H748: Google Ads | I748: 2024-01-02 | J748: 200 | K748: 1615 | L748: 54 | M748: 0 | N748: 32.76 | O748: 0 | P748: 3.34 | Q748: 0.61 | R748: 0 | S748: 3500
A749: thartfield69@yahoo.com | B749: thomas | C749: hartfield | D749: Chicago | E749: IL | F749: centurion | G749: Campaign_7 | H749: Google Ads | I749: 2024-01-15 | J749: 100 | K749: 1164 | L749: 30 | M749: 2 | N749: 18.25 | O749: 94.43 | P749: 2.58 | Q749: 0.61 | R749: 9.12 | S749: 2500
A750: hyltonheather@yahoo.com | B750: heather | C750: hylton | D750: Saint Petersb | E750: FL | F750: largo medical center | G750: Campaign_6 | H750: Google Ads | I750: 2024-01-31 | J750: 300 | K750: 1110 | L750: 22 | M750: 0 | N750: 9.21 | O750: 0 | P750: 1.98 | Q750: 0.42 | R750: 0 | S750: 2500
A751: daddio_wifeylife@yahoo.com | B751: angela | C751: cooper | D751: Fort Lauderda | E751: FL | F751: ckh business | G751: Campaign_14 | H751: Google Ads | I751: 2024-01-30 | J751: 300 | K751: 1310 | L751: 53 | M751: 1 | N751: 41.57 | O751: 35.6 | P751: 4.05 | Q751: 0.78 | R751: 41.57 | S751: 2200
A752: kimber3662@yahoo.com | B752: kim | C752: tucker | D752: Lakewood | E752: CA | F752: ucla medical | G752: Campaign_7 | H752: Google Ads | I752: 2024-01-11 | J752: 1000 | K752: 1657 | L752: 69 | M752: 1 | N752: 57.73 | O752: 74.65 | P752: 4.16 | Q752: 0.84 | R752: 57.73 | S752: 3000
A753: leisafortney@yahoo.com | B753: leisa | C753: fortney | D753: Lacey | E753: WA | F753: state of washington | G753: Campaign_17 | H753: Google Ads | I753: 2024-01-23 | J753: 1000 | K753: 1535 | L753: 51 | M753: 0 | N753: 31.74 | O753: 0 | P753: 3.32 | Q753: 0.62 | R753: 0 | S753: 4800
A754: stephanie.gustin5@yahoo.com | B754: stephanie | C754: gustin | D754: Greenfield | E754: IN | F754: dsa | G754: Campaign_10 | H754: Google Ads | I754: 2024-01-26 | J754: 100 | K754: 2224 | L754: 33 | M754: 0 | N754: 14.1 | O754: 0 | P754: 1.48 | Q754: 0.43 | R754: 0 | S754: 3000
A755: vlwilliam66@yahoo.com | B755: valerie | C755: williams | D755: Sacramento | E755: CA | F755: relationship skills center | G755: Campaign_13 | H755: Google Ads | I755: 2024-01-17 | J755: 500 | K755: 1390 | L755: 57 | M755: 0 | N755: 36.5 | O755: 0 | P755: 4.1 | Q755: 0.64 | R755: 0 | S755: 2800
A756: monica_vance@yahoo.com | B756: monica | C756: vance | D756: Maple Heights | E756: OH | F756: bank of america | G756: Campaign_16 | H756: Google Ads | I756: 2024-01-21 | J756: 400 | K756: 639 | L756: 14 | M756: 0 | N756: 11.71 | O756: 0 | P756: 2.19 | Q756: 0.84 | R756: 0 | S756: 2349
A757: prttythikgirl@gmail.com | B757: michael | C757: jones | D757: Sacramento | E757: CA | F757: sprint | G757: Campaign_14 | H757: Google Ads | I757: 2024-01-27 | J757: 700 | K757: 1570 | L757: 36 | M757: 1 | N757: 23.86 | O757: 68.13 | P757: 2.29 | Q757: 0.66 | R757: 23.86 | S757: 1500
A758: fitter14b@yahoo.com | B758: elbert | C758: grinstead | D758: Chicago | E758: IL | F758: dyesspeterson | G758: Campaign_16 | H758: Google Ads | I758: 2024-01-30 | J758: 600 | K758: 1053 | L758: 36 | M758: 0 | N758: 28.6 | O758: 0 | P758: 3.42 | Q758: 0.79 | R758: 0 | S758: 2200
... A822: alyssaher@hotmail.com | B822: alyssa | C822: her | D822: Milwaukee | E822: WI | F822: columbia st. marys | G822: Campaign_18 | H822: Google Ads | I822: 2024-01-20 | J822: 700 | K822: 1643 | L822: 58 | M822: 1 | N822: 34.91 | O822: 61.45 | P822: 3.53 | Q822: 0.6 | R822: 34.91 | S822: 1535
A823: dh11982d@gmail.com | B823: dee | C823: harbour | D823: Meridian | E823: ID | F823: 0 | G823: Campaign_17 | H823: Google Ads | I823: 2024-01-22 | J823: 600 | K823: 1203 | L823: 30 | M823: 0 | N823: 21.7 | O823: 0 | P823: 2.49 | Q823: 0.72 | R823: 0 | S823: 4500
A824: jlwverse@gmail.com | B824: jonathan | C824: williams | D824: San Antonio | E824: TX | F824: heb | G824: Campaign_7 | H824: Google Ads | I824: 2024-01-01 | J824: 700 | K824: 1953 | L824: 87 | M824: 2 | N824: 35.37 | O824: 84.61 | P824: 4.45 | Q824: 0.41 | R824: 17.68 | S824: 1700
A825: azesha_ryan@hotmail.com | B825: azesha | C825: ryan | D825: Portage | E825: IN | F825: massage envy | G825: Campaign_12 | H825: Google Ads | I825: 2024-01-30 | J825: 1000 | K825: 947 | L825: 20 | M825: 0 | N825: 16.34 | O825: 0 | P825: 2.11 | Q825: 0.82 | R825: 0 | S825: 1500
A826: myesha_stewart92@yahoo.com | B826: myesha | C826: stewart | D826: Beaumont | E826: TX | F826: ssi | G826: Campaign_9 | H826: Google Ads | I826: 2024-01-16 | J826: 700 | K826: 2210 | L826: 35 | M826: 1 | N826: 22.19 | O826: 49.84 | P826: 1.58 | Q826: 0.63 | R826: 22.19 | S826: 3000
A827: carolmccomber@yahoo.com | B827: carol | C827: mccomber | D827: Lansing | E827: MI | F827: ryder loc | G827: Campaign_12 | H827: Google Ads | I827: 2024-01-14 | J827: 300 | K827: 1491 | L827: 26 | M827: 0 | N827: 16.39 | O827: 0 | P827: 1.74 | Q827: 0.63 | R827: 0 | S827: 3500
A828: fpvaskejr@yahoo.com | B828: francis | C828: vaske | D828: Sardinia | E828: OH | F828: state of ohio | G828: Campaign_7 | H828: Google Ads | I828: 2024-01-27 | J828: 400 | K828: 2428 | L828: 72 | M828: 2 | N828: 37.66 | O828: 77.73 | P828: 2.97 | Q828: 0.52 | R828: 18.83 | S828: 1600
A829: dominicankidzz@hotmail.com | B829: fernando | C829: santos | D829: Lutz | E829: FL | F829: tampa general hospital | G829: Campaign_4 | H829: Google Ads | I829: 2024-01-28 | J829: 800 | K829: 1685 | L829: 71 | M829: 3 | N829: 39.75 | O829: 122.06 | P829: 4.21 | Q829: 0.56 | R829: 13.25 | S829: 1625
A830: ckburk@hotmail.com | B830: cheryll | C830: burk | D830: Glendora | E830: CA | F830: retired | G830: Campaign_6 | H830: Google Ads | I830: 2024-01-11 | J830: 600 | K830: 2080 | L830: 78 | M830: 0 | N830: 40.11 | O830: 0 | P830: 3.75 | Q830: 0.51 | R830: 0 | S830: 3200
A831: rachel1779@hotmail.com | B831: rachel | C831: jacobs | D831: West Bend | E831: WI | F831: mikkelson | G831: Campaign_9 | H831: Google Ads | I831: 2024-01-06 | J831: 400 | K831: 943 | L831: 29 | M831: 0 | N831: 18.23 | O831: 0 | P831: 3.08 | Q831: 0.63 | R831: 0 | S831: 1535
A832: pascott33@yahoo.com | B832: melissa | C832: ross | D832: Simpsonville | E832: SC | F832: ssi | G832: Campaign_12 | H832: Google Ads | I832: 2024-01-02 | J832: 800 | K832: 1907 | L832: 34 | M832: 3 | N832: 19.62 | O832: 172.73 | P832: 1.78 | Q832: 0.58 | R832: 6.54 | S832: 3800
A833: k_little17@hotmail.com | B833: kemisha | C833: little | D833: Hartford | E833: CT | F833: rr donelley | G833: Campaign_7 | H833: Google Ads | I833: 2024-01-26 | J833: 100 | K833: 1467 | L833: 62 | M833: 2 | N833: 26.25 | O833: 140.31 | P833: 4.23 | Q833: 0.42 | R833: 13.12 | S833: 1500
A834: mztoya337@yahoo.com | B834: marquis | C834: ford | D834: Lafayette | E834: LA | F834: lafayette general hospital | G834: Campaign_17 | H834: Google Ads | I834: 2024-01-19 | J834: 800 | K834: 689 | L834: 21 | M834: 2 | N834: 16.83 | O834: 74.47 | P834: 3.05 | Q834: 0.8 | R834: 8.41 | S834: 1500
A835: jhbales2727@yahoo.com | B835: john | C835: bales | D835: Cleves | E835: OH | F835: iowa steak | G835: Campaign_1 | H835: Google Ads | I835: 2024-01-07 | J835: 400 | K835: 673 | L835: 16 | M835: 1 | N835: 11.29 | O835: 72.48 | P835: 2.38 | Q835: 0.71 | R835: 11.29 | S835: 3000
... A1925: kmcwane@yahoo.com | B1925: kim | C1925: mcwane | D1925: Killeen | E1925: TX | F1925: wells fargo | G1925: Campaign_4 | H1925: Google Ads | I1925: 2024-01-22 | J1925: 200 | K1925: 554 | L1925: 11 | M1925: 0 | N1925: 4.51 | O1925: 0 | P1925: 1.99 | Q1925: 0.41 | R1925: 0 | S1925: 1500
A1926: teyhall@gmail.com | B1926: teylor | C1926: hall | D1926: Rohnert Park | E1926: CA | F1926: 0 | G1926: Campaign_13 | H1926: Google Ads | I1926: 2024-01-05 | J1926: 400 | K1926: 615 | L1926: 23 | M1926: 0 | N1926: 17.08 | O1926: 0 | P1926: 3.74 | Q1926: 0.74 | R1926: 0 | S1926: 1818
A1927: jle522000@yahoo.com | B1927: janet | C1927: emmick | D1927: Washington | E1927: IN | F1927: government | G1927: Campaign_6 | H1927: Google Ads | I1927: 2024-01-17 | J1927: 400 | K1927: 1613 | L1927: 54 | M1927: 5 | N1927: 43.45 | O1927: 367.45 | P1927: 3.35 | Q1927: 0.8 | R1927: 8.69 | S1927: 1516
A1928: aminah22@hotmail.com | B1928: aminah | C1928: mears | D1928: Fontana | E1928: CA | F1928: en valley | G1928: Campaign_9 | H1928: Google Ads | I1928: 2024-01-14 | J1928: 1000 | K1928: 2059 | L1928: 32 | M1928: 3 | N1928: 13.53 | O1928: 160.45 | P1928: 1.55 | Q1928: 0.42 | R1928: 4.51 | S1928: 3116
A1929: peter_johnson697@yahoo.com | B1929: ann | C1929: talor | D1929: Birmingham | E1929: AL | F1929: ann taylor | G1929: Campaign_19 | H1929: Google Ads | I1929: 2024-01-02 | J1929: 200 | K1929: 1640 | L1929: 69 | M1929: 3 | N1929: 57.84 | O1929: 197.71 | P1929: 4.21 | Q1929: 0.84 | R1929: 19.28 | S1929: 1733
A1930: itserika21@gmail.com | B1930: erika | C1930: felipe | D1930: Hollywood | E1930: FL | F1930: h. d. smith | G1930: Campaign_19 | H1930: Google Ads | I1930: 2024-01-25 | J1930: 200 | K1930: 1844 | L1930: 52 | M1930: 0 | N1930: 41.58 | O1930: 0 | P1930: 2.82 | Q1930: 0.8 | R1930: 0 | S1930: 1000
A1931: vlmobley@aol.com | B1931: virgie | C1931: mobley | D1931: Killeen | E1931: TX | F1931: us army | G1931: Campaign_9 | H1931: Google Ads | I1931: 2024-01-14 | J1931: 300 | K1931: 1163 | L1931: 35 | M1931: 0 | N1931: 24.02 | O1931: 0 | P1931: 3.01 | Q1931: 0.69 | R1931: 0 | S1931: 2500
A1932: jjlroksolid@hotmail.com | B1932: joseph | C1932: litcher | D1932: Clearwater | E1932: FL | F1932: self | G1932: Campaign_11 | H1932: Google Ads | I1932: 2024-01-25 | J1932: 800 | K1932: 1726 | L1932: 66 | M1932: 0 | N1932: 31.79 | O1932: 0 | P1932: 3.82 | Q1932: 0.48 | R1932: 0 | S1932: 3692
A1933: helper_dough_girl@hotmail.com | B1933: john | C1933: harwood | D1933: Helper | E1933: UT | F1933: wendys | G1933: Campaign_4 | H1933: Google Ads | I1933: 2024-01-04 | J1933: 800 | K1933: 1547 | L1933: 62 | M1933: 5 | N1933: 42.21 | O1933: 279.25 | P1933: 4.01 | Q1933: 0.68 | R1933: 8.44 | S1933: 1384
A1934: christinevogt@hotmail.com | B1934: christine | C1934: vogt | D1934: Crystal Lake | E1934: IL | F1934: romp | G1934: Campaign_12 | H1934: Google Ads | I1934: 2024-01-19 | J1934: 100 | K1934: 2184 | L1934: 44 | M1934: 0 | N1934: 35.45 | O1934: 0 | P1934: 2.01 | Q1934: 0.81 | R1934: 0 | S1934: 4000
A1935: prdnice@gmail.com | B1935: phyllis | C1935: dorsey | D1935: Rayville | E1935: LA | F1935: richland parish schools | G1935: Campaign_18 | H1935: Google Ads | I1935: 2024-01-02 | J1935: 100 | K1935: 2115 | L1935: 90 | M1935: 8 | N1935: 37.78 | O1935: 533.95 | P1935: 4.26 | Q1935: 0.42 | R1935: 4.72 | S1935: 2306
A1936: phylannmo55@aol.com | B1936: phyllis | C1936: morris | D1936: Lake Charles | E1936: LA | F1936: first federal bank of la | G1936: Campaign_11 | H1936: Google Ads | I1936: 2024-01-27 | J1936: 800 | K1936: 2199 | L1936: 83 | M1936: 8 | N1936: 65.47 | O1936: 404.38 | P1936: 3.77 | Q1936: 0.79 | R1936: 8.18 | S1936: 3000
A1937: collinclayonna@gmail.com | B1937: vickie | C1937: perry | D1937: Cleveland | E1937: OH | F1937: kimcards | G1937: Campaign_12 | H1937: Google Ads | I1937: 2024-01-23 | J1937: 400 | K1937: 1957 | L1937: 64 | M1937: 6 | N1937: 34.33 | O1937: 334.59 | P1937: 3.27 | Q1937: 0.54 | R1937: 5.72 | S1937: 3500
A1938: kenken_1983@hotmail.com | B1938: kenneth | C1938: graham | D1938: Arlington | E1938: WA | F1938: apple bees | G1938: Campaign_11 | H1938: Google Ads | I1938: 2024-01-07 | J1938: 300 | K1938: 1308 | L1938: 32 | M1938: 1 | N1938: 21.24 | O1938: 45.53 | P1938: 2.45 | Q1938: 0.66 | R1938: 21.24 | S1938: 1907
... A2001: flossied@gmail.com | B2001: flossie | C2001: blackwell | D2001: Lansdale | E2001: PA | F2001: muscle factory | G2001: Campaign_20 | H2001: Google Ads | I2001: 2024-01-29 | J2001: 700 | K2001: 2488 | L2001: 62 | M2001: 1 | N2001: 36.22 | O2001: 64.56 | P2001: 2.49 | Q2001: 0.58 | R2001: 36.22 | S2001: 2340
A2002: kennethhill14@yahoo.com | B2002: kenneth | C2002: hill | D2002: Philadelphia | E2002: PA | F2002: 0 | G2002: Campaign_3 | H2002: Google Ads | I2002: 2024-01-21 | J2002: 700 | K2002: 1247 | L2002: 29 | M2002: 0 | N2002: 23.55 | O2002: 0 | P2002: 2.33 | Q2002: 0.81 | R2002: 0 | S2002: 6700
A2003: mrf_watson@yahoo.com | B2003: marife | C2003: watson | D2003: Sioux Falls | E2003: SD | F2003: hyvee | G2003: Campaign_11 | H2003: Google Ads | I2003: 2024-01-20 | J2003: 600 | K2003: 2175 | L2003: 65 | M2003: 0 | N2003: 38.54 | O2003: 0 | P2003: 2.99 | Q2003: 0.59 | R2003: 0 | S2003: 2849
...

Sheet raw_meta
A1: EMAIL | B1: firstname | C1: lastname | D1: city | E1: state | F1: employer | G1: campaign_name | H1: platform | I1: Date | J1: loan_amount.1 | K1: impressions | L1: clicks | M1: conversions | N1: cost | O1: revenue | P1: CTR | Q1: CPC | R1: CPA | S1: salary
A2: claudiaboyd2@yahoo.com | B2: claudia | C2: boyd | D2: Greenwood | E2: MS | F2: leflore county school district | G2: Campaign_18 | H2: Facebook Ads | I2: 2024-01-31 | J2: 400 | K2: 1688 | L2: 55 | M2: 0 | N2: 32.23 | O2: 0 | P2: 3.26 | Q2: 0.59 | R2: 0 | S2: 5958
A3: smrdar218@yahoo.com | B3: sadie | C3: royster | D3: Uniontown | E3: PA | F3: chs | G3: Campaign_7 | H3: Facebook Ads | I3: 2024-01-01 | J3: 700 | K3: 678 | L3: 18 | M3: 0 | N3: 8.62 | O3: 0 | P3: 2.65 | Q3: 0.48 | R3: 0 | S3: 3750
A4: jonesdarryl427@yahoo.com | B4: darryl | C4: jones | D4: Walnut Cove | E4: NC | F4: materials management | G4: Campaign_11 | H4: Facebook Ads | I4: 2024-01-22 | J4: 700 | K4: 1179 | L4: 42 | M4: 1 | N4: 21.11 | O4: 55.69 | P4: 3.56 | Q4: 0.5 | R4: 21.11 | S4: 4100
A5: telly1188@gmail.com | B5: shantel | C5: shantel | D5: Winston Salem | E5: NC | F5: twin city quarters | G5: Campaign_18 | H5: Facebook Ads | I5: 2024-01-04 | J5: 800 | K5: 1645 | L5: 56 | M5: 4 | N5: 40.74 | O5: 142.03 | P5: 3.4 | Q5: 0.73 | R5: 10.18 | S5: 3250
A6: bethahud@bellsouth.net | B6: mary | C6: hudson | D6: Knoxville | E6: TN | F6: knox county schools | G6: Campaign_6 | H6: Facebook Ads | I6: 2024-01-05 | J6: 500 | K6: 1315 | L6: 24 | M6: 0 | N6: 18.7 | O6: 0 | P6: 1.83 | Q6: 0.78 | R6: 0 | S6: 4900
A7: cnvarez85@gmail.com | B7: crystal | C7: nevarez | D7: Tallahassee | E7: FL | F7: south east eye specialist | G7: Campaign_17 | H7: Facebook Ads | I7: 2024-01-02 | J7: 300 | K7: 1165 | L7: 23 | M7: 2 | N7: 11.23 | O7: 115.62 | P7: 1.97 | Q7: 0.49 | R7: 5.62 | S7: 5000
A8: fanaticartrepreneur@yahoo.com | B8: dolllicia | C8: white | D8: Harrisburg | E8: PA | F8: department of auditor | G8: Campaign_7 | H8: Facebook Ads | I8: 2024-01-24 | J8: 200 | K8: 1248 | L8: 54 | M8: 1 | N8: 37.21 | O8: 45.12 | P8: 4.33 | Q8: 0.69 | R8: 37.21 | S8: 3700
A9: jmnaber@gmail.com | B9: jiries | C9: naber | D9: Canyon Countr | E9: CA | F9: in home supportive sercives | G9: Campaign_1 | H9: Facebook Ads | I9: 2024-01-03 | J9: 100 | K9: 2424 | L9: 86 | M9: 3 | N9: 54.01 | O9: 171.74 | P9: 3.55 | Q9: 0.63 | R9: 18 | S9: 3500
A10: fcb112@gmail.com | B10: frederick | C10: berry | D10: San Antonio | E10: TX | F10: woolf brothers | G10: Campaign_17 | H10: Facebook Ads | I10: 2024-01-07 | J10: 300 | K10: 2233 | L10: 81 | M10: 9 | N10: 67.58 | O10: 348.93 | P10: 3.63 | Q10: 0.83 | R10: 7.51 | S10: 2500
A11: lisawatson@optonline.net | B11: lisa | C11: watson | D11: Passaic | E11: NJ | F11: pnc bank new jersey | G11: Campaign_4 | H11: Facebook Ads | I11: 2024-01-15 | J11: 300 | K11: 2432 | L11: 39 | M11: 0 | N11: 16.2 | O11: 0 | P11: 1.6 | Q11: 0.42 | R11: 0 | S11: 1000
A12: lilchristian704@yahoo.com | B12: shamika | C12: hairston | D12: Houston | E12: TX | F12: fresenius | G12: Campaign_9 | H12: Facebook Ads | I12: 2024-01-31 | J12: 500 | K12: 1844 | L12: 72 | M12: 7 | N12: 29.5 | O12: 427.32 | P12: 3.9 | Q12: 0.41 | R12: 4.21 | S12: 1300
A13: jessdav19@gmail.com | B13: jessica | C13: davis | D13: Conroe | E13: TX | F13: tx dept of criminal justice | G13: Campaign_20 | H13: Facebook Ads | I13: 2024-01-25 | J13: 1000 | K13: 1364 | L13: 20 | M13: 0 | N13: 14.41 | O13: 0 | P13: 1.47 | Q13: 0.72 | R13: 0 | S13: 2334
... A361: chichismom29@hotmail.com | B361: dago | C361: villamil | D361: Hialeah | E361: FL | F361: asrc | G361: Campaign_1 | H361: Facebook Ads | I361: 2024-01-06 | J361: 200 | K361: 1675 | L361: 27 | M361: 0 | N361: 17.61 | O361: 0 | P361: 1.61 | Q361: 0.65 | R361: 0 | S361: 4500
A362: gothamsknights@hotmail.com | B362: aaron | C362: moser | D362: Maricopa | E362: AZ | F362: 0 | G362: Campaign_14 | H362: Facebook Ads | I362: 2024-01-08 | J362: 100 | K362: 551 | L362: 21 | M362: 0 | N362: 13.92 | O362: 0 | P362: 3.81 | Q362: 0.66 | R362: 0 | S362: 2750
A363: teresha0824@yahoo.com | B363: teresha | C363: cooper | D363: Houston | E363: TX | F363: at and t | G363: Campaign_18 | H363: Facebook Ads | I363: 2024-01-30 | J363: 400 | K363: 1279 | L363: 53 | M363: 1 | N363: 25.33 | O363: 73.65 | P363: 4.14 | Q363: 0.48 | R363: 25.33 | S363: 2250
A364: shyraaaa@hotmail.com | B364: latoya | C364: paige | D364: Tuscaloosa | E364: AL | F364: self | G364: Campaign_9 | H364: Facebook Ads | I364: 2024-01-23 | J364: 700 | K364: 2203 | L364: 73 | M364: 0 | N364: 33.56 | O364: 0 | P364: 3.31 | Q364: 0.46 | R364: 0 | S364: 2200
A365: usmarinemom46@yahoo.com | B365: lori | C365: martin | D365: Worcester | E365: MA | F365: durham school services | G365: Campaign_15 | H365: Facebook Ads | I365: 2024-01-15 | J365: 400 | K365: 2019 | L365: 80 | M365: 0 | N365: 37.32 | O365: 0 | P365: 3.96 | Q365: 0.47 | R365: 0 | S365: 2000
A366: bnjmnwhtnr634@gmail.com | B366: benjamin | C366: whitener | D366: Athens | E366: GA | F366: nibco | G366: Campaign_5 | H366: Facebook Ads | I366: 2024-01-19 | J366: 500 | K366: 1275 | L366: 53 | M366: 2 | N366: 33.71 | O366: 80.15 | P366: 4.16 | Q366: 0.64 | R366: 16.86 | S366: 4800
A367: robert212315@gmail.com | B367: wayne | C367: kitten | D367: Chicago | E367: IL | F367: midtown toyota | G367: Campaign_16 | H367: Facebook Ads | I367: 2024-01-26 | J367: 800 | K367: 1880 | L367: 31 | M367: 3 | N367: 25.88 | O367: 159.56 | P367: 1.65 | Q367: 0.83 | R367: 8.63 | S367: 4100
A368: lisa_dawn_72@yahoo.com | B368: lisa | C368: simons | D368: Montgomery | E368: TX | F368: k9kuts | G368: Campaign_17 | H368: Facebook Ads | I368: 2024-01-21 | J368: 100 | K368: 1400 | L368: 54 | M368: 1 | N368: 38.63 | O368: 47.32 | P368: 3.86 | Q368: 0.72 | R368: 38.63 | S368: 2700
A369: williamlacayo@hotmail.com | B369: william | C369: lacayo | D369: Miami | E369: FL | F369: larkin community hospital | G369: Campaign_4 | H369: Facebook Ads | I369: 2024-01-18 | J369: 800 | K369: 1380 | L369: 34 | M369: 0 | N369: 22.45 | O369: 0 | P369: 2.46 | Q369: 0.66 | R369: 0 | S369: 4500
A370: andreasand27@hotmail.com | B370: andrea | C370: sanders | D370: Chicago | E370: IL | F370: uas properties | G370: Campaign_18 | H370: Facebook Ads | I370: 2024-01-25 | J370: 200 | K370: 2497 | L370: 64 | M370: 0 | N370: 49.9 | O370: 0 | P370: 2.56 | Q370: 0.78 | R370: 0 | S370: 2400
A371: kyla.steenson@gmail.com | B371: kyla | C371: steenson | D371: Kanopolis | E371: KS | F371: casey's general story | G371: Campaign_13 | H371: Facebook Ads | I371: 2024-01-25 | J371: 500 | K371: 1417 | L371: 46 | M371: 4 | N371: 23.59 | O371: 185.32 | P371: 3.25 | Q371: 0.51 | R371: 5.9 | S371: 1560
A372: jr.correa176@gmail.com | B372: gumercindo | C372: correa | D372: Dimmitt | E372: TX | F372: texas tech university | G372: Campaign_4 | H372: Facebook Ads | I372: 2024-01-13 | J372: 600 | K372: 1008 | L372: 17 | M372: 1 | N372: 13.82 | O372: 53.69 | P372: 1.69 | Q372: 0.81 | R372: 13.82 | S372: 2000
A373: racmckin@yahoo.com | B373: racheal | C373: mckinnon | D373: Rhineland | E373: MO | F373: parker hannifin sporlan | G373: Campaign_11 | H373: Facebook Ads | I373: 2024-01-12 | J373: 200 | K373: 813 | L373: 19 | M373: 2 | N373: 12.53 | O373: 149.12 | P373: 2.34 | Q373: 0.66 | R373: 6.26 | S373: 1499
A374: cleora_9@yahoo.com | B374: brockbank | C374: cleora | D374: Ballwin | E374: MO | F374: burger king | G374: Campaign_19 | H374: Facebook Ads | I374: 2024-01-13 | J374: 100 | K374: 1740 | L374: 28 | M374: 0 | N374: 17.9 | O374: 0 | P374: 1.61 | Q374: 0.64 | R374: 0 | S374: 2166
... A446: ventwan21@gmail.com | B446: napoleon | C446: hall | D446: Atlanta | E446: GA | F446: e transform | G446: Campaign_14 | H446: Facebook Ads | I446: 2024-01-04 | J446: 800 | K446: 734 | L446: 13 | M446: 0 | N446: 6.06 | O446: 0 | P446: 1.77 | Q446: 0.47 | R446: 0 | S446: 4333
A447: sabrina.jenkins1@yahoo.com | B447: willie | C447: jenkins | D447: Auburndale | E447: FL | F447: 0 | G447: Campaign_8 | H447: Facebook Ads | I447: 2024-01-30 | J447: 100 | K447: 612 | L447: 18 | M447: 0 | N447: 11.1 | O447: 0 | P447: 2.94 | Q447: 0.62 | R447: 0 | S447: 2750
A448: amazingjana@yahoo.com | B448: january | C448: jurado | D448: Daly City | E448: CA | F448: ucsf medical center | G448: Campaign_3 | H448: Facebook Ads | I448: 2024-01-24 | J448: 1000 | K448: 2415 | L448: 98 | M448: 3 | N448: 61.05 | O448: 136.03 | P448: 4.06 | Q448: 0.62 | R448: 20.35 | S448: 1196
A449: huiihochen@yahoo.com | B449: xiuyan | C449: ge | D449: Monterey Park | E449: CA | F449: wu construction co | G449: Campaign_10 | H449: Facebook Ads | I449: 2024-01-23 | J449: 1000 | K449: 1004 | L449: 22 | M449: 2 | N449: 13.07 | O449: 135.32 | P449: 2.19 | Q449: 0.59 | R449: 6.54 | S449: 1864
A450: jramosdirect@yahoo.com | B450: john | C450: ramos | D450: Provo | E450: UT | F450: brownstrauss steel | G450: Campaign_17 | H450: Facebook Ads | I450: 2024-01-20 | J450: 400 | K450: 576 | L450: 12 | M450: 0 | N450: 7.35 | O450: 0 | P450: 2.08 | Q450: 0.61 | R450: 0 | S450: 1600
A451: nicole_espinoza1983@yahoo.com | B451: ronald | C451: simmons | D451: Hamilton | E451: TX | F451: flowers construction/infastrux | G451: Campaign_9 | H451: Facebook Ads | I451: 2024-01-27 | J451: 500 | K451: 1551 | L451: 68 | M451: 2 | N451: 28.87 | O451: 84.5 | P451: 4.38 | Q451: 0.42 | R451: 14.44 | S451: 3160
A452: shimia81@msn.com | B452: shimia | C452: forch | D452: Tacoma | E452: WA | F452: target | G452: Campaign_3 | H452: Facebook Ads | I452: 2024-01-21 | J452: 500 | K452: 734 | L452: 31 | M452: 2 | N452: 14.52 | O452: 80.52 | P452: 4.22 | Q452: 0.47 | R452: 7.26 | S452: 4200
A453: ms.terry7338@yahoo.com | B453: terry | C453: morgan | D453: Franklinton | E453: NC | F453: cooke health care | G453: Campaign_3 | H453: Facebook Ads | I453: 2024-01-25 | J453: 200 | K453: 1505 | L453: 65 | M453: 0 | N453: 50.69 | O453: 0 | P453: 4.32 | Q453: 0.78 | R453: 0 | S453: 1400
A454: sxynurse32@gmail.com | B454: kenneth | C454: smith | D454: Sandusky | E454: OH | F454: ohio veterans home | G454: Campaign_20 | H454: Facebook Ads | I454: 2024-01-24 | J454: 200 | K454: 1909 | L454: 42 | M454: 1 | N454: 32.51 | O454: 44.62 | P454: 2.2 | Q454: 0.77 | R454: 32.51 | S454: 1100
A455: rigmechanic2000@yahoo.com | B455: humberto | C455: botello | D455: Corpus Christ | E455: TX | F455: holt cat | G455: Campaign_20 | H455: Facebook Ads | I455: 2024-01-07 | J455: 100 | K455: 1807 | L455: 36 | M455: 0 | N455: 22.02 | O455: 0 | P455: 1.99 | Q455: 0.61 | R455: 0 | S455: 3250
A456: baybaynealy@yahoo.com | B456: gwenda | C456: nealy | D456: High Point | E456: NC | F456: kmart | G456: Campaign_12 | H456: Facebook Ads | I456: 2024-01-12 | J456: 800 | K456: 1902 | L456: 61 | M456: 0 | N456: 40.23 | O456: 0 | P456: 3.21 | Q456: 0.66 | R456: 0 | S456: 1500
A457: matilda_sanchez@hotmail.com | B457: matilda | C457: sanchez | D457: Fullerton | E457: CA | F457: homdepot | G457: Campaign_6 | H457: Facebook Ads | I457: 2024-01-26 | J457: 300 | K457: 1037 | L457: 27 | M457: 0 | N457: 14.37 | O457: 0 | P457: 2.6 | Q457: 0.53 | R457: 0 | S457: 2600
A458: adknott13@msn.com | B458: april | C458: emmel | D458: Reading | E458: PA | F458: pervading health system | G458: Campaign_3 | H458: Facebook Ads | I458: 2024-01-22 | J458: 1000 | K458: 1626 | L458: 46 | M458: 1 | N458: 21.46 | O458: 41.13 | P458: 2.83 | Q458: 0.47 | R458: 21.46 | S458: 3750
A459: lhilton89@gmail.com | B459: lakinya | C459: hilton | D459: Baltimore | E459: MD | F459: mid atlantic realty mgmt | G459: Campaign_10 | H459: Facebook Ads | I459: 2024-01-29 | J459: 500 | K459: 2063 | L459: 74 | M459: 1 | N459: 46.19 | O459: 37.33 | P459: 3.59 | Q459: 0.62 | R459: 46.19 | S459: 2250
... A658: tashahoward2@yahoo.com | B658: latasha | C658: howad | D658: Birmingham | E658: AL | F658: smooth designs | G658: Campaign_20 | H658: Facebook Ads | I658: 2024-01-29 | J658: 1000 | K658: 1906 | L658: 42 | M658: 1 | N658: 30.64 | O658: 68.3 | P658: 2.2 | Q658: 0.73 | R658: 30.64 | S658: 2000
A659: alanwaidelich@yahoo.com | B659: alan | C659: waidelich | D659: Woodstock | E659: IL | F659: 0 | G659: Campaign_17 | H659: Facebook Ads | I659: 2024-01-08 | J659: 400 | K659: 1259 | L659: 31 | M659: 0 | N659: 18.93 | O659: 0 | P659: 2.46 | Q659: 0.61 | R659: 0 | S659: 3038
A660: gsteve0786@yahoo.com | B660: gerald | C660: nelson | D660: Harrisburg | E660: PA | F660: retired | G660: Campaign_2 | H660: Facebook Ads | I660: 2024-01-14 | J660: 700 | K660: 2388 | L660: 82 | M660: 0 | N660: 41.42 | O660: 0 | P660: 3.43 | Q660: 0.51 | R660: 0 | S660: 1500
A661: anthonyfor24@aol.com | B661: anthony | C661: nelson | D661: Union City | E661: PA | F661: safelite auto glass | G661: Campaign_8 | H661: Facebook Ads | I661: 2024-01-27 | J661: 400 | K661: 1859 | L661: 49 | M661: 1 | N661: 22.24 | O661: 39.69 | P661: 2.64 | Q661: 0.45 | R661: 22.24 | S661: 1500
A662: superwomanwinona@yahoo.com | B662: marcus | C662: young | D662: Oklahoma City | E662: OK | F662: janpro | G662: Campaign_16 | H662: Facebook Ads | I662: 2024-01-23 | J662: 600 | K662: 775 | L662: 30 | M662: 0 | N662: 15.66 | O662: 0 | P662: 3.87 | Q662: 0.52 | R662: 0 | S662: 2500
A663: lakeshiamcintosh@yahoo.com | B663: lakeshia | C663: mcintosh | D663: Savannah | E663: GA | F663: coastal georgia center | G663: Campaign_13 | H663: Facebook Ads | I663: 2024-01-08 | J663: 700 | K663: 1831 | L663: 52 | M663: 0 | N663: 35.47 | O663: 0 | P663: 2.84 | Q663: 0.68 | R663: 0 | S663: 2500
A664: l.bridges1@aol.com | B664: richard | C664: bridges | D664: Loganville | E664: GA | F664: rogers bridge co inc | G664: Campaign_8 | H664: Facebook Ads | I664: 2024-01-07 | J664: 500 | K664: 2063 | L664: 47 | M664: 5 | N664: 30.51 | O664: 237.7 | P664: 2.28 | Q664: 0.65 | R664: 6.1 | S664: 4700
A665: fesagraham@aol.com | B665: nafeesah | C665: graham | D665: Upper Darby | E665: PA | F665: na | G665: Campaign_2 | H665: Facebook Ads | I665: 2024-01-17 | J665: 600 | K665: 2175 | L665: 69 | M665: 2 | N665: 55.55 | O665: 113.3 | P665: 3.17 | Q665: 0.81 | R665: 27.78 | S665: 5417
A666: aleonfam4058@yahoo.com | B666: felipe | C666: leon | D666: Santa Paula | E666: CA | F666: westlake golf coursr | G666: Campaign_7 | H666: Facebook Ads | I666: 2024-01-08 | J666: 600 | K666: 1181 | L666: 41 | M666: 1 | N666: 31.57 | O666: 52.64 | P666: 3.47 | Q666: 0.77 | R666: 31.57 | S666: 2250
A667: michelleholli@yahoo.com | B667: michelle | C667: scott | D667: Hollister | E667: CA | F667: alliedbarton | G667: Campaign_12 | H667: Facebook Ads | I667: 2024-01-22 | J667: 600 | K667: 1122 | L667: 22 | M667: 2 | N667: 9.45 | O667: 70.51 | P667: 1.96 | Q667: 0.43 | R667: 4.72 | S667: 5000
A668: slimdrink@aol.com | B668: thomas | C668: haynes | D668: Riverview | E668: FL | F668: brinks ink | G668: Campaign_2 | H668: Facebook Ads | I668: 2024-01-18 | J668: 800 | K668: 561 | L668: 24 | M668: 0 | N668: 16.59 | O668: 0 | P668: 4.28 | Q668: 0.69 | R668: 0 | S668: 3250
A669: mr.martin2212@yahoo.com | B669: christophe | C669: martin | D669: Memphis | E669: TN | F669: jabil | G669: Campaign_16 | H669: Facebook Ads | I669: 2024-01-06 | J669: 700 | K669: 669 | L669: 11 | M669: 0 | N669: 8.19 | O669: 0 | P669: 1.64 | Q669: 0.74 | R669: 0 | S669: 2346
A670: lennyshaw101@hotmail.com | B670: leonard | C670: shough | D670: Pittsburgh | E670: PA | F670: appliance warehouse | G670: Campaign_15 | H670: Facebook Ads | I670: 2024-01-06 | J670: 500 | K670: 2169 | L670: 76 | M670: 3 | N670: 49.25 | O670: 151.63 | P670: 3.5 | Q670: 0.65 | R670: 16.42 | S670: 5371
A671: shakilpatrick@yahoo.com | B671: shana | C671: kilpatrick | D671: Oakland | E671: CA | F671: premier staffing | G671: Campaign_1 | H671: Facebook Ads | I671: 2024-01-23 | J671: 500 | K671: 1880 | L671: 58 | M671: 1 | N671: 43.29 | O671: 58.75 | P671: 3.09 | Q671: 0.75 | R671: 43.29 | S671: 2200
... A704: sarahysasaga@hotmail.com | B704: johnny | C704: ysasaga | D704: Houston | E704: TX | F704: extended stay hotel | G704: Campaign_6 | H704: Facebook Ads | I704: 2024-01-23 | J704: 200 | K704: 1382 | L704: 28 | M704: 2 | N704: 21.01 | O704: 87.52 | P704: 2.03 | Q704: 0.75 | R704: 10.5 | S704: 2250
A705: martinjeffrey62@yahoo.com | B705: jeffrey | C705: martin | D705: Hampton | E705: VA | F705: 0 | G705: Campaign_5 | H705: Facebook Ads | I705: 2024-01-28 | J705: 1000 | K705: 1239 | L705: 48 | M705: 2 | N705: 27.5 | O705: 76.88 | P705: 3.87 | Q705: 0.57 | R705: 13.75 | S705: 2250
A706: bigchachi3@msn.com | B706: chauncey | C706: hyslip | D706: Jackson | E706: MO | F706: sears holdings | G706: Campaign_15 | H706: Facebook Ads | I706: 2024-01-18 | J706: 1000 | K706: 2192 | L706: 95 | M706: 3 | N706: 60.48 | O706: 168.07 | P706: 4.33 | Q706: 0.64 | R706: 20.16 | S706: 2299
A707: pam7108@yahoo.com | B707: pamela | C707: carpenter | D707: Monrovia | E707: IN | F707: genco bd | G707: Campaign_4 | H707: Facebook Ads | I707: 2024-01-07 | J707: 800 | K707: 1435 | L707: 30 | M707: 1 | N707: 23.04 | O707: 52.91 | P707: 2.09 | Q707: 0.77 | R707: 23.04 | S707: 4500
A708: hateraid10@yahoo.com | B708: jason | C708: thompson | D708: Canton | E708: MS | F708: mvp | G708: Campaign_4 | H708: Facebook Ads | I708: 2024-01-30 | J708: 600 | K708: 2009 | L708: 73 | M708: 0 | N708: 50.14 | O708: 0 | P708: 3.63 | Q708: 0.69 | R708: 0 | S708: 3750
A709: callieandinnall@yahoo.com | B709: calliean | C709: dinnall | D709: Lithonia | E709: GA | F709: hampton inn | G709: Campaign_18 | H709: Facebook Ads | I709: 2024-01-06 | J709: 400 | K709: 990 | L709: 23 | M709: 0 | N709: 19.29 | O709: 0 | P709: 2.32 | Q709: 0.84 | R709: 0 | S709: 1100
A710: suzy9602@gmail.com | B710: susana | C710: martinez | D710: Katy | E710: TX | F710: the bancorp bank | G710: Campaign_9 | H710: Facebook Ads | I710: 2024-01-25 | J710: 800 | K710: 1106 | L710: 24 | M710: 0 | N710: 15.92 | O710: 0 | P710: 2.17 | Q710: 0.66 | R710: 0 | S710: 2250
A711: peggylacey74@yahoo.com | B711: margaret | C711: lacey | D711: Canal Winches | E711: OH | F711: fci academy | G711: Campaign_7 | H711: Facebook Ads | I711: 2024-01-28 | J711: 500 | K711: 727 | L711: 29 | M711: 2 | N711: 23.18 | O711: 74.02 | P711: 3.99 | Q711: 0.8 | R711: 11.59 | S711: 2501
A712: sarah37660@yahoo.com | B712: sarah | C712: light | D712: Rogersville | E712: TN | F712: holston medical group | G712: Campaign_18 | H712: Facebook Ads | I712: 2024-01-09 | J712: 300 | K712: 2091 | L712: 81 | M712: 1 | N712: 64.41 | O712: 51.21 | P712: 3.87 | Q712: 0.8 | R712: 64.41 | S712: 1256
A713: tthomskywalker52@yahoo.com | B713: tommie | C713: thompson | D713: Phoenix | E713: AZ | F713: us airways | G713: Campaign_20 | H713: Facebook Ads | I713: 2024-01-20 | J713: 100 | K713: 2253 | L713: 84 | M713: 0 | N713: 58.04 | O713: 0 | P713: 3.73 | Q713: 0.69 | R713: 0 | S713: 1580
A714: taya.gowdy@yahoo.com | B714: taya | C714: gowdy | D714: Louisville | E714: KY | F714: packaging unlimited | G714: Campaign_5 | H714: Facebook Ads | I714: 2024-01-13 | J714: 1000 | K714: 1235 | L714: 55 | M714: 5 | N714: 22.09 | O714: 275.85 | P714: 4.45 | Q714: 0.4 | R714: 4.42 | S714: 3109
A715: bookercv@cox.net | B715: carrie | C715: johnson book | D715: Las Vegas | E715: NV | F715: national security technologies | G715: Campaign_19 | H715: Facebook Ads | I715: 2024-01-23 | J715: 800 | K715: 2327 | L715: 88 | M715: 0 | N715: 60.49 | O715: 0 | P715: 3.78 | Q715: 0.69 | R715: 0 | S715: 1950
A716: dchance1@hotmail.com | B716: donald | C716: chance | D716: Las Vegas | E716: NV | F716: ssdi | G716: Campaign_12 | H716: Facebook Ads | I716: 2024-01-16 | J716: 600 | K716: 998 | L716: 27 | M716: 2 | N716: 21.39 | O716: 123.13 | P716: 2.71 | Q716: 0.79 | R716: 10.7 | S716: 2200
A717: drizzleusmc1982@yahoo.com | B717: derrick | C717: pedraza | D717: Kingsville | E717: TX | F717: dept of the navy | G717: Campaign_2 | H717: Facebook Ads | I717: 2024-01-29 | J717: 1000 | K717: 506 | L717: 8 | M717: 1 | N717: 5.48 | O717: 46.36 | P717: 1.58 | Q717: 0.68 | R717: 5.48 | S717: 2200
... A947: kfashe2012@gmail.com | B947: natasha | C947: rouse | D947: Detroit | E947: MI | F947: checkers | G947: Campaign_4 | H947: Facebook Ads | I947: 2024-01-28 | J947: 500 | K947: 1932 | L947: 54 | M947: 4 | N947: 36.26 | O947: 205.99 | P947: 2.8 | Q947: 0.67 | R947: 9.06 | S947: 2700
A948: mauricep_8@hotmail.com | B948: maurice | C948: powell | D948: McKees Rocks | E948: PA | F948: 0 | G948: Campaign_11 | H948: Facebook Ads | I948: 2024-01-30 | J948: 500 | K948: 2063 | L948: 87 | M948: 0 | N948: 68.75 | O948: 0 | P948: 4.22 | Q948: 0.79 | R948: 0 | S948: 2600
A949: queenbananah@yahoo.com | B949: hannah | C949: kotey | D949: Montebello | E949: CA | F949: ca appellate project | G949: Campaign_5 | H949: Facebook Ads | I949: 2024-01-11 | J949: 800 | K949: 617 | L949: 23 | M949: 0 | N949: 18.14 | O949: 0 | P949: 3.73 | Q949: 0.79 | R949: 0 | S949: 4800
A950: dejastaley@yahoo.com | B950: deandre | C950: staley | D950: Jacksonville | E950: FL | F950: applebees | G950: Campaign_2 | H950: Facebook Ads | I950: 2024-01-15 | J950: 500 | K950: 2483 | L950: 73 | M950: 2 | N950: 41.32 | O950: 78.91 | P950: 2.94 | Q950: 0.57 | R950: 20.66 | S950: 2700
A951: bbintijua@hotmail.com | B951: barbara | C951: rae | D951: Richmond | E951: VA | F951: ssdi | G951: Campaign_4 | H951: Facebook Ads | I951: 2024-01-25 | J951: 100 | K951: 913 | L951: 22 | M951: 2 | N951: 15.95 | O951: 126.07 | P951: 2.41 | Q951: 0.72 | R951: 7.98 | S951: 3000
A952: jshannon1284@gmail.com | B952: jimel | C952: shannon | D952: Hickory | E952: NC | F952: buffalo wild wings | G952: Campaign_8 | H952: Facebook Ads | I952: 2024-01-20 | J952: 600 | K952: 1510 | L952: 56 | M952: 0 | N952: 34.3 | O952: 0 | P952: 3.71 | Q952: 0.61 | R952: 0 | S952: 4000
A953: www.danamesofine1@yahoo.com | B953: dana | C953: bullard | D953: Philadelphia | E953: PA | F953: homemakerservices | G953: Campaign_3 | H953: Facebook Ads | I953: 2024-01-08 | J953: 600 | K953: 1762 | L953: 38 | M953: 4 | N953: 18.67 | O953: 272.45 | P953: 2.16 | Q953: 0.49 | R953: 4.67 | S953: 2708
A954: nathan1327thomas@yahoo.com | B954: nathan | C954: thomas | D954: Washington | E954: DC | F954: tiny findings | G954: Campaign_20 | H954: Facebook Ads | I954: 2024-01-03 | J954: 500 | K954: 1258 | L954: 55 | M954: 4 | N954: 45.72 | O954: 174.24 | P954: 4.37 | Q954: 0.83 | R954: 11.43 | S954: 3115
A955: blowinkisses88@gmail.com | B955: tahinah | C955: borgella | D955: West Orange | E955: NJ | F955: ssi | G955: Campaign_17 | H955: Facebook Ads | I955: 2024-01-18 | J955: 100 | K955: 2425 | L955: 100 | M955: 8 | N955: 43.2 | O955: 535.48 | P955: 4.12 | Q955: 0.43 | R955: 5.4 | S955: 2349
A956: chaseeileen2012@yahoo.com | B956: eileen | C956: chase | D956: Bangor | E956: ME | F956: attitudes | G956: Campaign_16 | H956: Facebook Ads | I956: 2024-01-19 | J956: 600 | K956: 1021 | L956: 35 | M956: 1 | N956: 27.84 | O956: 63.32 | P956: 3.43 | Q956: 0.8 | R956: 27.84 | S956: 1700
A957: tyanashaw09@gmail.com | B957: tyana | C957: shaw | D957: Oakland | E957: CA | F957: ihss | G957: Campaign_8 | H957: Facebook Ads | I957: 2024-01-07 | J957: 300 | K957: 2279 | L957: 55 | M957: 2 | N957: 27.91 | O957: 135.64 | P957: 2.41 | Q957: 0.51 | R957: 13.96 | S957: 3300
A958: aprilstatzel@yahoo.com | B958: lynn | C958: statzel | D958: Irvine | E958: CA | F958: l stewart | G958: Campaign_12 | H958: Facebook Ads | I958: 2024-01-26 | J958: 300 | K958: 1922 | L958: 61 | M958: 5 | N958: 37.8 | O958: 257.68 | P958: 3.17 | Q958: 0.62 | R958: 7.56 | S958: 2400
A959: joel.e.114@live.com | B959: joel | C959: vaughn | D959: Eden | E959: NC | F959: rockingham co sherif | G959: Campaign_5 | H959: Facebook Ads | I959: 2024-01-05 | J959: 500 | K959: 2397 | L959: 47 | M959: 0 | N959: 33.94 | O959: 0 | P959: 1.96 | Q959: 0.72 | R959: 0 | S959: 1900
A960: rossjamiejosh@gmail.com | B960: mimi | C960: ross | D960: Chino | E960: CA | F960: first data amour group | G960: Campaign_3 | H960: Facebook Ads | I960: 2024-01-03 | J960: 300 | K960: 1668 | L960: 52 | M960: 0 | N960: 31.59 | O960: 0 | P960: 3.12 | Q960: 0.61 | R960: 0 | S960: 3900
... A987: agnes2cute@yahoo.com | B987: rebecca | C987: budge | D987: Rancho Cordov | E987: CA | F987: benefits | G987: Campaign_5 | H987: Facebook Ads | I987: 2024-01-18 | J987: 700 | K987: 2060 | L987: 55 | M987: 0 | N987: 30.89 | O987: 0 | P987: 2.67 | Q987: 0.56 | R987: 0 | S987: 2583
A988: filmfantasywisconsin@yahoo.com | B988: sonja | C988: joseph | D988: Waukesha | E988: WI | F988: 0 | G988: Campaign_6 | H988: Facebook Ads | I988: 2024-01-17 | J988: 300 | K988: 1250 | L988: 20 | M988: 0 | N988: 16.99 | O988: 0 | P988: 1.6 | Q988: 0.85 | R988: 0 | S988: 4500
A989: daphenereed@hotmail.com | B989: timon | C989: smith | D989: Cleveland | E989: OH | F989: daffs darling daycare academy | G989: Campaign_2 | H989: Facebook Ads | I989: 2024-01-22 | J989: 700 | K989: 653 | L989: 14 | M989: 1 | N989: 11.64 | O989: 35.18 | P989: 2.14 | Q989: 0.83 | R989: 11.64 | S989: 5000
A990: javieralejandrocamacho@gmail.com | B990: javier | C990: camacho | D990: Chicago | E990: IL | F990: scopelit | G990: Campaign_12 | H990: Facebook Ads | I990: 2024-01-27 | J990: 100 | K990: 871 | L990: 25 | M990: 2 | N990: 21.19 | O990: 120.86 | P990: 2.87 | Q990: 0.85 | R990: 10.6 | S990: 2400
A991: boricquachick09@aol.com | B991: erica | C991: merced | D991: Lake Worth | E991: FL | F991: denny s | G991: Campaign_1 | H991: Facebook Ads | I991: 2024-01-07 | J991: 1000 | K991: 757 | L991: 17 | M991: 0 | N991: 12.33 | O991: 0 | P991: 2.25 | Q991: 0.73 | R991: 0 | S991: 800
A992: susancheapouv@yahoo.com | B992: susan | C992: chea | D992: Modesto | E992: CA | F992: panda express | G992: Campaign_3 | H992: Facebook Ads | I992: 2024-01-20 | J992: 1000 | K992: 1362 | L992: 47 | M992: 0 | N992: 34.49 | O992: 0 | P992: 3.45 | Q992: 0.73 | R992: 0 | S992: 2200
A993: misshardy2007@yahoo.com | B993: cassandra | C993: hardy | D993: Rockford | E993: IL | F993: alpine clinic | G993: Campaign_18 | H993: Facebook Ads | I993: 2024-01-01 | J993: 800 | K993: 2314 | L993: 91 | M993: 2 | N993: 69.18 | O993: 103.08 | P993: 3.93 | Q993: 0.76 | R993: 34.59 | S993: 2112
A994: ronda.jones77@gmail.com | B994: ronda | C994: jones | D994: Ogden | E994: UT | F994: irs | G994: Campaign_19 | H994: Facebook Ads | I994: 2024-01-30 | J994: 700 | K994: 2483 | L994: 51 | M994: 0 | N994: 39.85 | O994: 0 | P994: 2.05 | Q994: 0.78 | R994: 0 | S994: 1800
A995: dormull@live.com | B995: nicole | C995: burrell | D995: Van Nuys | E995: CA | F995: wellpoint | G995: Campaign_20 | H995: Facebook Ads | I995: 2024-01-06 | J995: 200 | K995: 1750 | L995: 58 | M995: 0 | N995: 44.84 | O995: 0 | P995: 3.31 | Q995: 0.77 | R995: 0 | S995: 5000
A996: goethemom@aol.com | B996: priscilla | C996: goethe | D996: Bradenton | E996: FL | F996: our daily bread of braden | G996: Campaign_14 | H996: Facebook Ads | I996: 2024-01-18 | J996: 200 | K996: 2187 | L996: 77 | M996: 3 | N996: 38.28 | O996: 210.39 | P996: 3.52 | Q996: 0.5 | R996: 12.76 | S996: 1343
A997: sue03best@yahoo.com | B997: susan | C997: best | D997: Modesto | E997: CA | F997: franklinanddowns | G997: Campaign_9 | H997: Facebook Ads | I997: 2024-01-05 | J997: 800 | K997: 925 | L997: 19 | M997: 0 | N997: 9.51 | O997: 0 | P997: 2.05 | Q997: 0.5 | R997: 0 | S997: 4000
A998: vickijcote@hotmail.com | B998: vicki | C998: cote | D998: San Diego | E998: CA | F998: jobcorps | G998: Campaign_14 | H998: Facebook Ads | I998: 2024-01-20 | J998: 200 | K998: 1760 | L998: 66 | M998: 7 | N998: 42.09 | O998: 436.71 | P998: 3.75 | Q998: 0.64 | R998: 6.01 | S998: 5001
A999: varshachandra_510@yahoo.com | B999: varsha | C999: chandra | D999: San Mateo | E999: CA | F999: primepay | G999: Campaign_5 | H999: Facebook Ads | I999: 2024-01-25 | J999: 1000 | K999: 2078 | L999: 37 | M999: 0 | N999: 27.96 | O999: 0 | P999: 1.78 | Q999: 0.76 | R999: 0 | S999: 2400
A1000: jackie_guerrrant@hotmail.com | B1000: jackie | C1000: guerrant | D1000: Cincinnati | E1000: OH | F1000: resident homes corp. | G1000: Campaign_1 | H1000: Facebook Ads | I1000: 2024-01-17 | J1000: 100 | K1000: 1124 | L1000: 33 | M1000: 0 | N1000: 21.22 | O1000: 0 | P1000: 2.94 | Q1000: 0.64 | R1000: 0 | S1000: 2167
... A1120: carolo@gmail.com | B1120: carol | C1120: hite | D1120: Fort Huachuca | E1120: AZ | F1120: mancharm | G1120: Campaign_17 | H1120: Facebook Ads | I1120: 2024-01-03 | J1120: 1000 | K1120: 1271 | L1120: 32 | M1120: 1 | N1120: 26.18 | O1120: 55.42 | P1120: 2.52 | Q1120: 0.82 | R1120: 26.18 | S1120: 5200
A1121: c4mom2dr@yahoo.com | B1121: rosemary | C1121: isaac | D1121: Williamsburg | E1121: VA | F1121: 0 | G1121: Campaign_3 | H1121: Facebook Ads | I1121: 2024-01-07 | J1121: 1000 | K1121: 1350 | L1121: 24 | M1121: 0 | N1121: 18.7 | O1121: 0 | P1121: 1.78 | Q1121: 0.78 | R1121: 0 | S1121: 2500
A1122: cusuneve1959@hotmail.com | B1122: john | C1122: green | D1122: Issaquah | E1122: WA | F1122: almacs | G1122: Campaign_3 | H1122: Facebook Ads | I1122: 2024-01-06 | J1122: 600 | K1122: 924 | L1122: 27 | M1122: 1 | N1122: 12.6 | O1122: 47.46 | P1122: 2.92 | Q1122: 0.47 | R1122: 12.6 | S1122: 1000
...

Sheet raw_tiktok
A1: EMAIL | B1: firstname | C1: lastname | D1: city | E1: state | F1: employer | G1: campaign_name | H1: platform | I1: Date | J1: loan_amount.1 | K1: impressions | L1: clicks | M1: conversions | N1: cost | O1: revenue | P1: CTR | Q1: CPC | R1: CPA | S1: salary
A2: ddarmahn@yahoo.com | B2: darmahn | C2: dixon | D2: Oakland | E2: CA | F2: state of california | G2: Campaign_9 | H2: TikTok Ads | I2: 2024-01-29 | J2: 500 | K2: 815 | L2: 33 | M2: 0 | N2: 26.72 | O2: 0 | P2: 4.05 | Q2: 0.81 | R2: 0 | S2: 4800
A3: anica79@yahoo.com | B3: candice | C3: george | D3: Seffner | E3: FL | F3: security finance | G3: Campaign_1 | H3: TikTok Ads | I3: 2024-01-30 | J3: 300 | K3: 1053 | L3: 29 | M3: 0 | N3: 15.22 | O3: 0 | P3: 2.75 | Q3: 0.52 | R3: 0 | S3: 1733
A4: aliclift.ac@gmail.com | B4: alexandria | C4: clift | D4: San Antonio | E4: TX | F4: united marketing group | G4: Campaign_3 | H4: TikTok Ads | I4: 2024-01-26 | J4: 400 | K4: 1557 | L4: 63 | M4: 2 | N4: 51.76 | O4: 82.43 | P4: 4.05 | Q4: 0.82 | R4: 25.88 | S4: 1800
A5: davidvonalst@yahoo.com | B5: barbara | C5: vonalst | D5: Pahrump | E5: NV | F5: self employed | G5: Campaign_8 | H5: TikTok Ads | I5: 2024-01-25 | J5: 800 | K5: 832 | L5: 32 | M5: 1 | N5: 22.24 | O5: 73.82 | P5: 3.85 | Q5: 0.7 | R5: 22.24 | S5: 1000
A6: arcuricraig@gmail.com | B6: craig | C6: arcuri | D6: Susquehanna | E6: PA | F6: penn star bank | G6: Campaign_16 | H6: TikTok Ads | I6: 2024-01-15 | J6: 600 | K6: 627 | L6: 10 | M6: 0 | N6: 8.08 | O6: 0 | P6: 1.59 | Q6: 0.81 | R6: 0 | S6: 6461
A7: hyarpih98@gmail.com | B7: ayarpi | C7: sogomonyan | D7: North Hollywo | E7: CA | F7: hpmc | G7: Campaign_7 | H7: TikTok Ads | I7: 2024-01-26 | J7: 200 | K7: 919 | L7: 23 | M7: 2 | N7: 16.29 | O7: 149.55 | P7: 2.5 | Q7: 0.71 | R7: 8.14 | S7: 5666
A8: kenishatquick@hotmail.com | B8: kenisha | C8: quick | D8: West Point | E8: GA | F8: soundtrack | G8: Campaign_17 | H8: TikTok Ads | I8: 2024-01-23 | J8: 800 | K8: 1099 | L8: 28 | M8: 1 | N8: 13.24 | O8: 46.5 | P8: 2.55 | Q8: 0.47 | R8: 13.24 | S8: 2250
A9: fields1900@gmail.com | B9: nena | C9: fields | D9: Norristown | E9: PA | F9: legal aid of se pa | G9: Campaign_6 | H9: TikTok Ads | I9: 2024-01-15 | J9: 500 | K9: 2129 | L9: 50 | M9: 2 | N9: 34.28 | O9: 70.93 | P9: 2.35 | Q9: 0.69 | R9: 17.14 | S9: 3900
A10: hectorcolonarias@yahoo.com | B10: hector | C10: colon | D10: caguas | E10: PA | F10: gilster marylee | G10: Campaign_10 | H10: TikTok Ads | I10: 2024-01-09 | J10: 100 | K10: 2165 | L10: 49 | M10: 5 | N10: 23.79 | O10: 195.93 | P10: 2.26 | Q10: 0.49 | R10: 4.76 | S10: 3750
A11: helenjdavis@hotmail.com | B11: helen | C11: davis | D11: Harrisburg | E11: PA | F11: star merchant services | G11: Campaign_14 | H11: TikTok Ads | I11: 2024-01-22 | J11: 600 | K11: 895 | L11: 23 | M11: 0 | N11: 18.4 | O11: 0 | P11: 2.57 | Q11: 0.8 | R11: 0 | S11: 1463
A12: jeannieandtrudy@hotmail.com | B12: trudy | C12: givens | D12: Porterville | E12: CA | F12: 0 | G12: Campaign_7 | H12: TikTok Ads | I12: 2024-01-13 | J12: 1000 | K12: 1495 | L12: 66 | M12: 6 | N12: 46.54 | O12: 347.09 | P12: 4.41 | Q12: 0.71 | R12: 7.76 | S12: 5000
A13: krtjjjj@yahoo.com | B13: terri | C13: hilton | D13: Philadelphia | E13: PA | F13: disabled | G13: Campaign_13 | H13: TikTok Ads | I13: 2024-01-25 | J13: 700 | K13: 2347 | L13: 105 | M13: 10 | N13: 77.52 | O13: 356.18 | P13: 4.47 | Q13: 0.74 | R13: 7.75 | S13: 2078
A14: harold.beal@gmail.com | B14: harold | C14: beal | D14: Baytown | E14: TX | F14: gold medal | G14: Campaign_4 | H14: TikTok Ads | I14: 2024-01-13 | J14: 400 | K14: 2007 | L14: 76 | M14: 2 | N14: 59.31 | O14: 97.19 | P14: 3.79 | Q14: 0.78 | R14: 29.66 | S14: 1700
A15: dream99103@yahoo.com | B15: cassandra | C15: johnson | D15: Harvey | E15: IL | F15: johnson transportation | G15: Campaign_17 | H15: TikTok Ads | I15: 2024-01-18 | J15: 1000 | K15: 2243 | L15: 62 | M15: 2 | N15: 28.38 | O15: 107.09 | P15: 2.76 | Q15: 0.46 | R15: 14.19 | S15: 4500
A16: lilbetsy9@yahoo.com | B16: elizabeth | C16: banks | D16: Houston | E16: TX | F16: fidelity national title | G16: Campaign_10 | H16: TikTok Ads | I16: 2024-01-31 | J16: 700 | K16: 694 | L16: 25 | M16: 2 | N16: 16.75 | O16: 81.37 | P16: 3.6 | Q16: 0.67 | R16: 8.38 | S16: 3519
A17: lukeddavisjr@yahoo.com | B17: luke | C17: davis | D17: Chicago | E17: IL | F17: job corps | G17: Campaign_15 | H17: TikTok Ads | I17: 2024-01-05 | J17: 400 | K17: 1545 | L17: 43 | M17: 1 | N17: 31.69 | O17: 62.6 | P17: 2.78 | Q17: 0.74 | R17: 31.69 | S17: 5200
A18: lanies1026@yahoo.com | B18: terri | C18: dyson | D18: Woodbridge | E18: VA | F18: dc trails | G18: Campaign_16 | H18: TikTok Ads | I18: 2024-01-05 | J18: 200 | K18: 951 | L18: 16 | M18: 0 | N18: 7.51 | O18: 0 | P18: 1.68 | Q18: 0.47 | R18: 0 | S18: 2250
A19: jonniewalker7@gmail.com | B19: jonnie | C19: walker | D19: Allen | E19: TX | F19: walmart | G19: Campaign_4 | H19: TikTok Ads | I19: 2024-01-18 | J19: 400 | K19: 1188 | L19: 19 | M19: 0 | N19: 12.18 | O19: 0 | P19: 1.6 | Q19: 0.64 | R19: 0 | S19: 2167
A20: davisdanat@gmail.com | B20: dana | C20: davis | D20: Trenton | E20: NC | F20: caswell center | G20: Campaign_4 | H20: TikTok Ads | I20: 2024-01-07 | J20: 700 | K20: 1858 | L20: 28 | M20: 0 | N20: 20.03 | O20: 0 | P20: 1.51 | Q20: 0.72 | R20: 0 | S20: 3004
A21: juliawendling30@yahoo.com | B21: julia | C21: wendling | D21: Canton | E21: OH | F21: j&k subway | G21: Campaign_7 | H21: TikTok Ads | I21: 2024-01-13 | J21: 800 | K21: 691 | L21: 22 | M21: 1 | N21: 10.53 | O21: 54.33 | P21: 3.18 | Q21: 0.48 | R21: 10.53 | S21: 1500
A22: webster536085@bellsouth.net | B22: shelly | C22: williams | D22: Carrollton | E22: GA | F22: truckin together | G22: Campaign_13 | H22: TikTok Ads | I22: 2024-01-12 | J22: 100 | K22: 1889 | L22: 45 | M22: 4 | N22: 26.01 | O22: 262.51 | P22: 2.38 | Q22: 0.58 | R22: 6.5 | S22: 2300
A23: saritamd2u@yahoo.com | B23: sarita | C23: davis | D23: Macon | E23: GA | F23: nu attraction | G23: Campaign_6 | H23: TikTok Ads | I23: 2024-01-09 | J23: 400 | K23: 942 | L23: 21 | M23: 0 | N23: 10.33 | O23: 0 | P23: 2.23 | Q23: 0.49 | R23: 0 | S23: 1733
A24: seniorayanda@yahoo.com | B24: ayanda | C24: akagha | D24: Arlington | E24: TX | F24: comforcare senior services | G24: Campaign_16 | H24: TikTok Ads | I24: 2024-01-09 | J24: 200 | K24: 1158 | L24: 47 | M24: 1 | N24: 37.51 | O24: 46.69 | P24: 4.06 | Q24: 0.8 | R24: 37.51 | S24: 4882
A25: gbfitzgerald2001@yahoo.com | B25: geraldine | C25: fitzgerald | D25: Chicago | E25: IL | F25: 0 | G25: Campaign_17 | H25: TikTok Ads | I25: 2024-01-18 | J25: 800 | K25: 692 | L25: 17 | M25: 1 | N25: 14.42 | O25: 67.06 | P25: 2.46 | Q25: 0.85 | R25: 14.42 | S25: 1500
A26: rainyweather10@yahoo.com | B26: jordan | C26: musguire | D26: New Galilee | E26: PA | F26: musguire milling | G26: Campaign_5 | H26: TikTok Ads | I26: 2024-01-14 | J26: 400 | K26: 2364 | L26: 78 | M26: 0 | N26: 61.3 | O26: 0 | P26: 3.3 | Q26: 0.79 | R26: 0 | S26: 5843
A27: rdprotruckdriver@aol.com | B27: raymond | C27: dougher | D27: Pittston | E27: PA | F27: unempolyed | G27: Campaign_2 | H27: TikTok Ads | I27: 2024-01-28 | J27: 200 | K27: 1782 | L27: 52 | M27: 4 | N27: 41.87 | O27: 241.93 | P27: 2.92 | Q27: 0.81 | R27: 10.47 | S27: 915
A28: sonialatejana@yahoo.com | B28: sonia | C28: orozco | D28: West Jordan | E28: UT | F28: jordan school district | G28: Campaign_18 | H28: TikTok Ads | I28: 2024-01-03 | J28: 500 | K28: 995 | L28: 19 | M28: 0 | N28: 9.71 | O28: 0 | P28: 1.91 | Q28: 0.51 | R28: 0 | S28: 4500
A29: wareagle7474.tjc@gmail.com | B29: thelma | C29: colovin | D29: Crestview | E29: FL | F29: state of florida | G29: Campaign_6 | H29: TikTok Ads | I29: 2024-01-28 | J29: 800 | K29: 1201 | L29: 41 | M29: 4 | N29: 23.54 | O29: 140.7 | P29: 3.41 | Q29: 0.57 | R29: 5.88 | S29: 2000
A30: sexytaetae41@gmail.com | B30: shanta | C30: walker | D30: Victorville | E30: CA | F30: ihss | G30: Campaign_18 | H30: TikTok Ads | I30: 2024-01-23 | J30: 800 | K30: 1538 | L30: 40 | M30: 1 | N30: 30.12 | O30: 54.73 | P30: 2.6 | Q30: 0.75 | R30: 30.12 | S30: 1100
A31: rabago@gmail.com | B31: annie | C31: rabago | D31: Fontana | E31: CA | F31: super shops | G31: Campaign_5 | H31: TikTok Ads | I31: 2024-01-01 | J31: 800 | K31: 2456 | L31: 40 | M31: 3 | N31: 29.52 | O31: 158.01 | P31: 1.63 | Q31: 0.74 | R31: 9.84 | S31: 4108
A32: meprgirl69@yahoo.com | B32: confesora | C32: lopez | D32: Cleveland | E32: OH | F32: alliance | G32: Campaign_5 | H32: TikTok Ads | I32: 2024-01-07 | J32: 100 | K32: 2096 | L32: 44 | M32: 0 | N32: 19.26 | O32: 0 | P32: 2.1 | Q32: 0.44 | R32: 0 | S32: 2700
A33: ronnie.stang@rockets.utoledo.edu | B33: ronnie | C33: stang | D33: Toledo | E33: OH | F33: fifth third bank | G33: Campaign_7 | H33: TikTok Ads | I33: 2024-01-01 | J33: 800 | K33: 2054 | L33: 85 | M33: 2 | N33: 45.28 | O33: 113.29 | P33: 4.14 | Q33: 0.53 | R33: 22.64 | S33: 4000
A34: lacourparis@yahoo.com | B34: paris | C34: lacour | D34: Chicago | E34: IL | F34: center for community academic | G34: Campaign_13 | H34: TikTok Ads | I34: 2024-01-28 | J34: 500 | K34: 1061 | L34: 28 | M34: 0 | N34: 19.79 | O34: 0 | P34: 2.64 | Q34: 0.71 | R34: 0 | S34: 3000
A35: amberdinni@aol.com | B35: amber | C35: wagner | D35: San Antonio | E35: TX | F35: state of texas | G35: Campaign_1 | H35: TikTok Ads | I35: 2024-01-24 | J35: 700 | K35: 1555 | L35: 65 | M35: 5 | N35: 46.9 | O35: 279.26 | P35: 4.18 | Q35: 0.72 | R35: 9.38 | S35: 1975
A36: apopkamomof4@gmail.com | B36: luci | C36: sheehan | D36: Apopka | E36: FL | F36: virgina calvert | G36: Campaign_9 | H36: TikTok Ads | I36: 2024-01-06 | J36: 800 | K36: 1710 | L36: 29 | M36: 0 | N36: 15.31 | O36: 0 | P36: 1.7 | Q36: 0.53 | R36: 0 | S36: 4500
A37: pameva16@yahoo.com | B37: paula | C37: pamevayahooc | D37: nutley | E37: NJ | F37: the childrens place | G37: Campaign_7 | H37: TikTok Ads | I37: 2024-01-18 | J37: 100 | K37: 1737 | L37: 53 | M37: 1 | N37: 27.02 | O37: 62.61 | P37: 3.05 | Q37: 0.51 | R37: 27.02 | S37: 3521
... A377: tmmymcconnell@yahoo.com | B377: tammy | C377: mcconnell | D377: Salem | E377: AL | F377: east alabama urology | G377: Campaign_1 | H377: TikTok Ads | I377: 2024-01-10 | J377: 100 | K377: 1356 | L377: 55 | M377: 5 | N377: 22.85 | O377: 186.9 | P377: 4.06 | Q377: 0.42 | R377: 4.57 | S377: 2427
A378: dirobr76@yahoo.com | B378: diane | C378: brooks | D378: Trenton | E378: NJ | F378: 0 | G378: Campaign_5 | H378: TikTok Ads | I378: 2024-01-09 | J378: 400 | K378: 695 | L378: 29 | M378: 3 | N378: 20.32 | O378: 153.33 | P378: 4.17 | Q378: 0.7 | R378: 6.77 | S378: 1750
A379: jerrynleah@hotmail.com | B379: angie | C379: russell | D379: Latonia | E379: KY | F379: dhl | G379: Campaign_16 | H379: TikTok Ads | I379: 2024-01-28 | J379: 400 | K379: 1545 | L379: 65 | M379: 2 | N379: 45.62 | O379: 114.98 | P379: 4.21 | Q379: 0.7 | R379: 22.81 | S379: 3750
A380: sabrinasexy2386@yahoo.com | B380: sabrina | C380: robinson | D380: Palatka | E380: FL | F380: palatka health care | G380: Campaign_11 | H380: TikTok Ads | I380: 2024-01-03 | J380: 100 | K380: 2436 | L380: 66 | M380: 1 | N380: 47.42 | O380: 65.24 | P380: 2.71 | Q380: 0.72 | R380: 47.42 | S380: 1501
A381: 907izer@gmail.com | B381: christophe | C381: duvall | D381: Anchorage | E381: AK | F381: alaska snow removal | G381: Campaign_11 | H381: TikTok Ads | I381: 2024-01-31 | J381: 200 | K381: 1020 | L381: 26 | M381: 2 | N381: 20.17 | O381: 123.34 | P381: 2.55 | Q381: 0.78 | R381: 10.09 | S381: 2250
A382: anthonydaniels1972@yahoo.com | B382: anthony | C382: daniels | D382: Trenton | E382: NJ | F382: sms | G382: Campaign_12 | H382: TikTok Ads | I382: 2024-01-15 | J382: 1000 | K382: 1952 | L382: 57 | M382: 6 | N382: 38.66 | O382: 398.01 | P382: 2.92 | Q382: 0.68 | R382: 6.44 | S382: 1500
A383: mathewsvayeton@hotmail.com | B383: vayeton | C383: mathews | D383: Huntsville | E383: AL | F383: west corporation | G383: Campaign_16 | H383: TikTok Ads | I383: 2024-01-05 | J383: 100 | K383: 2487 | L383: 82 | M383: 0 | N383: 51.63 | O383: 0 | P383: 3.3 | Q383: 0.63 | R383: 0 | S383: 1500
A384: tiffanychantell@gmail.com | B384: tiffany | C384: lynch | D384: Richmond | E384: VA | F384: acs | G384: Campaign_2 | H384: TikTok Ads | I384: 2024-01-31 | J384: 100 | K384: 865 | L384: 27 | M384: 2 | N384: 12.15 | O384: 114.53 | P384: 3.12 | Q384: 0.45 | R384: 6.08 | S384: 3250
A385: dr8210@googlemail.com | B385: david | C385: rocha | D385: West Liberty | E385: IA | F385: plastic products co | G385: Campaign_17 | H385: TikTok Ads | I385: 2024-01-19 | J385: 1000 | K385: 658 | L385: 11 | M385: 1 | N385: 7.88 | O385: 50.45 | P385: 1.67 | Q385: 0.72 | R385: 7.88 | S385: 3000
A386: fabfourty@hotmail.com | B386: melissa | C386: wahlberg | D386: Baraga | E386: MI | F386: northstar health system | G386: Campaign_14 | H386: TikTok Ads | I386: 2024-01-02 | J386: 300 | K386: 2441 | L386: 39 | M386: 3 | N386: 26.81 | O386: 146.88 | P386: 1.6 | Q386: 0.69 | R386: 8.94 | S386: 3750
A387: elizabeth.perez20@hotmail.com | B387: iraida | C387: perez | D387: Miami | E387: FL | F387: panalpina inc | G387: Campaign_18 | H387: TikTok Ads | I387: 2024-01-12 | J387: 200 | K387: 1275 | L387: 50 | M387: 4 | N387: 23.64 | O387: 208.22 | P387: 3.92 | Q387: 0.47 | R387: 5.91 | S387: 3000
A388: philadandra2007@yahoo.com | B388: phyllis | C388: gibbs | D388: Memphis | E388: TN | F388: abl management | G388: Campaign_4 | H388: TikTok Ads | I388: 2024-01-10 | J388: 100 | K388: 2207 | L388: 36 | M388: 0 | N388: 17.34 | O388: 0 | P388: 1.63 | Q388: 0.48 | R388: 0 | S388: 2061
A389: thelhan@saber.net | B389: thelma | C389: hansard | D389: Spanish Fork | E389: UT | F389: state assistance | G389: Campaign_15 | H389: TikTok Ads | I389: 2024-01-23 | J389: 300 | K389: 2239 | L389: 99 | M389: 10 | N389: 63.79 | O389: 746.92 | P389: 4.42 | Q389: 0.64 | R389: 6.38 | S389: 3792
A390: debra.fritch@yahoo.com | B390: debra | C390: fritch | D390: Greenville | E390: IL | F390: bond co unit 2 schoo | G390: Campaign_11 | H390: TikTok Ads | I390: 2024-01-26 | J390: 500 | K390: 1532 | L390: 49 | M390: 4 | N390: 38.67 | O390: 180.88 | P390: 3.2 | Q390: 0.79 | R390: 9.67 | S390: 1511
... A1112: davidhenke@hotmail.com | B1112: david | C1112: henke | D1112: Hesperia | E1112: CA | F1112: your future is now | G1112: Campaign_6 | H1112: TikTok Ads | I1112: 2024-01-06 | J1112: 800 | K1112: 1209 | L1112: 22 | M1112: 2 | N1112: 12.78 | O1112: 108.57 | P1112: 1.82 | Q1112: 0.58 | R1112: 6.39 | S1112: 2400
A1113: edalford@hotmail.com | B1113: erica | C1113: berry | D1113: Paterson | E1113: NJ | F1113: 0 | G1113: Campaign_17 | H1113: TikTok Ads | I1113: 2024-01-25 | J1113: 600 | K1113: 1243 | L1113: 23 | M1113: 2 | N1113: 18.68 | O1113: 135.59 | P1113: 1.85 | Q1113: 0.81 | R1113: 9.34 | S1113: 1900
A1114: louishawkins_69@hotmail.com | B1114: louis | C1114: hawkins | D1114: Freetown | E1114: IN | F1114: cfa staffing | G1114: Campaign_13 | H1114: TikTok Ads | I1114: 2024-01-23 | J1114: 1000 | K1114: 1224 | L1114: 41 | M1114: 1 | N1114: 16.86 | O1114: 59.19 | P1114: 3.35 | Q1114: 0.41 | R1114: 16.86 | S1114: 1250
A1115: kaceycrowe@yahoo.com | B1115: kacey | C1115: crowe | D1115: Indianapolis | E1115: IN | F1115: regions bank | G1115: Campaign_13 | H1115: TikTok Ads | I1115: 2024-01-17 | J1115: 600 | K1115: 1452 | L1115: 41 | M1115: 0 | N1115: 18.43 | O1115: 0 | P1115: 2.82 | Q1115: 0.45 | R1115: 0 | S1115: 2275
A1116: marcus.alexander@gmail.com | B1116: marcus | C1116: alexander | D1116: Deerwood | E1116: MN | F1116: home quarters warehouse | G1116: Campaign_14 | H1116: TikTok Ads | I1116: 2024-01-25 | J1116: 300 | K1116: 575 | L1116: 9 | M1116: 0 | N1116: 6.36 | O1116: 0 | P1116: 1.57 | Q1116: 0.71 | R1116: 0 | S1116: 2000
A1117: juanitaa@gmail.com | B1117: juanita | C1117: cole | D1117: Irvington | E1117: NJ | F1117: plan future | G1117: Campaign_18 | H1117: TikTok Ads | I1117: 2024-01-22 | J1117: 100 | K1117: 1660 | L1117: 64 | M1117: 0 | N1117: 41.91 | O1117: 0 | P1117: 3.86 | Q1117: 0.65 | R1117: 0 | S1117: 1100
A1118: cfisk14@gmail.com | B1118: christina | C1118: fisk | D1118: Willoughby | E1118: OH | F1118: top notch tutoring | G1118: Campaign_4 | H1118: TikTok Ads | I1118: 2024-01-31 | J1118: 100 | K1118: 1804 | L1118: 34 | M1118: 1 | N1118: 24.91 | O1118: 46.4 | P1118: 1.88 | Q1118: 0.73 | R1118: 24.91 | S1118: 1000
A1119: clas1940@hotmail.com | B1119: kenneth | C1119: martin | D1119: Detroit | E1119: MI | F1119: audio aid | G1119: Campaign_16 | H1119: TikTok Ads | I1119: 2024-01-25 | J1119: 300 | K1119: 1861 | L1119: 48 | M1119: 0 | N1119: 40.57 | O1119: 0 | P1119: 2.58 | Q1119: 0.85 | R1119: 0 | S1119: 1500
A1120: rtfrahm2@yahoo.com | B1120: rachel | C1120: frahm | D1120: Golden | E1120: CO | F1120: target corp | G1120: Campaign_12 | H1120: TikTok Ads | I1120: 2024-01-20 | J1120: 100 | K1120: 1128 | L1120: 20 | M1120: 0 | N1120: 10.84 | O1120: 0 | P1120: 1.77 | Q1120: 0.54 | R1120: 0 | S1120: 3300
A1121: abcool43@yahoo.com | B1121: amelia | C1121: barlow | D1121: Sacramento | E1121: CA | F1121: retired | G1121: Campaign_19 | H1121: TikTok Ads | I1121: 2024-01-20 | J1121: 300 | K1121: 2247 | L1121: 97 | M1121: 8 | N1121: 75.5 | O1121: 354.24 | P1121: 4.32 | Q1121: 0.78 | R1121: 9.44 | S1121: 3500
A1122: myrajo210@yahoo.com | B1122: mayra | C1122: artiga | D1122: Van Nuys | E1122: CA | F1122: valleypreshospital | G1122: Campaign_11 | H1122: TikTok Ads | I1122: 2024-01-20 | J1122: 700 | K1122: 2333 | L1122: 56 | M1122: 5 | N1122: 33.22 | O1122: 291.27 | P1122: 2.4 | Q1122: 0.59 | R1122: 6.64 | S1122: 2666
A1123: aureplas1@aol.com | B1123: aurelio | C1123: plascencia | D1123: San Jose | E1123: CA | F1123: jet blast | G1123: Campaign_13 | H1123: TikTok Ads | I1123: 2024-01-17 | J1123: 400 | K1123: 2449 | L1123: 55 | M1123: 0 | N1123: 24.21 | O1123: 0 | P1123: 2.25 | Q1123: 0.44 | R1123: 0 | S1123: 2611
A1124: abetmart@aol.com | B1124: albert | C1124: martinez | D1124: North Hollywo | E1124: CA | F1124: robert half int'l | G1124: Campaign_4 | H1124: TikTok Ads | I1124: 2024-01-09 | J1124: 600 | K1124: 823 | L1124: 32 | M1124: 1 | N1124: 20.51 | O1124: 68.05 | P1124: 3.89 | Q1124: 0.64 | R1124: 20.51 | S1124: 2500
A1125: kced909@yahoo.com | B1125: edward | C1125: simmons | D1125: Stone Mountai | E1125: GA | F1125: envision payment solution | G1125: Campaign_11 | H1125: TikTok Ads | I1125: 2024-01-06 | J1125: 100 | K1125: 1126 | L1125: 32 | M1125: 0 | N1125: 16.12 | O1125: 0 | P1125: 2.84 | Q1125: 0.5 | R1125: 0 | S1125: 1997
... A1278: smithjar24@gmail.com | B1278: jared | C1278: smith | D1278: Nampa | E1278: ID | F1278: idaho pizza co | G1278: Campaign_1 | H1278: TikTok Ads | I1278: 2024-01-01 | J1278: 300 | K1278: 1535 | L1278: 28 | M1278: 2 | N1278: 23.72 | O1278: 133.36 | P1278: 1.82 | Q1278: 0.85 | R1278: 11.86 | S1278: 2167
A1279: paigeteets@yahoo.com | B1279: 0 | C1279: paige | D1279: Maumee | E1279: OH | F1279: pnc bank | G1279: Campaign_12 | H1279: TikTok Ads | I1279: 2024-01-28 | J1279: 700 | K1279: 1190 | L1279: 28 | M1279: 2 | N1279: 15.84 | O1279: 115.69 | P1279: 2.35 | Q1279: 0.57 | R1279: 7.92 | S1279: 1500
A1280: anitastrahm@yahoo.com | B1280: anita | C1280: strahm | D1280: Auburn | E1280: IN | F1280: provena sacred heart home | G1280: Campaign_9 | H1280: TikTok Ads | I1280: 2024-01-29 | J1280: 800 | K1280: 1940 | L1280: 79 | M1280: 0 | N1280: 34.12 | O1280: 0 | P1280: 4.07 | Q1280: 0.43 | R1280: 0 | S1280: 4500
A1281: dntdv06@yahoo.com | B1281: dion | C1281: graham | D1281: Milford | E1281: OH | F1281: graybar | G1281: Campaign_18 | H1281: TikTok Ads | I1281: 2024-01-04 | J1281: 200 | K1281: 2398 | L1281: 46 | M1281: 5 | N1281: 20.89 | O1281: 200.46 | P1281: 1.92 | Q1281: 0.45 | R1281: 4.18 | S1281: 1500
A1282: dalinkwentkb@gmail.com | B1282: khris | C1282: briley | D1282: Ruther Glen | E1282: VA | F1282: chipotle | G1282: Campaign_14 | H1282: TikTok Ads | I1282: 2024-01-21 | J1282: 700 | K1282: 535 | L1282: 20 | M1282: 1 | N1282: 12.45 | O1282: 65.85 | P1282: 3.74 | Q1282: 0.62 | R1282: 12.45 | S1282: 3800
A1283: bsanders0487@gmail.com | B1283: brittany | C1283: sanders | D1283: Portage | E1283: IN | F1283: target | G1283: Campaign_2 | H1283: TikTok Ads | I1283: 2024-01-11 | J1283: 500 | K1283: 1552 | L1283: 46 | M1283: 1 | N1283: 19.61 | O1283: 36.62 | P1283: 2.96 | Q1283: 0.43 | R1283: 19.61 | S1283: 3000
A1284: tammyjohnsonj@aol.com | B1284: tammy | C1284: johnson | D1284: Phillipsburg | E1284: NJ | F1284: genesis | G1284: Campaign_20 | H1284: TikTok Ads | I1284: 2024-01-18 | J1284: 500 | K1284: 1271 | L1284: 53 | M1284: 2 | N1284: 41.45 | O1284: 106.02 | P1284: 4.17 | Q1284: 0.78 | R1284: 20.72 | S1284: 2346
A1285: antoine_092991@yahoo.com | B1285: antoine | C1285: simmons | D1285: Hillside | E1285: IL | F1285: uic college prep | G1285: Campaign_7 | H1285: TikTok Ads | I1285: 2024-01-27 | J1285: 400 | K1285: 2241 | L1285: 34 | M1285: 0 | N1285: 28.57 | O1285: 0 | P1285: 1.52 | Q1285: 0.84 | R1285: 0 | S1285: 1998
A1286: crosenberg225@gmail.com | B1286: colby | C1286: rosenberg | D1286: Philadelphia | E1286: PA | F1286: self | G1286: Campaign_15 | H1286: TikTok Ads | I1286: 2024-01-20 | J1286: 400 | K1286: 644 | L1286: 26 | M1286: 0 | N1286: 13.31 | O1286: 0 | P1286: 4.04 | Q1286: 0.51 | R1286: 0 | S1286: 5000
A1287: nita.4511@yahoo.com | B1287: anita | C1287: malone | D1287: Wharton | E1287: TX | F1287: bethany | G1287: Campaign_7 | H1287: TikTok Ads | I1287: 2024-01-25 | J1287: 1000 | K1287: 1906 | L1287: 85 | M1287: 0 | N1287: 48.04 | O1287: 0 | P1287: 4.46 | Q1287: 0.57 | R1287: 0 | S1287: 2500
A1288: jacksonvandervort@live.com | B1288: jackson | C1288: vandervort | D1288: Halifax | E1288: VA | F1288: tricounty community action | G1288: Campaign_7 | H1288: TikTok Ads | I1288: 2024-01-16 | J1288: 200 | K1288: 2052 | L1288: 32 | M1288: 0 | N1288: 18.67 | O1288: 0 | P1288: 1.56 | Q1288: 0.58 | R1288: 0 | S1288: 1750
A1289: babyhova2004@yahoo.com | B1289: samantha | C1289: smith | D1289: Appomattox | E1289: VA | F1289: evergreen basement systems | G1289: Campaign_2 | H1289: TikTok Ads | I1289: 2024-01-01 | J1289: 600 | K1289: 604 | L1289: 10 | M1289: 1 | N1289: 6.82 | O1289: 46.02 | P1289: 1.66 | Q1289: 0.68 | R1289: 6.82 | S1289: 3500
A1290: g.mojr@hotmail.com | B1290: gerald | C1290: moore | D1290: Saint Louis | E1290: MO | F1290: st louis childrens hospital | G1290: Campaign_2 | H1290: TikTok Ads | I1290: 2024-01-30 | J1290: 1000 | K1290: 920 | L1290: 37 | M1290: 0 | N1290: 18.97 | O1290: 0 | P1290: 4.02 | Q1290: 0.51 | R1290: 0 | S1290: 3600
A1291: hildastay10@yahoo.com | B1291: hilda | C1291: staten | D1291: Fuquay Varina | E1291: NC | F1291: exquisitey | G1291: Campaign_4 | H1291: TikTok Ads | I1291: 2024-01-06 | J1291: 600 | K1291: 787 | L1291: 26 | M1291: 1 | N1291: 15.06 | O1291: 74.42 | P1291: 3.3 | Q1291: 0.58 | R1291: 15.06 | S1291: 4000
... A1464: valles.gabriel@gmail.com | B1464: gabriel | C1464: valles | D1464: Denver | E1464: CO | F1464: ami wellness | G1464: Campaign_2 | H1464: TikTok Ads | I1464: 2024-01-22 | J1464: 700 | K1464: 941 | L1464: 14 | M1464: 0 | N1464: 8.12 | O1464: 0 | P1464: 1.49 | Q1464: 0.58 | R1464: 0 | S1464: 1625
A1465: jamesfarmer01@gmail.com | B1465: james | C1465: farmer | D1465: Cleveland | E1465: OH | F1465: 0 | G1465: Campaign_11 | H1465: TikTok Ads | I1465: 2024-01-20 | J1465: 300 | K1465: 2025 | L1465: 82 | M1465: 3 | N1465: 61.57 | O1465: 162.27 | P1465: 4.05 | Q1465: 0.75 | R1465: 20.52 | S1465: 1100
A1466: beckyflores59@yahoo.com | B1466: becky | C1466: flores | D1466: Monahans | E1466: TX | F1466: cullender | G1466: Campaign_5 | H1466: TikTok Ads | I1466: 2024-01-16 | J1466: 400 | K1466: 1313 | L1466: 30 | M1466: 2 | N1466: 21.56 | O1466: 106.74 | P1466: 2.28 | Q1466: 0.72 | R1466: 10.78 | S1466: 2100
A1467: williamsc.1032@yahoo.com | B1467: charlene | C1467: williams | D1467: Capitol Heigh | E1467: MD | F1467: shoppers food whse | G1467: Campaign_7 | H1467: TikTok Ads | I1467: 2024-01-25 | J1467: 700 | K1467: 1252 | L1467: 24 | M1467: 0 | N1467: 9.84 | O1467: 0 | P1467: 1.92 | Q1467: 0.41 | R1467: 0 | S1467: 5760
A1468: wllmsjacqueline@yahoo.com | B1468: jacqueline | C1468: williams | D1468: Fort Worth | E1468: TX | F1468: the t | G1468: Campaign_13 | H1468: TikTok Ads | I1468: 2024-01-22 | J1468: 1000 | K1468: 2278 | L1468: 80 | M1468: 1 | N1468: 56.1 | O1468: 69.55 | P1468: 3.51 | Q1468: 0.7 | R1468: 56.1 | S1468: 4536
A1469: cjwatson1178@yahoo.com | B1469: clarence | C1469: watson | D1469: Bandera | E1469: TX | F1469: flying l guest ranch | G1469: Campaign_13 | H1469: TikTok Ads | I1469: 2024-01-07 | J1469: 300 | K1469: 568 | L1469: 14 | M1469: 0 | N1469: 9.56 | O1469: 0 | P1469: 2.46 | Q1469: 0.68 | R1469: 0 | S1469: 2500
A1470: nrwillms@yahoo.com | B1470: noreen | C1470: williams | D1470: Marietta | E1470: GA | F1470: benefits | G1470: Campaign_5 | H1470: TikTok Ads | I1470: 2024-01-23 | J1470: 500 | K1470: 2317 | L1470: 68 | M1470: 1 | N1470: 45.45 | O1470: 67.83 | P1470: 2.93 | Q1470: 0.67 | R1470: 45.45 | S1470: 4000
A1471: pinkstaffkaren@yahoo.com | B1471: tiffany | C1471: burks | D1471: Amarillo | E1471: TX | F1471: aig company | G1471: Campaign_6 | H1471: TikTok Ads | I1471: 2024-01-22 | J1471: 300 | K1471: 1344 | L1471: 55 | M1471: 5 | N1471: 36.45 | O1471: 229.49 | P1471: 4.09 | Q1471: 0.66 | R1471: 7.29 | S1471: 1625
A1472: lynnme0925@yahoo.com | B1472: lynn | C1472: melander | D1472: Mount Laurel | E1472: NJ | F1472: first student | G1472: Campaign_18 | H1472: TikTok Ads | I1472: 2024-01-04 | J1472: 400 | K1472: 1414 | L1472: 62 | M1472: 2 | N1472: 37.77 | O1472: 105.77 | P1472: 4.38 | Q1472: 0.61 | R1472: 18.89 | S1472: 1500
A1473: renzofj21@yahoo.com | B1473: lorenzo | C1473: jackson | D1473: Jacksonville | E1473: FL | F1473: chilis | G1473: Campaign_10 | H1473: TikTok Ads | I1473: 2024-01-17 | J1473: 500 | K1473: 2245 | L1473: 94 | M1473: 4 | N1473: 65.7 | O1473: 166.39 | P1473: 4.19 | Q1473: 0.7 | R1473: 16.42 | S1473: 4200
A1474: torresyz1@yahoo.com | B1474: ofelia | C1474: rangel | D1474: Battle Creek | E1474: MI | F1474: battle creek public | G1474: Campaign_5 | H1474: TikTok Ads | I1474: 2024-01-03 | J1474: 300 | K1474: 629 | L1474: 25 | M1474: 0 | N1474: 11.43 | O1474: 0 | P1474: 3.97 | Q1474: 0.46 | R1474: 0 | S1474: 3000
A1475: glowharris@yahoo.com | B1475: glorietta | C1475: jefferson | D1475: Grand Prairie | E1475: TX | F1475: dallas va medical ce | G1475: Campaign_19 | H1475: TikTok Ads | I1475: 2024-01-24 | J1475: 500 | K1475: 2468 | L1475: 101 | M1475: 9 | N1475: 43.49 | O1475: 655.02 | P1475: 4.09 | Q1475: 0.43 | R1475: 4.83 | S1475: 2750
A1476: lakeshacuffee@yahoo.com | B1476: lakesha | C1476: cuffee | D1476: Portsmouth | E1476: VA | F1476: marriott hotel | G1476: Campaign_20 | H1476: TikTok Ads | I1476: 2024-01-20 | J1476: 500 | K1476: 1269 | L1476: 26 | M1476: 0 | N1476: 15.83 | O1476: 0 | P1476: 2.05 | Q1476: 0.61 | R1476: 0 | S1476: 1600
A1477: sweetnative72@yahoo.com | B1477: adrienne | C1477: white bull | D1477: Ogden | E1477: UT | F1477: weber human services | G1477: Campaign_18 | H1477: TikTok Ads | I1477: 2024-01-10 | J1477: 700 | K1477: 692 | L1477: 21 | M1477: 0 | N1477: 10.95 | O1477: 0 | P1477: 3.03 | Q1477: 0.52 | R1477: 0 | S1477: 1500
... A1732: davidreiter@yahoo.com | B1732: david | C1732: reiter | D1732: Bridgeport | E1732: TX | F1732: club wholesale | G1732: Campaign_14 | H1732: TikTok Ads | I1732: 2024-01-29 | J1732: 1000 | K1732: 2245 | L1732: 94 | M1732: 0 | N1732: 38.64 | O1732: 0 | P1732: 4.19 | Q1732: 0.41 | R1732: 0 | S1732: 3800
A1733: cmelliott54@yahoo.com | B1733: michael | C1733: elliott | D1733: High Point | E1733: NC | F1733: 0 | G1733: Campaign_13 | H1733: TikTok Ads | I1733: 2024-01-16 | J1733: 600 | K1733: 1528 | L1733: 54 | M1733: 5 | N1733: 40.66 | O1733: 352.21 | P1733: 3.53 | Q1733: 0.75 | R1733: 8.13 | S1733: 3000
A1734: davidwarren@hotmail.com | B1734: david | C1734: warren | D1734: Riverside | E1734: CA | F1734: wetson's | G1734: Campaign_13 | H1734: TikTok Ads | I1734: 2024-01-18 | J1734: 600 | K1734: 684 | L1734: 28 | M1734: 0 | N1734: 22.42 | O1734: 0 | P1734: 4.09 | Q1734: 0.8 | R1734: 0 | S1734: 2400
A1735: charmainewilkins@hotmail.com | B1735: charmaine | C1735: wilkins | D1735: Bowling Green | E1735: VA | F1735: pediatric connection | G1735: Campaign_10 | H1735: TikTok Ads | I1735: 2024-01-31 | J1735: 800 | K1735: 2074 | L1735: 42 | M1735: 1 | N1735: 24.65 | O1735: 35.09 | P1735: 2.03 | Q1735: 0.59 | R1735: 24.65 | S1735: 3300
A1736: fboehm72@gmail.com | B1736: fred | C1736: boehm | D1736: New Port Rich | E1736: FL | F1736: certex | G1736: Campaign_14 | H1736: TikTok Ads | I1736: 2024-01-01 | J1736: 200 | K1736: 1743 | L1736: 40 | M1736: 0 | N1736: 18.31 | O1736: 0 | P1736: 2.29 | Q1736: 0.46 | R1736: 0 | S1736: 2600
A1737: india.woods@hotmail.com | B1737: india | C1737: woods | D1737: Saint Louis | E1737: MO | F1737: medical assistant | G1737: Campaign_15 | H1737: TikTok Ads | I1737: 2024-01-20 | J1737: 100 | K1737: 2443 | L1737: 94 | M1737: 9 | N1737: 63.58 | O1737: 463.35 | P1737: 3.85 | Q1737: 0.68 | R1737: 7.06 | S1737: 5000
A1738: johnny.ohrenstein@gmail.com | B1738: johnny | C1738: ohrenstein | D1738: Griffin | E1738: GA | F1738: legacy ford | G1738: Campaign_13 | H1738: TikTok Ads | I1738: 2024-01-08 | J1738: 500 | K1738: 1160 | L1738: 27 | M1738: 2 | N1738: 11.05 | O1738: 91.15 | P1738: 2.33 | Q1738: 0.41 | R1738: 5.52 | S1738: 1700
...
